Workbook
Name arc_fem: RanksChart!$CN$1:$CO$77
Name arc_masc: RanksChart!$AX$1:$AY$90
Name bad_fem: RanksChart!$BM$1:$BN$23
Name bad_masc: RanksChart!$W$1:$X$23
Name bal_fem: RanksChart!$CH$1:$CI$17
Name bal_masc: RanksChart!$AR$1:$AS$18
Name bas_fem: RanksChart!$BG$1:$BH$121
Name bas_masc: RanksChart!$Q$1:$R$160
Name bes_fem: RanksChart!$BJ$1:$BK$30
Name bes_masc: RanksChart!$T$1:$U$84
Name cur_fem: RanksChart!$BP$1:$BQ$48
Name cur_masc: RanksChart!$Z$1:$AA$62
Name esg_fem: RanksChart!$CQ$1:$CR$59
Name esg_masc: RanksChart!$BA$1:$BB$74
Name fts_fem: RanksChart!$K$1:$L$92
Name fts_masc: RanksChart!$H$1:$I$140
Name fut_fem: RanksChart!$E$1:$F$199
Name fut_masc: RanksChart!$B$1:$C$211
Name hck_fem: RanksChart!$CK$1:$CL$84
Name hck_masc: RanksChart!$AU$1:$AV$101
Name national_teams: NationalTeams!$B$3:$C$448
Name rug_fem: RanksChart!$BV$1:$BW$69
Name rug_masc: RanksChart!$AF$1:$AG$114
Name sqs_fem: RanksChart!$BY$1:$BZ$19
Name sqs_masc: RanksChart!$AI$1:$AJ$23
Name tem_fem: RanksChart!$CE$1:$CF$61
Name tem_masc: RanksChart!$AO$1:$AP$67
Name ten_fem: RanksChart!$BS$1:$BT$48
Name ten_masc: RanksChart!$AC$1:$AD$49
Name vlp_fem: RanksChart!$CB$1:$CC$53
Name vlp_masc: RanksChart!$AL$1:$AM$59
Name vol_fem: RanksChart!$BD$1:$BE$89
Name vol_masc: RanksChart!$N$1:$O$101

Sheet NationalTeams
B1: NationalTeams | S1: INSERT INTO | T1: VALUES | U1: ( | V1: ) | W1: " | X1: ' | Y1: , | Z1: ;
B2: team_id | C2: team_name | E2: team_type | F2: rank | I2: E:\imagenes | J2: region | K2: team_region_id | L2: ruta_b | M2: team_flag | N2: ruta_e | O2: team_shield | P2: country | Q2: ol_country_id | S2: pg_read_binary_file
B3: 1 | C3: Afganistan | E3: M | G3: 52 | H3: 56 | I3: 56 | J3: Asia | K3: =INDEX(TeamRegion!B:B,MATCH(J3,TeamRegion!C:C,0)) -> 2 | L3: \banderas\afganistan.jpg | M3: =_xlfn.CONCAT($I$2,L3) -> E:\imagenes\banderas\afganistan.jpg | N3: \escudos\afganistan.png | O3: =_xlfn.CONCAT($I$2,N3) -> E:\imagenes\escudos\afganistan.png | P3: Dinazor | Q3: =INDEX(PlayerCountry!B:B,MATCH(P3,PlayerCountry!C:C,0)) -> 2 | S3: =_xlfn.CONCAT($S$1,$W$1,$B$1,$W$1," ",$U$1,$C$2,$Y$1,$E$2,$Y$1,$K$2,$Y$1,$M$2,$Y$1,$O$2,$Y$1,$Q$2,$V$1,$T$1,$U$1,$X$1,C3,$X$1,$Y$1,$X$1,E3,$X$1,$Y$1,K3,$Y$1,$S$2,$U$1,$X$1,M3,$X$1,$V$1,$Y$1,$S$2,$U$1,$X$1,O3,$X$1,$V$1,$Y$1,Q3,$V$1,$Z$1) -> INSERT INTO "NationalTeams" (team_name,team_type,team_region_id,team_flag,team_shield,ol_country_id) VALUES ('Afganistan','M',2,pg_read_binary_file('E:\imagenes\banderas\afganistan.jpg'),pg_read_binary_file('E:\imagenes\escudos\afganistan.png'),2);
B4: 2 | C4: Africa Stars | E4: M | G4: 75 | H4: 71 | I4: 74 | J4: Africa | K4: =INDEX(TeamRegion!B:B,MATCH(J4,TeamRegion!C:C,0)) -> 1 | L4: \banderas\africa stars.png | M4: =_xlfn.CONCAT($I$2,L4) -> E:\imagenes\banderas\africa stars.png | N4: \escudos\africa stars.png | O4: =_xlfn.CONCAT($I$2,N4) -> E:\imagenes\escudos\africa stars.png | P4: Igra | Q4: =INDEX(PlayerCountry!B:B,MATCH(P4,PlayerCountry!C:C,0)) -> 3 | S4: =_xlfn.CONCAT($S$1,$W$1,$B$1,$W$1," ",$U$1,$C$2,$Y$1,$E$2,$Y$1,$K$2,$Y$1,$M$2,$Y$1,$O$2,$Y$1,$Q$2,$V$1,$T$1,$U$1,$X$1,C4,$X$1,$Y$1,$X$1,E4,$X$1,$Y$1,K4,$Y$1,$S$2,$U$1,$X$1,M4,$X$1,$V$1,$Y$1,$S$2,$U$1,$X$1,O4,$X$1,$V$1,$Y$1,Q4,$V$1,$Z$1) -> INSERT INTO "NationalTeams" (team_name,team_type,team_region_id,team_flag,team_shield,ol_country_id) VALUES ('Africa Stars','M',1,pg_read_binary_file('E:\imagenes\banderas\africa stars.png'),pg_read_binary_file('E:\imagenes\escudos\africa stars.png'),3);
B5: 3 | C5: Albania | E5: M | G5: 75 | H5: 66 | I5: 65 | J5: Europa | K5: =INDEX(TeamRegion!B:B,MATCH(J5,TeamRegion!C:C,0)) -> 4 | L5: \banderas\albania.jpg | M5: =_xlfn.CONCAT($I$2,L5) -> E:\imagenes\banderas\albania.jpg | N5: \escudos\albania.png | O5: =_xlfn.CONCAT($I$2,N5) -> E:\imagenes\escudos\albania.png | P5: Dinazor | Q5: =INDEX(PlayerCountry!B:B,MATCH(P5,PlayerCountry!C:C,0)) -> 2 | S5: =_xlfn.CONCAT($S$1,$W$1,$B$1,$W$1," ",$U$1,$C$2,$Y$1,$E$2,$Y$1,$K$2,$Y$1,$M$2,$Y$1,$O$2,$Y$1,$Q$2,$V$1,$T$1,$U$1,$X$1,C5,$X$1,$Y$1,$X$1,E5,$X$1,$Y$1,K5,$Y$1,$S$2,$U$1,$X$1,M5,$X$1,$V$1,$Y$1,$S$2,$U$1,$X$1,O5,$X$1,$V$1,$Y$1,Q5,$V$1,$Z$1) -> INSERT INTO "NationalTeams" (team_name,team_type,team_region_id,team_flag,team_shield,ol_country_id) VALUES ('Albania','M',4,pg_read_binary_file('E:\imagenes\banderas\albania.jpg'),pg_read_binary_file('E:\imagenes\escudos\albania.png'),2);
B6: 4 | C6: Alemania | E6: M | G6: 85 | H6: 87 | I6: 84 | J6: Europa | K6: =INDEX(TeamRegion!B:B,MATCH(J6,TeamRegion!C:C,0)) -> 4 | L6: \banderas\alemania.jpg | M6: =_xlfn.CONCAT($I$2,L6) -> E:\imagenes\banderas\alemania.jpg | N6: \escudos\alemania.png | O6: =_xlfn.CONCAT($I$2,N6) -> E:\imagenes\escudos\alemania.png | P6: Dinazor | Q6: =INDEX(PlayerCountry!B:B,MATCH(P6,PlayerCountry!C:C,0)) -> 2 | S6: =_xlfn.CONCAT($S$1,$W$1,$B$1,$W$1," ",$U$1,$C$2,$Y$1,$E$2,$Y$1,$K$2,$Y$1,$M$2,$Y$1,$O$2,$Y$1,$Q$2,$V$1,$T$1,$U$1,$X$1,C6,$X$1,$Y$1,$X$1,E6,$X$1,$Y$1,K6,$Y$1,$S$2,$U$1,$X$1,M6,$X$1,$V$1,$Y$1,$S$2,$U$1,$X$1,O6,$X$1,$V$1,$Y$1,Q6,$V$1,$Z$1) -> INSERT INTO "NationalTeams" (team_name,team_type,team_region_id,team_flag,team_shield,ol_country_id) VALUES ('Alemania','M',4,pg_read_binary_file('E:\imagenes\banderas\alemania.jpg'),pg_read_binary_file('E:\imagenes\escudos\alemania.png'),2);
B7: 5 | C7: America Stars | E7: M | G7: 76 | H7: 77 | I7: 78 | J7: America | K7: =INDEX(TeamRegion!B:B,MATCH(J7,TeamRegion!C:C,0)) -> 3 | L7: \banderas\america stars.png | M7: =_xlfn.CONCAT($I$2,L7) -> E:\imagenes\banderas\america stars.png | N7: \escudos\america stars.png | O7: =_xlfn.CONCAT($I$2,N7) -> E:\imagenes\escudos\america stars.png | P7: Dinazor | Q7: =INDEX(PlayerCountry!B:B,MATCH(P7,PlayerCountry!C:C,0)) -> 2 | S7: =_xlfn.CONCAT($S$1,$W$1,$B$1,$W$1," ",$U$1,$C$2,$Y$1,$E$2,$Y$1,$K$2,$Y$1,$M$2,$Y$1,$O$2,$Y$1,$Q$2,$V$1,$T$1,$U$1,$X$1,C7,$X$1,$Y$1,$X$1,E7,$X$1,$Y$1,K7,$Y$1,$S$2,$U$1,$X$1,M7,$X$1,$V$1,$Y$1,$S$2,$U$1,$X$1,O7,$X$1,$V$1,$Y$1,Q7,$V$1,$Z$1) -> INSERT INTO "NationalTeams" (team_name,team_type,team_region_id,team_flag,team_shield,ol_country_id) VALUES ('America Stars','M',3,pg_read_binary_file('E:\imagenes\banderas\america stars.png'),pg_read_binary_file('E:\imagenes\escudos\america stars.png'),2);
B8: 6 | C8: Andorra | E8: M | G8: 56 | H8: 53 | I8: 54 | J8: Europa | K8: =INDEX(TeamRegion!B:B,MATCH(J8,TeamRegion!C:C,0)) -> 4 | L8: \banderas\andorra.jpg | M8: =_xlfn.CONCAT($I$2,L8) -> E:\imagenes\banderas\andorra.jpg | N8: \escudos\andorra.png | O8: =_xlfn.CONCAT($I$2,N8) -> E:\imagenes\escudos\andorra.png | P8: Bollstam | Q8: =INDEX(PlayerCountry!B:B,MATCH(P8,PlayerCountry!C:C,0)) -> 1 | S8: =_xlfn.CONCAT($S$1,$W$1,$B$1,$W$1," ",$U$1,$C$2,$Y$1,$E$2,$Y$1,$K$2,$Y$1,$M$2,$Y$1,$O$2,$Y$1,$Q$2,$V$1,$T$1,$U$1,$X$1,C8,$X$1,$Y$1,$X$1,E8,$X$1,$Y$1,K8,$Y$1,$S$2,$U$1,$X$1,M8,$X$1,$V$1,$Y$1,$S$2,$U$1,$X$1,O8,$X$1,$V$1,$Y$1,Q8,$V$1,$Z$1) -> INSERT INTO "NationalTeams" (team_name,team_type,team_region_id,team_flag,team_shield,ol_country_id) VALUES ('Andorra','M',4,pg_read_binary_file('E:\imagenes\banderas\andorra.jpg'),pg_read_binary_file('E:\imagenes\escudos\andorra.png'),1);
B9: 7 | C9: Angola | E9: M | G9: 64 | H9: 61 | I9: 62 | J9: Africa | K9: =INDEX(TeamRegion!B:B,MATCH(J9,TeamRegion!C:C,0)) -> 1 | L9: \banderas\angola.jpg | M9: =_xlfn.CONCAT($I$2,L9) -> E:\imagenes\banderas\angola.jpg | N9: \escudos\angola.png | O9: =_xlfn.CONCAT($I$2,N9) -> E:\imagenes\escudos\angola.png | P9: Silnik | Q9: =INDEX(PlayerCountry!B:B,MATCH(P9,PlayerCountry!C:C,0)) -> 8 | S9: =_xlfn.CONCAT($S$1,$W$1,$B$1,$W$1," ",$U$1,$C$2,$Y$1,$E$2,$Y$1,$K$2,$Y$1,$M$2,$Y$1,$O$2,$Y$1,$Q$2,$V$1,$T$1,$U$1,$X$1,C9,$X$1,$Y$1,$X$1,E9,$X$1,$Y$1,K9,$Y$1,$S$2,$U$1,$X$1,M9,$X$1,$V$1,$Y$1,$S$2,$U$1,$X$1,O9,$X$1,$V$1,$Y$1,Q9,$V$1,$Z$1) -> INSERT INTO "NationalTeams" (team_name,team_type,team_region_id,team_flag,team_shield,ol_country_id) VALUES ('Angola','M',1,pg_read_binary_file('E:\imagenes\banderas\angola.jpg'),pg_read_binary_file('E:\imagenes\escudos\angola.png'),8);
B10: 8 | C10: Anguila | E10: M | G10: 46 | H10: 47 | I10: 46 | J10: America | K10: =INDEX(TeamRegion!B:B,MATCH(J10,TeamRegion!C:C,0)) -> 3 | L10: \banderas\anguila.png | M10: =_xlfn.CONCAT($I$2,L10) -> E:\imagenes\banderas\anguila.png | N10: \escudos\anguila.png | O10: =_xlfn.CONCAT($I$2,N10) -> E:\imagenes\escudos\anguila.png | P10: Pokemonia | Q10: =INDEX(PlayerCountry!B:B,MATCH(P10,PlayerCountry!C:C,0)) -> 5 | S10: =_xlfn.CONCAT($S$1,$W$1,$B$1,$W$1," ",$U$1,$C$2,$Y$1,$E$2,$Y$1,$K$2,$Y$1,$M$2,$Y$1,$O$2,$Y$1,$Q$2,$V$1,$T$1,$U$1,$X$1,C10,$X$1,$Y$1,$X$1,E10,$X$1,$Y$1,K10,$Y$1,$S$2,$U$1,$X$1,M10,$X$1,$V$1,$Y$1,$S$2,$U$1,$X$1,O10,$X$1,$V$1,$Y$1,Q10,$V$1,$Z$1) -> INSERT INTO "NationalTeams" (team_name,team_type,team_region_id,team_flag,team_shield,ol_country_id) VALUES ('Anguila','M',3,pg_read_binary_file('E:\imagenes\banderas\anguila.png'),pg_read_binary_file('E:\imagenes\escudos\anguila.png'),5);
B11: 9 | C11: Antigua y Barbuda | E11: M | G11: 58 | H11: 58 | I11: 59 | J11: America | K11: =INDEX(TeamRegion!B:B,MATCH(J11,TeamRegion!C:C,0)) -> 3 | L11: \banderas\antigua.png | M11: =_xlfn.CONCAT($I$2,L11) -> E:\imagenes\banderas\antigua.png | N11: \escudos\antigua.png | O11: =_xlfn.CONCAT($I$2,N11) -> E:\imagenes\escudos\antigua.png | P11: Igra | Q11: =INDEX(PlayerCountry!B:B,MATCH(P11,PlayerCountry!C:C,0)) -> 3 | S11: =_xlfn.CONCAT($S$1,$W$1,$B$1,$W$1," ",$U$1,$C$2,$Y$1,$E$2,$Y$1,$K$2,$Y$1,$M$2,$Y$1,$O$2,$Y$1,$Q$2,$V$1,$T$1,$U$1,$X$1,C11,$X$1,$Y$1,$X$1,E11,$X$1,$Y$1,K11,$Y$1,$S$2,$U$1,$X$1,M11,$X$1,$V$1,$Y$1,$S$2,$U$1,$X$1,O11,$X$1,$V$1,$Y$1,Q11,$V$1,$Z$1) -> INSERT INTO "NationalTeams" (team_name,team_type,team_region_id,team_flag,team_shield,ol_country_id) VALUES ('Antigua y Barbuda','M',3,pg_read_binary_file('E:\imagenes\banderas\antigua.png'),pg_read_binary_file('E:\imagenes\escudos\antigua.png'),3);
B12: 10 | C12: Arabia Saudita | E12: M | G12: 67 | H12: 68 | I12: 72 | J12: Asia | K12: =INDEX(TeamRegion!B:B,MATCH(J12,TeamRegion!C:C,0)) -> 2 | L12: \banderas\arabia saudita.jpg | M12: =_xlfn.CONCAT($I$2,L12) -> E:\imagenes\banderas\arabia saudita.jpg | N12: \escudos\arabia saudita.png | O12: =_xlfn.CONCAT($I$2,N12) -> E:\imagenes\escudos\arabia saudita.png | P12: Raimei | Q12: =INDEX(PlayerCountry!B:B,MATCH(P12,PlayerCountry!C:C,0)) -> 6 | S12: =_xlfn.CONCAT($S$1,$W$1,$B$1,$W$1," ",$U$1,$C$2,$Y$1,$E$2,$Y$1,$K$2,$Y$1,$M$2,$Y$1,$O$2,$Y$1,$Q$2,$V$1,$T$1,$U$1,$X$1,C12,$X$1,$Y$1,$X$1,E12,$X$1,$Y$1,K12,$Y$1,$S$2,$U$1,$X$1,M12,$X$1,$V$1,$Y$1,$S$2,$U$1,$X$1,O12,$X$1,$V$1,$Y$1,Q12,$V$1,$Z$1) -> INSERT INTO "NationalTeams" (team_name,team_type,team_region_id,team_flag,team_shield,ol_country_id) VALUES ('Arabia Saudita','M',2,pg_read_binary_file('E:\imagenes\banderas\arabia saudita.jpg'),pg_read_binary_file('E:\imagenes\escudos\arabia saudita.png'),6);
B13: 11 | C13: Argelia | E13: M | G13: 73 | H13: 75 | I13: 82 | J13: Africa | K13: =INDEX(TeamRegion!B:B,MATCH(J13,TeamRegion!C:C,0)) -> 1 | L13: \banderas\argelia.jpg | M13: =_xlfn.CONCAT($I$2,L13) -> E:\imagenes\banderas\argelia.jpg | N13: \escudos\argelia.png | O13: =_xlfn.CONCAT($I$2,N13) -> E:\imagenes\escudos\argelia.png | P13: Dinazor | Q13: =INDEX(PlayerCountry!B:B,MATCH(P13,PlayerCountry!C:C,0)) -> 2 | S13: =_xlfn.CONCAT($S$1,$W$1,$B$1,$W$1," ",$U$1,$C$2,$Y$1,$E$2,$Y$1,$K$2,$Y$1,$M$2,$Y$1,$O$2,$Y$1,$Q$2,$V$1,$T$1,$U$1,$X$1,C13,$X$1,$Y$1,$X$1,E13,$X$1,$Y$1,K13,$Y$1,$S$2,$U$1,$X$1,M13,$X$1,$V$1,$Y$1,$S$2,$U$1,$X$1,O13,$X$1,$V$1,$Y$1,Q13,$V$1,$Z$1) -> INSERT INTO "NationalTeams" (team_name,team_type,team_region_id,team_flag,team_shield,ol_country_id) VALUES ('Argelia','M',1,pg_read_binary_file('E:\imagenes\banderas\argelia.jpg'),pg_read_binary_file('E:\imagenes\escudos\argelia.png'),2);
B14: 12 | C14: Argentina | E14: M | G14: 81 | H14: 83 | I14: 91 | J14: America | K14: =INDEX(TeamRegion!B:B,MATCH(J14,TeamRegion!C:C,0)) -> 3 | L14: \banderas\argentina.jpg | M14: =_xlfn.CONCAT($I$2,L14) -> E:\imagenes\banderas\argentina.jpg | N14: \escudos\argentina.png | O14: =_xlfn.CONCAT($I$2,N14) -> E:\imagenes\escudos\argentina.png | P14: Bollstam | Q14: =INDEX(PlayerCountry!B:B,MATCH(P14,PlayerCountry!C:C,0)) -> 1 | S14: =_xlfn.CONCAT($S$1,$W$1,$B$1,$W$1," ",$U$1,$C$2,$Y$1,$E$2,$Y$1,$K$2,$Y$1,$M$2,$Y$1,$O$2,$Y$1,$Q$2,$V$1,$T$1,$U$1,$X$1,C14,$X$1,$Y$1,$X$1,E14,$X$1,$Y$1,K14,$Y$1,$S$2,$U$1,$X$1,M14,$X$1,$V$1,$Y$1,$S$2,$U$1,$X$1,O14,$X$1,$V$1,$Y$1,Q14,$V$1,$Z$1) -> INSERT INTO "NationalTeams" (team_name,team_type,team_region_id,team_flag,team_shield,ol_country_id) VALUES ('Argentina','M',3,pg_read_binary_file('E:\imagenes\banderas\argentina.jpg'),pg_read_binary_file('E:\imagenes\escudos\argentina.png'),1);
... B448: 446 | C448: Zimbaue Fem | E448: F | G448: 49 | H448: 49 | I448: 49 | J448: Africa | K448: =INDEX(TeamRegion!B:B,MATCH(J448,TeamRegion!C:C,0)) -> 1 | L448: \banderas\zimbaue.jpg | M448: =_xlfn.CONCAT($I$2,L448) -> E:\imagenes\banderas\zimbaue.jpg | N448: \escudos\zimbaue.png | O448: =_xlfn.CONCAT($I$2,N448) -> E:\imagenes\escudos\zimbaue.png | P448: Lordena | Q448: =INDEX(PlayerCountry!B:B,MATCH(P448,PlayerCountry!C:C,0)) -> 4 | S448: =_xlfn.CONCAT($S$1,$W$1,$B$1,$W$1," ",$U$1,$C$2,$Y$1,$E$2,$Y$1,$K$2,$Y$1,$M$2,$Y$1,$O$2,$Y$1,$Q$2,$V$1,$T$1,$U$1,$X$1,C448,$X$1,$Y$1,$X$1,E448,$X$1,$Y$1,K448,$Y$1,$S$2,$U$1,$X$1,M448,$X$1,$V$1,$Y$1,$S$2,$U$1,$X$1,O448,$X$1,$V$1,$Y$1,Q448,$V$1,$Z$1) -> INSERT INTO "NationalTeams" (team_name,team_type,team_region_id,team_flag,team_shield,ol_country_id) VALUES ('Zimbaue Fem','F',1,pg_read_binary_file('E:\imagenes\banderas\zimbaue.jpg'),pg_read_binary_file('E:\imagenes\escudos\zimbaue.png'),4);

Sheet OlympicPlayers
A1: E:\imagenes | B1: OlympicPlayers | L1: INSERT INTO | M1: VALUES | N1: ( | O1: ) | P1: " | Q1: ' | R1: , | S1: ;
B2: ol_player_id | C2: ol_player_name | D2: ol_player_value | E2: ruta | F2: ol_player_image | G2: country | H2: ol_country_id | I2: sport | J2: team_sport_id | L2: pg_read_binary_file
B3: 1 | C3: Jim Rivers | D3: 1 | E3: \personajes\jim_rivers.png | F3: =_xlfn.CONCAT($A$1,E3) -> E:\imagenes\personajes\jim_rivers.png | G3: Lordena | H3: =INDEX(PlayerCountry!B:B,MATCH(G3,PlayerCountry!C:C,0)) -> 4 | I3: Excitebike | J3: =INDEX(TeamSports!B:B,MATCH(I3,TeamSports!C:C,0)) -> 40 | L3: =_xlfn.CONCAT($L$1,$P$1,$B$1,$P$1," ",$N$1,$C$2,$R$1,$D$2,$R$1,$F$2,$R$1,$H$2,$R$1,$J$2,$O$1,$M$1,$N$1,$Q$1,C3,$Q$1,$R$1,D3,$R$1,$L$2,$N$1,$Q$1,F3,$Q$1,$O$1,$R$1,H3,$R$1,J3,$O$1,$S$1) -> INSERT INTO "OlympicPlayers" (ol_player_name,ol_player_value,ol_player_image,ol_country_id,team_sport_id) VALUES ('Jim Rivers',1,pg_read_binary_file('E:\imagenes\personajes\jim_rivers.png'),4,40);
B4: 2 | C4: Sarah Hill | D4: 1 | E4: \personajes\sarah_hill.png | F4: =_xlfn.CONCAT($A$1,E4) -> E:\imagenes\personajes\sarah_hill.png | G4: Bollstam | H4: =INDEX(PlayerCountry!B:B,MATCH(G4,PlayerCountry!C:C,0)) -> 1 | I4: Excitebike | J4: =INDEX(TeamSports!B:B,MATCH(I4,TeamSports!C:C,0)) -> 40 | L4: =_xlfn.CONCAT($L$1,$P$1,$B$1,$P$1," ",$N$1,$C$2,$R$1,$D$2,$R$1,$F$2,$R$1,$H$2,$R$1,$J$2,$O$1,$M$1,$N$1,$Q$1,C4,$Q$1,$R$1,D4,$R$1,$L$2,$N$1,$Q$1,F4,$Q$1,$O$1,$R$1,H4,$R$1,J4,$O$1,$S$1) -> INSERT INTO "OlympicPlayers" (ol_player_name,ol_player_value,ol_player_image,ol_country_id,team_sport_id) VALUES ('Sarah Hill',1,pg_read_binary_file('E:\imagenes\personajes\sarah_hill.png'),1,40);
B5: 3 | C5: Bobby Malone | D5: 1 | E5: \personajes\bobby_malone.png | F5: =_xlfn.CONCAT($A$1,E5) -> E:\imagenes\personajes\bobby_malone.png | G5: Dinazor | H5: =INDEX(PlayerCountry!B:B,MATCH(G5,PlayerCountry!C:C,0)) -> 2 | I5: Excitebike | J5: =INDEX(TeamSports!B:B,MATCH(I5,TeamSports!C:C,0)) -> 40 | L5: =_xlfn.CONCAT($L$1,$P$1,$B$1,$P$1," ",$N$1,$C$2,$R$1,$D$2,$R$1,$F$2,$R$1,$H$2,$R$1,$J$2,$O$1,$M$1,$N$1,$Q$1,C5,$Q$1,$R$1,D5,$R$1,$L$2,$N$1,$Q$1,F5,$Q$1,$O$1,$R$1,H5,$R$1,J5,$O$1,$S$1) -> INSERT INTO "OlympicPlayers" (ol_player_name,ol_player_value,ol_player_image,ol_country_id,team_sport_id) VALUES ('Bobby Malone',1,pg_read_binary_file('E:\imagenes\personajes\bobby_malone.png'),2,40);
B6: 4 | C6: Vicky Steele | D6: 1 | E6: \personajes\vicky_steele.png | F6: =_xlfn.CONCAT($A$1,E6) -> E:\imagenes\personajes\vicky_steele.png | G6: Schattenmond | H6: =INDEX(PlayerCountry!B:B,MATCH(G6,PlayerCountry!C:C,0)) -> 7 | I6: Excitebike | J6: =INDEX(TeamSports!B:B,MATCH(I6,TeamSports!C:C,0)) -> 40 | L6: =_xlfn.CONCAT($L$1,$P$1,$B$1,$P$1," ",$N$1,$C$2,$R$1,$D$2,$R$1,$F$2,$R$1,$H$2,$R$1,$J$2,$O$1,$M$1,$N$1,$Q$1,C6,$Q$1,$R$1,D6,$R$1,$L$2,$N$1,$Q$1,F6,$Q$1,$O$1,$R$1,H6,$R$1,J6,$O$1,$S$1) -> INSERT INTO "OlympicPlayers" (ol_player_name,ol_player_value,ol_player_image,ol_country_id,team_sport_id) VALUES ('Vicky Steele',1,pg_read_binary_file('E:\imagenes\personajes\vicky_steele.png'),7,40);
B7: 5 | C7: Ricky Stern | D7: 1 | E7: \personajes\ricky_stern.png | F7: =_xlfn.CONCAT($A$1,E7) -> E:\imagenes\personajes\ricky_stern.png | G7: Dinazor | H7: =INDEX(PlayerCountry!B:B,MATCH(G7,PlayerCountry!C:C,0)) -> 2 | I7: Excitebike | J7: =INDEX(TeamSports!B:B,MATCH(I7,TeamSports!C:C,0)) -> 40 | L7: =_xlfn.CONCAT($L$1,$P$1,$B$1,$P$1," ",$N$1,$C$2,$R$1,$D$2,$R$1,$F$2,$R$1,$H$2,$R$1,$J$2,$O$1,$M$1,$N$1,$Q$1,C7,$Q$1,$R$1,D7,$R$1,$L$2,$N$1,$Q$1,F7,$Q$1,$O$1,$R$1,H7,$R$1,J7,$O$1,$S$1) -> INSERT INTO "OlympicPlayers" (ol_player_name,ol_player_value,ol_player_image,ol_country_id,team_sport_id) VALUES ('Ricky Stern',1,pg_read_binary_file('E:\imagenes\personajes\ricky_stern.png'),2,40);
B8: 6 | C8: Nigel York | D8: 1 | E8: \personajes\nigel_york.png | F8: =_xlfn.CONCAT($A$1,E8) -> E:\imagenes\personajes\nigel_york.png | G8: Silnik | H8: =INDEX(PlayerCountry!B:B,MATCH(G8,PlayerCountry!C:C,0)) -> 8 | I8: Excitebike | J8: =INDEX(TeamSports!B:B,MATCH(I8,TeamSports!C:C,0)) -> 40 | L8: =_xlfn.CONCAT($L$1,$P$1,$B$1,$P$1," ",$N$1,$C$2,$R$1,$D$2,$R$1,$F$2,$R$1,$H$2,$R$1,$J$2,$O$1,$M$1,$N$1,$Q$1,C8,$Q$1,$R$1,D8,$R$1,$L$2,$N$1,$Q$1,F8,$Q$1,$O$1,$R$1,H8,$R$1,J8,$O$1,$S$1) -> INSERT INTO "OlympicPlayers" (ol_player_name,ol_player_value,ol_player_image,ol_country_id,team_sport_id) VALUES ('Nigel York',1,pg_read_binary_file('E:\imagenes\personajes\nigel_york.png'),8,40);
B9: 7 | C9: Juan Pablo Montoya | D9: 1 | E9: =_xlfn.CONCAT("\personajes\",SUBSTITUTE(LOWER(C9)," ","_"),".png") -> \personajes\juan_pablo_montoya.png | F9: =_xlfn.CONCAT($A$1,E9) -> E:\imagenes\personajes\juan_pablo_montoya.png | G9: Bollstam | H9: =INDEX(PlayerCountry!B:B,MATCH(G9,PlayerCountry!C:C,0)) -> 1 | I9: Formula1 | J9: =INDEX(TeamSports!B:B,MATCH(I9,TeamSports!C:C,0)) -> 41 | L9: =_xlfn.CONCAT($L$1,$P$1,$B$1,$P$1," ",$N$1,$C$2,$R$1,$D$2,$R$1,$F$2,$R$1,$H$2,$R$1,$J$2,$O$1,$M$1,$N$1,$Q$1,C9,$Q$1,$R$1,D9,$R$1,$L$2,$N$1,$Q$1,F9,$Q$1,$O$1,$R$1,H9,$R$1,J9,$O$1,$S$1) -> INSERT INTO "OlympicPlayers" (ol_player_name,ol_player_value,ol_player_image,ol_country_id,team_sport_id) VALUES ('Juan Pablo Montoya',1,pg_read_binary_file('E:\imagenes\personajes\juan_pablo_montoya.png'),1,41);
B10: 8 | C10: Heinz Harald Frentzen | D10: 1 | E10: =_xlfn.CONCAT("\personajes\",SUBSTITUTE(LOWER(C10)," ","_"),".png") -> \personajes\heinz_harald_frentzen.png | F10: =_xlfn.CONCAT($A$1,E10) -> E:\imagenes\personajes\heinz_harald_frentzen.png | G10: Dinazor | H10: =INDEX(PlayerCountry!B:B,MATCH(G10,PlayerCountry!C:C,0)) -> 2 | I10: Formula1 | J10: =INDEX(TeamSports!B:B,MATCH(I10,TeamSports!C:C,0)) -> 41 | L10: =_xlfn.CONCAT($L$1,$P$1,$B$1,$P$1," ",$N$1,$C$2,$R$1,$D$2,$R$1,$F$2,$R$1,$H$2,$R$1,$J$2,$O$1,$M$1,$N$1,$Q$1,C10,$Q$1,$R$1,D10,$R$1,$L$2,$N$1,$Q$1,F10,$Q$1,$O$1,$R$1,H10,$R$1,J10,$O$1,$S$1) -> INSERT INTO "OlympicPlayers" (ol_player_name,ol_player_value,ol_player_image,ol_country_id,team_sport_id) VALUES ('Heinz Harald Frentzen',1,pg_read_binary_file('E:\imagenes\personajes\heinz_harald_frentzen.png'),2,41);
B11: 9 | C11: Michael Schuhmacher | D11: 1 | E11: =_xlfn.CONCAT("\personajes\",SUBSTITUTE(LOWER(C11)," ","_"),".png") -> \personajes\michael_schuhmacher.png | F11: =_xlfn.CONCAT($A$1,E11) -> E:\imagenes\personajes\michael_schuhmacher.png | G11: Dinazor | H11: =INDEX(PlayerCountry!B:B,MATCH(G11,PlayerCountry!C:C,0)) -> 2 | I11: Formula1 | J11: =INDEX(TeamSports!B:B,MATCH(I11,TeamSports!C:C,0)) -> 41 | L11: =_xlfn.CONCAT($L$1,$P$1,$B$1,$P$1," ",$N$1,$C$2,$R$1,$D$2,$R$1,$F$2,$R$1,$H$2,$R$1,$J$2,$O$1,$M$1,$N$1,$Q$1,C11,$Q$1,$R$1,D11,$R$1,$L$2,$N$1,$Q$1,F11,$Q$1,$O$1,$R$1,H11,$R$1,J11,$O$1,$S$1) -> INSERT INTO "OlympicPlayers" (ol_player_name,ol_player_value,ol_player_image,ol_country_id,team_sport_id) VALUES ('Michael Schuhmacher',1,pg_read_binary_file('E:\imagenes\personajes\michael_schuhmacher.png'),2,41);
B12: 10 | C12: Gerhard Berger | D12: 1 | E12: =_xlfn.CONCAT("\personajes\",SUBSTITUTE(LOWER(C12)," ","_"),".png") -> \personajes\gerhard_berger.png | F12: =_xlfn.CONCAT($A$1,E12) -> E:\imagenes\personajes\gerhard_berger.png | G12: Igra | H12: =INDEX(PlayerCountry!B:B,MATCH(G12,PlayerCountry!C:C,0)) -> 3 | I12: Formula1 | J12: =INDEX(TeamSports!B:B,MATCH(I12,TeamSports!C:C,0)) -> 41 | L12: =_xlfn.CONCAT($L$1,$P$1,$B$1,$P$1," ",$N$1,$C$2,$R$1,$D$2,$R$1,$F$2,$R$1,$H$2,$R$1,$J$2,$O$1,$M$1,$N$1,$Q$1,C12,$Q$1,$R$1,D12,$R$1,$L$2,$N$1,$Q$1,F12,$Q$1,$O$1,$R$1,H12,$R$1,J12,$O$1,$S$1) -> INSERT INTO "OlympicPlayers" (ol_player_name,ol_player_value,ol_player_image,ol_country_id,team_sport_id) VALUES ('Gerhard Berger',1,pg_read_binary_file('E:\imagenes\personajes\gerhard_berger.png'),3,41);
B13: 11 | C13: Ralph Schuhmacher | D13: 1 | E13: =_xlfn.CONCAT("\personajes\",SUBSTITUTE(LOWER(C13)," ","_"),".png") -> \personajes\ralph_schuhmacher.png | F13: =_xlfn.CONCAT($A$1,E13) -> E:\imagenes\personajes\ralph_schuhmacher.png | G13: Dinazor | H13: =INDEX(PlayerCountry!B:B,MATCH(G13,PlayerCountry!C:C,0)) -> 2 | I13: Formula1 | J13: =INDEX(TeamSports!B:B,MATCH(I13,TeamSports!C:C,0)) -> 41 | L13: =_xlfn.CONCAT($L$1,$P$1,$B$1,$P$1," ",$N$1,$C$2,$R$1,$D$2,$R$1,$F$2,$R$1,$H$2,$R$1,$J$2,$O$1,$M$1,$N$1,$Q$1,C13,$Q$1,$R$1,D13,$R$1,$L$2,$N$1,$Q$1,F13,$Q$1,$O$1,$R$1,H13,$R$1,J13,$O$1,$S$1) -> INSERT INTO "OlympicPlayers" (ol_player_name,ol_player_value,ol_player_image,ol_country_id,team_sport_id) VALUES ('Ralph Schuhmacher',1,pg_read_binary_file('E:\imagenes\personajes\ralph_schuhmacher.png'),2,41);
B14: 12 | C14: Jean Alesi | D14: 1 | E14: =_xlfn.CONCAT("\personajes\",SUBSTITUTE(LOWER(C14)," ","_"),".png") -> \personajes\jean_alesi.png | F14: =_xlfn.CONCAT($A$1,E14) -> E:\imagenes\personajes\jean_alesi.png | G14: Lordena | H14: =INDEX(PlayerCountry!B:B,MATCH(G14,PlayerCountry!C:C,0)) -> 4 | I14: Formula1 | J14: =INDEX(TeamSports!B:B,MATCH(I14,TeamSports!C:C,0)) -> 41 | L14: =_xlfn.CONCAT($L$1,$P$1,$B$1,$P$1," ",$N$1,$C$2,$R$1,$D$2,$R$1,$F$2,$R$1,$H$2,$R$1,$J$2,$O$1,$M$1,$N$1,$Q$1,C14,$Q$1,$R$1,D14,$R$1,$L$2,$N$1,$Q$1,F14,$Q$1,$O$1,$R$1,H14,$R$1,J14,$O$1,$S$1) -> INSERT INTO "OlympicPlayers" (ol_player_name,ol_player_value,ol_player_image,ol_country_id,team_sport_id) VALUES ('Jean Alesi',1,pg_read_binary_file('E:\imagenes\personajes\jean_alesi.png'),4,41);
B15: 13 | C15: Mika Hakkinen | D15: 1 | E15: =_xlfn.CONCAT("\personajes\",SUBSTITUTE(LOWER(C15)," ","_"),".png") -> \personajes\mika_hakkinen.png | F15: =_xlfn.CONCAT($A$1,E15) -> E:\imagenes\personajes\mika_hakkinen.png | G15: Bollstam | H15: =INDEX(PlayerCountry!B:B,MATCH(G15,PlayerCountry!C:C,0)) -> 1 | I15: Formula1 | J15: =INDEX(TeamSports!B:B,MATCH(I15,TeamSports!C:C,0)) -> 41 | L15: =_xlfn.CONCAT($L$1,$P$1,$B$1,$P$1," ",$N$1,$C$2,$R$1,$D$2,$R$1,$F$2,$R$1,$H$2,$R$1,$J$2,$O$1,$M$1,$N$1,$Q$1,C15,$Q$1,$R$1,D15,$R$1,$L$2,$N$1,$Q$1,F15,$Q$1,$O$1,$R$1,H15,$R$1,J15,$O$1,$S$1) -> INSERT INTO "OlympicPlayers" (ol_player_name,ol_player_value,ol_player_image,ol_country_id,team_sport_id) VALUES ('Mika Hakkinen',1,pg_read_binary_file('E:\imagenes\personajes\mika_hakkinen.png'),1,41);
B16: 14 | C16: Damon Hill | D16: 1 | E16: =_xlfn.CONCAT("\personajes\",SUBSTITUTE(LOWER(C16)," ","_"),".png") -> \personajes\damon_hill.png | F16: =_xlfn.CONCAT($A$1,E16) -> E:\imagenes\personajes\damon_hill.png | G16: Lordena | H16: =INDEX(PlayerCountry!B:B,MATCH(G16,PlayerCountry!C:C,0)) -> 4 | I16: Formula1 | J16: =INDEX(TeamSports!B:B,MATCH(I16,TeamSports!C:C,0)) -> 41 | L16: =_xlfn.CONCAT($L$1,$P$1,$B$1,$P$1," ",$N$1,$C$2,$R$1,$D$2,$R$1,$F$2,$R$1,$H$2,$R$1,$J$2,$O$1,$M$1,$N$1,$Q$1,C16,$Q$1,$R$1,D16,$R$1,$L$2,$N$1,$Q$1,F16,$Q$1,$O$1,$R$1,H16,$R$1,J16,$O$1,$S$1) -> INSERT INTO "OlympicPlayers" (ol_player_name,ol_player_value,ol_player_image,ol_country_id,team_sport_id) VALUES ('Damon Hill',1,pg_read_binary_file('E:\imagenes\personajes\damon_hill.png'),4,41);
B17: 15 | C17: David Coulthard | D17: 1 | E17: =_xlfn.CONCAT("\personajes\",SUBSTITUTE(LOWER(C17)," ","_"),".png") -> \personajes\david_coulthard.png | F17: =_xlfn.CONCAT($A$1,E17) -> E:\imagenes\personajes\david_coulthard.png | G17: Lordena | H17: =INDEX(PlayerCountry!B:B,MATCH(G17,PlayerCountry!C:C,0)) -> 4 | I17: Formula1 | J17: =INDEX(TeamSports!B:B,MATCH(I17,TeamSports!C:C,0)) -> 41 | L17: =_xlfn.CONCAT($L$1,$P$1,$B$1,$P$1," ",$N$1,$C$2,$R$1,$D$2,$R$1,$F$2,$R$1,$H$2,$R$1,$J$2,$O$1,$M$1,$N$1,$Q$1,C17,$Q$1,$R$1,D17,$R$1,$L$2,$N$1,$Q$1,F17,$Q$1,$O$1,$R$1,H17,$R$1,J17,$O$1,$S$1) -> INSERT INTO "OlympicPlayers" (ol_player_name,ol_player_value,ol_player_image,ol_country_id,team_sport_id) VALUES ('David Coulthard',1,pg_read_binary_file('E:\imagenes\personajes\david_coulthard.png'),4,41);
B18: 16 | C18: Pedro Diniz | D18: 1 | E18: =_xlfn.CONCAT("\personajes\",SUBSTITUTE(LOWER(C18)," ","_"),".png") -> \personajes\pedro_diniz.png | F18: =_xlfn.CONCAT($A$1,E18) -> E:\imagenes\personajes\pedro_diniz.png | G18: Dinazor | H18: =INDEX(PlayerCountry!B:B,MATCH(G18,PlayerCountry!C:C,0)) -> 2 | I18: Formula1 | J18: =INDEX(TeamSports!B:B,MATCH(I18,TeamSports!C:C,0)) -> 41 | L18: =_xlfn.CONCAT($L$1,$P$1,$B$1,$P$1," ",$N$1,$C$2,$R$1,$D$2,$R$1,$F$2,$R$1,$H$2,$R$1,$J$2,$O$1,$M$1,$N$1,$Q$1,C18,$Q$1,$R$1,D18,$R$1,$L$2,$N$1,$Q$1,F18,$Q$1,$O$1,$R$1,H18,$R$1,J18,$O$1,$S$1) -> INSERT INTO "OlympicPlayers" (ol_player_name,ol_player_value,ol_player_image,ol_country_id,team_sport_id) VALUES ('Pedro Diniz',1,pg_read_binary_file('E:\imagenes\personajes\pedro_diniz.png'),2,41);
B19: 17 | C19: Giancarlo Fisichella | D19: 1 | E19: =_xlfn.CONCAT("\personajes\",SUBSTITUTE(LOWER(C19)," ","_"),".png") -> \personajes\giancarlo_fisichella.png | F19: =_xlfn.CONCAT($A$1,E19) -> E:\imagenes\personajes\giancarlo_fisichella.png | G19: Dinazor | H19: =INDEX(PlayerCountry!B:B,MATCH(G19,PlayerCountry!C:C,0)) -> 2 | I19: Formula1 | J19: =INDEX(TeamSports!B:B,MATCH(I19,TeamSports!C:C,0)) -> 41 | L19: =_xlfn.CONCAT($L$1,$P$1,$B$1,$P$1," ",$N$1,$C$2,$R$1,$D$2,$R$1,$F$2,$R$1,$H$2,$R$1,$J$2,$O$1,$M$1,$N$1,$Q$1,C19,$Q$1,$R$1,D19,$R$1,$L$2,$N$1,$Q$1,F19,$Q$1,$O$1,$R$1,H19,$R$1,J19,$O$1,$S$1) -> INSERT INTO "OlympicPlayers" (ol_player_name,ol_player_value,ol_player_image,ol_country_id,team_sport_id) VALUES ('Giancarlo Fisichella',1,pg_read_binary_file('E:\imagenes\personajes\giancarlo_fisichella.png'),2,41);
B20: 18 | C20: Eddie Irvine | D20: 1 | E20: =_xlfn.CONCAT("\personajes\",SUBSTITUTE(LOWER(C20)," ","_"),".png") -> \personajes\eddie_irvine.png | F20: =_xlfn.CONCAT($A$1,E20) -> E:\imagenes\personajes\eddie_irvine.png | G20: Lordena | H20: =INDEX(PlayerCountry!B:B,MATCH(G20,PlayerCountry!C:C,0)) -> 4 | I20: Formula1 | J20: =INDEX(TeamSports!B:B,MATCH(I20,TeamSports!C:C,0)) -> 41 | L20: =_xlfn.CONCAT($L$1,$P$1,$B$1,$P$1," ",$N$1,$C$2,$R$1,$D$2,$R$1,$F$2,$R$1,$H$2,$R$1,$J$2,$O$1,$M$1,$N$1,$Q$1,C20,$Q$1,$R$1,D20,$R$1,$L$2,$N$1,$Q$1,F20,$Q$1,$O$1,$R$1,H20,$R$1,J20,$O$1,$S$1) -> INSERT INTO "OlympicPlayers" (ol_player_name,ol_player_value,ol_player_image,ol_country_id,team_sport_id) VALUES ('Eddie Irvine',1,pg_read_binary_file('E:\imagenes\personajes\eddie_irvine.png'),4,41);
... B60: 58 | C60: Zoda | D60: 1 | E60: =_xlfn.CONCAT("\personajes\",SUBSTITUTE(LOWER(C60)," ","_"),".png") -> \personajes\zoda.png | F60: =_xlfn.CONCAT($A$1,E60) -> E:\imagenes\personajes\zoda.png | G60: Dinazor | H60: =INDEX(PlayerCountry!B:B,MATCH(G60,PlayerCountry!C:C,0)) -> 2 | I60: F-Zero | J60: =INDEX(TeamSports!B:B,MATCH(I60,TeamSports!C:C,0)) -> 42 | L60: =_xlfn.CONCAT($L$1,$P$1,$B$1,$P$1," ",$N$1,$C$2,$R$1,$D$2,$R$1,$F$2,$R$1,$H$2,$R$1,$J$2,$O$1,$M$1,$N$1,$Q$1,C60,$Q$1,$R$1,D60,$R$1,$L$2,$N$1,$Q$1,F60,$Q$1,$O$1,$R$1,H60,$R$1,J60,$O$1,$S$1) -> INSERT INTO "OlympicPlayers" (ol_player_name,ol_player_value,ol_player_image,ol_country_id,team_sport_id) VALUES ('Zoda',1,pg_read_binary_file('E:\imagenes\personajes\zoda.png'),2,42);
B61: 59 | C61: Dimitri Mishkin | D61: 1 | E61: \personajes\mishkin.png | F61: =_xlfn.CONCAT($A$1,E61) -> E:\imagenes\personajes\mishkin.png | G61: Dinazor | H61: =INDEX(PlayerCountry!B:B,MATCH(G61,PlayerCountry!C:C,0)) -> 2 | I61: Goldeneye | J61: =INDEX(TeamSports!B:B,MATCH(I61,TeamSports!C:C,0)) -> 43 | L61: =_xlfn.CONCAT($L$1,$P$1,$B$1,$P$1," ",$N$1,$C$2,$R$1,$D$2,$R$1,$F$2,$R$1,$H$2,$R$1,$J$2,$O$1,$M$1,$N$1,$Q$1,C61,$Q$1,$R$1,D61,$R$1,$L$2,$N$1,$Q$1,F61,$Q$1,$O$1,$R$1,H61,$R$1,J61,$O$1,$S$1) -> INSERT INTO "OlympicPlayers" (ol_player_name,ol_player_value,ol_player_image,ol_country_id,team_sport_id) VALUES ('Dimitri Mishkin',1,pg_read_binary_file('E:\imagenes\personajes\mishkin.png'),2,43);
B62: 60 | C62: Alan | D62: 1 | E62: \personajes\goldeneye.png | F62: =_xlfn.CONCAT($A$1,E62) -> E:\imagenes\personajes\goldeneye.png | G62: Lordena | H62: =INDEX(PlayerCountry!B:B,MATCH(G62,PlayerCountry!C:C,0)) -> 4 | I62: Goldeneye | J62: =INDEX(TeamSports!B:B,MATCH(I62,TeamSports!C:C,0)) -> 43 | L62: =_xlfn.CONCAT($L$1,$P$1,$B$1,$P$1," ",$N$1,$C$2,$R$1,$D$2,$R$1,$F$2,$R$1,$H$2,$R$1,$J$2,$O$1,$M$1,$N$1,$Q$1,C62,$Q$1,$R$1,D62,$R$1,$L$2,$N$1,$Q$1,F62,$Q$1,$O$1,$R$1,H62,$R$1,J62,$O$1,$S$1) -> INSERT INTO "OlympicPlayers" (ol_player_name,ol_player_value,ol_player_image,ol_country_id,team_sport_id) VALUES ('Alan',1,pg_read_binary_file('E:\imagenes\personajes\goldeneye.png'),4,43);
B63: 61 | C63: Xenia Onatopp | D63: 1 | E63: \personajes\xenia.png | F63: =_xlfn.CONCAT($A$1,E63) -> E:\imagenes\personajes\xenia.png | G63: Bollstam | H63: =INDEX(PlayerCountry!B:B,MATCH(G63,PlayerCountry!C:C,0)) -> 1 | I63: Goldeneye | J63: =INDEX(TeamSports!B:B,MATCH(I63,TeamSports!C:C,0)) -> 43 | L63: =_xlfn.CONCAT($L$1,$P$1,$B$1,$P$1," ",$N$1,$C$2,$R$1,$D$2,$R$1,$F$2,$R$1,$H$2,$R$1,$J$2,$O$1,$M$1,$N$1,$Q$1,C63,$Q$1,$R$1,D63,$R$1,$L$2,$N$1,$Q$1,F63,$Q$1,$O$1,$R$1,H63,$R$1,J63,$O$1,$S$1) -> INSERT INTO "OlympicPlayers" (ol_player_name,ol_player_value,ol_player_image,ol_country_id,team_sport_id) VALUES ('Xenia Onatopp',1,pg_read_binary_file('E:\imagenes\personajes\xenia.png'),1,43);
B64: 62 | C64: Arkady Ourumov | D64: 1 | E64: \personajes\ourumov.png | F64: =_xlfn.CONCAT($A$1,E64) -> E:\imagenes\personajes\ourumov.png | G64: Dinazor | H64: =INDEX(PlayerCountry!B:B,MATCH(G64,PlayerCountry!C:C,0)) -> 2 | I64: Goldeneye | J64: =INDEX(TeamSports!B:B,MATCH(I64,TeamSports!C:C,0)) -> 43 | L64: =_xlfn.CONCAT($L$1,$P$1,$B$1,$P$1," ",$N$1,$C$2,$R$1,$D$2,$R$1,$F$2,$R$1,$H$2,$R$1,$J$2,$O$1,$M$1,$N$1,$Q$1,C64,$Q$1,$R$1,D64,$R$1,$L$2,$N$1,$Q$1,F64,$Q$1,$O$1,$R$1,H64,$R$1,J64,$O$1,$S$1) -> INSERT INTO "OlympicPlayers" (ol_player_name,ol_player_value,ol_player_image,ol_country_id,team_sport_id) VALUES ('Arkady Ourumov',1,pg_read_binary_file('E:\imagenes\personajes\ourumov.png'),2,43);
B65: 63 | C65: James Bond | D65: 1 | E65: \personajes\bond.png | F65: =_xlfn.CONCAT($A$1,E65) -> E:\imagenes\personajes\bond.png | G65: Lordena | H65: =INDEX(PlayerCountry!B:B,MATCH(G65,PlayerCountry!C:C,0)) -> 4 | I65: Goldeneye | J65: =INDEX(TeamSports!B:B,MATCH(I65,TeamSports!C:C,0)) -> 43 | L65: =_xlfn.CONCAT($L$1,$P$1,$B$1,$P$1," ",$N$1,$C$2,$R$1,$D$2,$R$1,$F$2,$R$1,$H$2,$R$1,$J$2,$O$1,$M$1,$N$1,$Q$1,C65,$Q$1,$R$1,D65,$R$1,$L$2,$N$1,$Q$1,F65,$Q$1,$O$1,$R$1,H65,$R$1,J65,$O$1,$S$1) -> INSERT INTO "OlympicPlayers" (ol_player_name,ol_player_value,ol_player_image,ol_country_id,team_sport_id) VALUES ('James Bond',1,pg_read_binary_file('E:\imagenes\personajes\bond.png'),4,43);
B66: 64 | C66: Martin | D66: 1 | E66: \personajes\goldeneye.png | F66: =_xlfn.CONCAT($A$1,E66) -> E:\imagenes\personajes\goldeneye.png | G66: Pokemonia | H66: =INDEX(PlayerCountry!B:B,MATCH(G66,PlayerCountry!C:C,0)) -> 5 | I66: Goldeneye | J66: =INDEX(TeamSports!B:B,MATCH(I66,TeamSports!C:C,0)) -> 43 | L66: =_xlfn.CONCAT($L$1,$P$1,$B$1,$P$1," ",$N$1,$C$2,$R$1,$D$2,$R$1,$F$2,$R$1,$H$2,$R$1,$J$2,$O$1,$M$1,$N$1,$Q$1,C66,$Q$1,$R$1,D66,$R$1,$L$2,$N$1,$Q$1,F66,$Q$1,$O$1,$R$1,H66,$R$1,J66,$O$1,$S$1) -> INSERT INTO "OlympicPlayers" (ol_player_name,ol_player_value,ol_player_image,ol_country_id,team_sport_id) VALUES ('Martin',1,pg_read_binary_file('E:\imagenes\personajes\goldeneye.png'),5,43);
B67: 65 | C67: Rosika | D67: 1 | E67: \personajes\rosika.png | F67: =_xlfn.CONCAT($A$1,E67) -> E:\imagenes\personajes\rosika.png | G67: Bollstam | H67: =INDEX(PlayerCountry!B:B,MATCH(G67,PlayerCountry!C:C,0)) -> 1 | I67: Goldeneye | J67: =INDEX(TeamSports!B:B,MATCH(I67,TeamSports!C:C,0)) -> 43 | L67: =_xlfn.CONCAT($L$1,$P$1,$B$1,$P$1," ",$N$1,$C$2,$R$1,$D$2,$R$1,$F$2,$R$1,$H$2,$R$1,$J$2,$O$1,$M$1,$N$1,$Q$1,C67,$Q$1,$R$1,D67,$R$1,$L$2,$N$1,$Q$1,F67,$Q$1,$O$1,$R$1,H67,$R$1,J67,$O$1,$S$1) -> INSERT INTO "OlympicPlayers" (ol_player_name,ol_player_value,ol_player_image,ol_country_id,team_sport_id) VALUES ('Rosika',1,pg_read_binary_file('E:\imagenes\personajes\rosika.png'),1,43);
B68: 66 | C68: Baron Samedi | D68: 1 | E68: \personajes\samedi.png | F68: =_xlfn.CONCAT($A$1,E68) -> E:\imagenes\personajes\samedi.png | G68: Dinazor | H68: =INDEX(PlayerCountry!B:B,MATCH(G68,PlayerCountry!C:C,0)) -> 2 | I68: Goldeneye | J68: =INDEX(TeamSports!B:B,MATCH(I68,TeamSports!C:C,0)) -> 43 | L68: =_xlfn.CONCAT($L$1,$P$1,$B$1,$P$1," ",$N$1,$C$2,$R$1,$D$2,$R$1,$F$2,$R$1,$H$2,$R$1,$J$2,$O$1,$M$1,$N$1,$Q$1,C68,$Q$1,$R$1,D68,$R$1,$L$2,$N$1,$Q$1,F68,$Q$1,$O$1,$R$1,H68,$R$1,J68,$O$1,$S$1) -> INSERT INTO "OlympicPlayers" (ol_player_name,ol_player_value,ol_player_image,ol_country_id,team_sport_id) VALUES ('Baron Samedi',1,pg_read_binary_file('E:\imagenes\personajes\samedi.png'),2,43);
B69: 67 | C69: Mayday | D69: 1 | E69: \personajes\mayday.png | F69: =_xlfn.CONCAT($A$1,E69) -> E:\imagenes\personajes\mayday.png | G69: Igra | H69: =INDEX(PlayerCountry!B:B,MATCH(G69,PlayerCountry!C:C,0)) -> 3 | I69: Goldeneye | J69: =INDEX(TeamSports!B:B,MATCH(I69,TeamSports!C:C,0)) -> 43 | L69: =_xlfn.CONCAT($L$1,$P$1,$B$1,$P$1," ",$N$1,$C$2,$R$1,$D$2,$R$1,$F$2,$R$1,$H$2,$R$1,$J$2,$O$1,$M$1,$N$1,$Q$1,C69,$Q$1,$R$1,D69,$R$1,$L$2,$N$1,$Q$1,F69,$Q$1,$O$1,$R$1,H69,$R$1,J69,$O$1,$S$1) -> INSERT INTO "OlympicPlayers" (ol_player_name,ol_player_value,ol_player_image,ol_country_id,team_sport_id) VALUES ('Mayday',1,pg_read_binary_file('E:\imagenes\personajes\mayday.png'),3,43);
B70: 68 | C70: Lee | D70: 1 | E70: \personajes\goldeneye.png | F70: =_xlfn.CONCAT($A$1,E70) -> E:\imagenes\personajes\goldeneye.png | G70: Raimei | H70: =INDEX(PlayerCountry!B:B,MATCH(G70,PlayerCountry!C:C,0)) -> 6 | I70: Goldeneye | J70: =INDEX(TeamSports!B:B,MATCH(I70,TeamSports!C:C,0)) -> 43 | L70: =_xlfn.CONCAT($L$1,$P$1,$B$1,$P$1," ",$N$1,$C$2,$R$1,$D$2,$R$1,$F$2,$R$1,$H$2,$R$1,$J$2,$O$1,$M$1,$N$1,$Q$1,C70,$Q$1,$R$1,D70,$R$1,$L$2,$N$1,$Q$1,F70,$Q$1,$O$1,$R$1,H70,$R$1,J70,$O$1,$S$1) -> INSERT INTO "OlympicPlayers" (ol_player_name,ol_player_value,ol_player_image,ol_country_id,team_sport_id) VALUES ('Lee',1,pg_read_binary_file('E:\imagenes\personajes\goldeneye.png'),6,43);
B71: 69 | C71: Ken | D71: 1 | E71: \personajes\goldeneye.png | F71: =_xlfn.CONCAT($A$1,E71) -> E:\imagenes\personajes\goldeneye.png | G71: Lordena | H71: =INDEX(PlayerCountry!B:B,MATCH(G71,PlayerCountry!C:C,0)) -> 4 | I71: Goldeneye | J71: =INDEX(TeamSports!B:B,MATCH(I71,TeamSports!C:C,0)) -> 43 | L71: =_xlfn.CONCAT($L$1,$P$1,$B$1,$P$1," ",$N$1,$C$2,$R$1,$D$2,$R$1,$F$2,$R$1,$H$2,$R$1,$J$2,$O$1,$M$1,$N$1,$Q$1,C71,$Q$1,$R$1,D71,$R$1,$L$2,$N$1,$Q$1,F71,$Q$1,$O$1,$R$1,H71,$R$1,J71,$O$1,$S$1) -> INSERT INTO "OlympicPlayers" (ol_player_name,ol_player_value,ol_player_image,ol_country_id,team_sport_id) VALUES ('Ken',1,pg_read_binary_file('E:\imagenes\personajes\goldeneye.png'),4,43);
B72: 70 | C72: Karl | D72: 1 | E72: \personajes\goldeneye.png | F72: =_xlfn.CONCAT($A$1,E72) -> E:\imagenes\personajes\goldeneye.png | G72: Pokemonia | H72: =INDEX(PlayerCountry!B:B,MATCH(G72,PlayerCountry!C:C,0)) -> 5 | I72: Goldeneye | J72: =INDEX(TeamSports!B:B,MATCH(I72,TeamSports!C:C,0)) -> 43 | L72: =_xlfn.CONCAT($L$1,$P$1,$B$1,$P$1," ",$N$1,$C$2,$R$1,$D$2,$R$1,$F$2,$R$1,$H$2,$R$1,$J$2,$O$1,$M$1,$N$1,$Q$1,C72,$Q$1,$R$1,D72,$R$1,$L$2,$N$1,$Q$1,F72,$Q$1,$O$1,$R$1,H72,$R$1,J72,$O$1,$S$1) -> INSERT INTO "OlympicPlayers" (ol_player_name,ol_player_value,ol_player_image,ol_country_id,team_sport_id) VALUES ('Karl',1,pg_read_binary_file('E:\imagenes\personajes\goldeneye.png'),5,43);
... B451: 449 | C451: Pokemonia_MN | D451: 1 | E451: \personajes\olympics.png | F451: =_xlfn.CONCAT($A$1,E451) -> E:\imagenes\personajes\olympics.png | G451: Pokemonia | H451: =INDEX(PlayerCountry!B:B,MATCH(G451,PlayerCountry!C:C,0)) -> 5 | I451: Munecos | J451: =INDEX(TeamSports!B:B,MATCH(I451,TeamSports!C:C,0)) -> 46 | L451: =_xlfn.CONCAT($L$1,$P$1,$B$1,$P$1," ",$N$1,$C$2,$R$1,$D$2,$R$1,$F$2,$R$1,$H$2,$R$1,$J$2,$O$1,$M$1,$N$1,$Q$1,C451,$Q$1,$R$1,D451,$R$1,$L$2,$N$1,$Q$1,F451,$Q$1,$O$1,$R$1,H451,$R$1,J451,$O$1,$S$1) -> INSERT INTO "OlympicPlayers" (ol_player_name,ol_player_value,ol_player_image,ol_country_id,team_sport_id) VALUES ('Pokemonia_MN',1,pg_read_binary_file('E:\imagenes\personajes\olympics.png'),5,46);
B452: 450 | C452: Bowser_SSB | D452: 1 | E452: \personajes\bowser.png | F452: =_xlfn.CONCAT($A$1,E452) -> E:\imagenes\personajes\bowser.png | G452: Bollstam | H452: =INDEX(PlayerCountry!B:B,MATCH(G452,PlayerCountry!C:C,0)) -> 1 | I452: Mario Tenis | J452: 45 | L452: =_xlfn.CONCAT($L$1,$P$1,$B$1,$P$1," ",$N$1,$C$2,$R$1,$D$2,$R$1,$F$2,$R$1,$H$2,$R$1,$J$2,$O$1,$M$1,$N$1,$Q$1,C452,$Q$1,$R$1,D452,$R$1,$L$2,$N$1,$Q$1,F452,$Q$1,$O$1,$R$1,H452,$R$1,J452,$O$1,$S$1) -> INSERT INTO "OlympicPlayers" (ol_player_name,ol_player_value,ol_player_image,ol_country_id,team_sport_id) VALUES ('Bowser_SSB',1,pg_read_binary_file('E:\imagenes\personajes\bowser.png'),1,45);
B453: 451 | C453: Captain Falcon | D453: 1 | E453: =_xlfn.CONCAT("\personajes\",SUBSTITUTE(LOWER(C453)," ","_"),".png") -> \personajes\captain_falcon.png | F453: =_xlfn.CONCAT($A$1,E453) -> E:\imagenes\personajes\captain_falcon.png | G453: Bollstam | H453: =INDEX(PlayerCountry!B:B,MATCH(G453,PlayerCountry!C:C,0)) -> 1 | I453: F-Zero | J453: 45 | L453: =_xlfn.CONCAT($L$1,$P$1,$B$1,$P$1," ",$N$1,$C$2,$R$1,$D$2,$R$1,$F$2,$R$1,$H$2,$R$1,$J$2,$O$1,$M$1,$N$1,$Q$1,C453,$Q$1,$R$1,D453,$R$1,$L$2,$N$1,$Q$1,F453,$Q$1,$O$1,$R$1,H453,$R$1,J453,$O$1,$S$1) -> INSERT INTO "OlympicPlayers" (ol_player_name,ol_player_value,ol_player_image,ol_country_id,team_sport_id) VALUES ('Captain Falcon',1,pg_read_binary_file('E:\imagenes\personajes\captain_falcon.png'),1,45);
B454: 452 | C454: Samus/Samus | D454: 1 | E454: \personajes\samus.png | F454: =_xlfn.CONCAT($A$1,E454) -> E:\imagenes\personajes\samus.png | G454: Silnik | H454: =INDEX(PlayerCountry!B:B,MATCH(G454,PlayerCountry!C:C,0)) -> 8 | I454: Super Smash | J454: =INDEX(TeamSports!B:B,MATCH(I454,TeamSports!C:C,0)) -> 45 | L454: =_xlfn.CONCAT($L$1,$P$1,$B$1,$P$1," ",$N$1,$C$2,$R$1,$D$2,$R$1,$F$2,$R$1,$H$2,$R$1,$J$2,$O$1,$M$1,$N$1,$Q$1,C454,$Q$1,$R$1,D454,$R$1,$L$2,$N$1,$Q$1,F454,$Q$1,$O$1,$R$1,H454,$R$1,J454,$O$1,$S$1) -> INSERT INTO "OlympicPlayers" (ol_player_name,ol_player_value,ol_player_image,ol_country_id,team_sport_id) VALUES ('Samus/Samus',1,pg_read_binary_file('E:\imagenes\personajes\samus.png'),8,45);

Sheet PlayerCountry
B1: PlayerCountry | E1: INSERT INTO | F1: VALUES | G1: ( | H1: ) | I1: " | J1: ' | K1: , | L1: ;
B2: ol_country_id | C2: ol_country_name
B3: 1 | C3: Bollstam | E3: =_xlfn.CONCAT($E$1," ",$I$1,$B$1,$I$1," ",$G$1,$C$2,$H$1," ",$F$1," ",$G$1,$J$1,C3,$J$1,$H$1,$L$1) -> INSERT INTO "PlayerCountry" (ol_country_name) VALUES ('Bollstam');
B4: 2 | C4: Dinazor | E4: =_xlfn.CONCAT($E$1," ",$I$1,$B$1,$I$1," ",$G$1,$C$2,$H$1," ",$F$1," ",$G$1,$J$1,C4,$J$1,$H$1,$L$1) -> INSERT INTO "PlayerCountry" (ol_country_name) VALUES ('Dinazor');
B5: 3 | C5: Igra | E5: =_xlfn.CONCAT($E$1," ",$I$1,$B$1,$I$1," ",$G$1,$C$2,$H$1," ",$F$1," ",$G$1,$J$1,C5,$J$1,$H$1,$L$1) -> INSERT INTO "PlayerCountry" (ol_country_name) VALUES ('Igra');
B6: 4 | C6: Lordena | E6: =_xlfn.CONCAT($E$1," ",$I$1,$B$1,$I$1," ",$G$1,$C$2,$H$1," ",$F$1," ",$G$1,$J$1,C6,$J$1,$H$1,$L$1) -> INSERT INTO "PlayerCountry" (ol_country_name) VALUES ('Lordena');
B7: 5 | C7: Pokemonia | E7: =_xlfn.CONCAT($E$1," ",$I$1,$B$1,$I$1," ",$G$1,$C$2,$H$1," ",$F$1," ",$G$1,$J$1,C7,$J$1,$H$1,$L$1) -> INSERT INTO "PlayerCountry" (ol_country_name) VALUES ('Pokemonia');
B8: 6 | C8: Raimei | E8: =_xlfn.CONCAT($E$1," ",$I$1,$B$1,$I$1," ",$G$1,$C$2,$H$1," ",$F$1," ",$G$1,$J$1,C8,$J$1,$H$1,$L$1) -> INSERT INTO "PlayerCountry" (ol_country_name) VALUES ('Raimei');
B9: 7 | C9: Schattenmond | E9: =_xlfn.CONCAT($E$1," ",$I$1,$B$1,$I$1," ",$G$1,$C$2,$H$1," ",$F$1," ",$G$1,$J$1,C9,$J$1,$H$1,$L$1) -> INSERT INTO "PlayerCountry" (ol_country_name) VALUES ('Schattenmond');
B10: 8 | C10: Silnik | E10: =_xlfn.CONCAT($E$1," ",$I$1,$B$1,$I$1," ",$G$1,$C$2,$H$1," ",$F$1," ",$G$1,$J$1,C10,$J$1,$H$1,$L$1) -> INSERT INTO "PlayerCountry" (ol_country_name) VALUES ('Silnik');

Sheet Clubs
A1: E:\imagenes | B1: Clubs | O1: INSERT INTO | P1: VALUES | Q1: ( | R1: ) | S1: " | T1: ' | U1: , | V1: ;
B2: club_id | C2: club_name | D2: club_league | E2: club_league_id | I2: club_value | J2: ruta | K2: club_shield | L2: country | M2: club_country | O2: pg_read_binary_file
B3: 1 | C3: 07 Vestur | D3: Faroe Islands Premier League | E3: =INDEX(ClubLeague!B:B,MATCH(D3,ClubLeague!C:C,0)) -> 56 | F3: 57 | G3: 52 | H3: 45 | I3: =ROUND(AVERAGE(F3:H3),0) -> 51 | J3: \escudos_cl\Europa\Faroe Islands Premier League\07 Vestur.png | K3: =_xlfn.CONCAT($A$1,J3) -> E:\imagenes\escudos_cl\Europa\Faroe Islands Premier League\07 Vestur.png | L3: Islas Feroe | M3: =INDEX(NationalTeams!B:B,MATCH(L3,NationalTeams!C:C,0)) -> 103 | O3: =_xlfn.CONCAT($O$1,$S$1,$B$1,$S$1," ",$Q$1,$C$2,$U$1,$E$2,$U$1,$I$2,$U$1,$K$2,$U$1,$M$2,$R$1,$P$1,$Q$1,$T$1,C3,$T$1,$U$1,E3,$U$1,I3,$U$1,$O$2,$Q$1,$T$1,K3,$T$1,$R$1,$U$1,M3,$R$1,$V$1) -> INSERT INTO "Clubs" (club_name,club_league_id,club_value,club_shield,club_country) VALUES ('07 Vestur',56,51,pg_read_binary_file('E:\imagenes\escudos_cl\Europa\Faroe Islands Premier League\07 Vestur.png'),103);
B4: 2 | C4: 1.FC Kaiserslautern | D4: 2. Bundesliga | E4: =INDEX(ClubLeague!B:B,MATCH(D4,ClubLeague!C:C,0)) -> 2 | F4: 65 | G4: 65 | H4: 69 | I4: =ROUND(AVERAGE(F4:H4),0) -> 66 | J4: \escudos_cl\Europa\2. Bundesliga\1.FC Kaiserslautern.png | K4: =_xlfn.CONCAT($A$1,J4) -> E:\imagenes\escudos_cl\Europa\2. Bundesliga\1.FC Kaiserslautern.png | L4: Alemania | M4: =INDEX(NationalTeams!B:B,MATCH(L4,NationalTeams!C:C,0)) -> 4 | O4: =_xlfn.CONCAT($O$1,$S$1,$B$1,$S$1," ",$Q$1,$C$2,$U$1,$E$2,$U$1,$I$2,$U$1,$K$2,$U$1,$M$2,$R$1,$P$1,$Q$1,$T$1,C4,$T$1,$U$1,E4,$U$1,I4,$U$1,$O$2,$Q$1,$T$1,K4,$T$1,$R$1,$U$1,M4,$R$1,$V$1) -> INSERT INTO "Clubs" (club_name,club_league_id,club_value,club_shield,club_country) VALUES ('1.FC Kaiserslautern',2,66,pg_read_binary_file('E:\imagenes\escudos_cl\Europa\2. Bundesliga\1.FC Kaiserslautern.png'),4);
B5: 3 | C5: 1.SK Prostejov | D5: Czech National Football League | E5: =INDEX(ClubLeague!B:B,MATCH(D5,ClubLeague!C:C,0)) -> 42 | F5: 47 | G5: 57 | H5: 51 | I5: =ROUND(AVERAGE(F5:H5),0) -> 52 | J5: \escudos_cl\Europa\Czech National Football League\1.SK Prostejov.png | K5: =_xlfn.CONCAT($A$1,J5) -> E:\imagenes\escudos_cl\Europa\Czech National Football League\1.SK Prostejov.png | L5: Republica Checa | M5: =INDEX(NationalTeams!B:B,MATCH(L5,NationalTeams!C:C,0)) -> 171 | O5: =_xlfn.CONCAT($O$1,$S$1,$B$1,$S$1," ",$Q$1,$C$2,$U$1,$E$2,$U$1,$I$2,$U$1,$K$2,$U$1,$M$2,$R$1,$P$1,$Q$1,$T$1,C5,$T$1,$U$1,E5,$U$1,I5,$U$1,$O$2,$Q$1,$T$1,K5,$T$1,$R$1,$U$1,M5,$R$1,$V$1) -> INSERT INTO "Clubs" (club_name,club_league_id,club_value,club_shield,club_country) VALUES ('1.SK Prostejov',42,52,pg_read_binary_file('E:\imagenes\escudos_cl\Europa\Czech National Football League\1.SK Prostejov.png'),171);
B6: 4 | C6: 22 de Julio FC | D6: LigaPro Ecuabet Serie B | E6: =INDEX(ClubLeague!B:B,MATCH(D6,ClubLeague!C:C,0)) -> 112 | F6: 58 | G6: 58 | H6: 58 | I6: =ROUND(AVERAGE(F6:H6),0) -> 58 | J6: \escudos_cl\America\LigaPro Ecuabet Serie B\22 de Julio FC.png | K6: =_xlfn.CONCAT($A$1,J6) -> E:\imagenes\escudos_cl\America\LigaPro Ecuabet Serie B\22 de Julio FC.png | L6: Ecuador | M6: =INDEX(NationalTeams!B:B,MATCH(L6,NationalTeams!C:C,0)) -> 58 | O6: =_xlfn.CONCAT($O$1,$S$1,$B$1,$S$1," ",$Q$1,$C$2,$U$1,$E$2,$U$1,$I$2,$U$1,$K$2,$U$1,$M$2,$R$1,$P$1,$Q$1,$T$1,C6,$T$1,$U$1,E6,$U$1,I6,$U$1,$O$2,$Q$1,$T$1,K6,$T$1,$R$1,$U$1,M6,$R$1,$V$1) -> INSERT INTO "Clubs" (club_name,club_league_id,club_value,club_shield,club_country) VALUES ('22 de Julio FC',112,58,pg_read_binary_file('E:\imagenes\escudos_cl\America\LigaPro Ecuabet Serie B\22 de Julio FC.png'),58);
B7: 5 | C7: 9 de Octubre FC | D7: LigaPro Ecuabet Serie B | E7: =INDEX(ClubLeague!B:B,MATCH(D7,ClubLeague!C:C,0)) -> 112 | F7: 58 | G7: 56 | H7: 59 | I7: =ROUND(AVERAGE(F7:H7),0) -> 58 | J7: \escudos_cl\America\LigaPro Ecuabet Serie B\9 de Octubre FC.png | K7: =_xlfn.CONCAT($A$1,J7) -> E:\imagenes\escudos_cl\America\LigaPro Ecuabet Serie B\9 de Octubre FC.png | L7: Ecuador | M7: =INDEX(NationalTeams!B:B,MATCH(L7,NationalTeams!C:C,0)) -> 58 | O7: =_xlfn.CONCAT($O$1,$S$1,$B$1,$S$1," ",$Q$1,$C$2,$U$1,$E$2,$U$1,$I$2,$U$1,$K$2,$U$1,$M$2,$R$1,$P$1,$Q$1,$T$1,C7,$T$1,$U$1,E7,$U$1,I7,$U$1,$O$2,$Q$1,$T$1,K7,$T$1,$R$1,$U$1,M7,$R$1,$V$1) -> INSERT INTO "Clubs" (club_name,club_league_id,club_value,club_shield,club_country) VALUES ('9 de Octubre FC',112,58,pg_read_binary_file('E:\imagenes\escudos_cl\America\LigaPro Ecuabet Serie B\9 de Octubre FC.png'),58);
B8: 6 | C8: Aalesunds FK | D8: Norwegian First Division | E8: =INDEX(ClubLeague!B:B,MATCH(D8,ClubLeague!C:C,0)) -> 141 | F8: 55 | G8: 58 | H8: 54 | I8: =ROUND(AVERAGE(F8:H8),0) -> 56 | J8: \escudos_cl\Europa\Norwegian First Division\Aalesunds FK.png | K8: =_xlfn.CONCAT($A$1,J8) -> E:\imagenes\escudos_cl\Europa\Norwegian First Division\Aalesunds FK.png | L8: Noruega | M8: =INDEX(NationalTeams!B:B,MATCH(L8,NationalTeams!C:C,0)) -> 154 | O8: =_xlfn.CONCAT($O$1,$S$1,$B$1,$S$1," ",$Q$1,$C$2,$U$1,$E$2,$U$1,$I$2,$U$1,$K$2,$U$1,$M$2,$R$1,$P$1,$Q$1,$T$1,C8,$T$1,$U$1,E8,$U$1,I8,$U$1,$O$2,$Q$1,$T$1,K8,$T$1,$R$1,$U$1,M8,$R$1,$V$1) -> INSERT INTO "Clubs" (club_name,club_league_id,club_value,club_shield,club_country) VALUES ('Aalesunds FK',141,56,pg_read_binary_file('E:\imagenes\escudos_cl\Europa\Norwegian First Division\Aalesunds FK.png'),154);
B9: 7 | C9: Aali CSC | D9: Bahrain Premier League | E9: =INDEX(ClubLeague!B:B,MATCH(D9,ClubLeague!C:C,0)) -> 17 | F9: 56 | G9: 59 | H9: 55 | I9: =ROUND(AVERAGE(F9:H9),0) -> 57 | J9: \escudos_cl\Asia\Bahrain Premier League\Aali CSC.png | K9: =_xlfn.CONCAT($A$1,J9) -> E:\imagenes\escudos_cl\Asia\Bahrain Premier League\Aali CSC.png | L9: Bahrein | M9: =INDEX(NationalTeams!B:B,MATCH(L9,NationalTeams!C:C,0)) -> 20 | O9: =_xlfn.CONCAT($O$1,$S$1,$B$1,$S$1," ",$Q$1,$C$2,$U$1,$E$2,$U$1,$I$2,$U$1,$K$2,$U$1,$M$2,$R$1,$P$1,$Q$1,$T$1,C9,$T$1,$U$1,E9,$U$1,I9,$U$1,$O$2,$Q$1,$T$1,K9,$T$1,$R$1,$U$1,M9,$R$1,$V$1) -> INSERT INTO "Clubs" (club_name,club_league_id,club_value,club_shield,club_country) VALUES ('Aali CSC',17,57,pg_read_binary_file('E:\imagenes\escudos_cl\Asia\Bahrain Premier League\Aali CSC.png'),20);
B10: 8 | C10: Aarhus GF | D10: 3F Superliga | E10: =INDEX(ClubLeague!B:B,MATCH(D10,ClubLeague!C:C,0)) -> 5 | F10: 52 | G10: 64 | H10: 59 | I10: =ROUND(AVERAGE(F10:H10),0) -> 58 | J10: \escudos_cl\Europa\3F Superliga\Aarhus GF.png | K10: =_xlfn.CONCAT($A$1,J10) -> E:\imagenes\escudos_cl\Europa\3F Superliga\Aarhus GF.png | L10: Dinamarca | M10: =INDEX(NationalTeams!B:B,MATCH(L10,NationalTeams!C:C,0)) -> 56 | O10: =_xlfn.CONCAT($O$1,$S$1,$B$1,$S$1," ",$Q$1,$C$2,$U$1,$E$2,$U$1,$I$2,$U$1,$K$2,$U$1,$M$2,$R$1,$P$1,$Q$1,$T$1,C10,$T$1,$U$1,E10,$U$1,I10,$U$1,$O$2,$Q$1,$T$1,K10,$T$1,$R$1,$U$1,M10,$R$1,$V$1) -> INSERT INTO "Clubs" (club_name,club_league_id,club_value,club_shield,club_country) VALUES ('Aarhus GF',5,58,pg_read_binary_file('E:\imagenes\escudos_cl\Europa\3F Superliga\Aarhus GF.png'),56);
B11: 9 | C11: Abahani Limited Dhaka | D11: Bangladesh Premier League | E11: =INDEX(ClubLeague!B:B,MATCH(D11,ClubLeague!C:C,0)) -> 18 | F11: 48 | G11: 48 | H11: 53 | I11: =ROUND(AVERAGE(F11:H11),0) -> 50 | J11: \escudos_cl\Asia\Bangladesh Premier League\Abahani Limited Dhaka.png | K11: =_xlfn.CONCAT($A$1,J11) -> E:\imagenes\escudos_cl\Asia\Bangladesh Premier League\Abahani Limited Dhaka.png | L11: Bangladesh | M11: =INDEX(NationalTeams!B:B,MATCH(L11,NationalTeams!C:C,0)) -> 21 | O11: =_xlfn.CONCAT($O$1,$S$1,$B$1,$S$1," ",$Q$1,$C$2,$U$1,$E$2,$U$1,$I$2,$U$1,$K$2,$U$1,$M$2,$R$1,$P$1,$Q$1,$T$1,C11,$T$1,$U$1,E11,$U$1,I11,$U$1,$O$2,$Q$1,$T$1,K11,$T$1,$R$1,$U$1,M11,$R$1,$V$1) -> INSERT INTO "Clubs" (club_name,club_league_id,club_value,club_shield,club_country) VALUES ('Abahani Limited Dhaka',18,50,pg_read_binary_file('E:\imagenes\escudos_cl\Asia\Bangladesh Premier League\Abahani Limited Dhaka.png'),21);
B12: 10 | C12: Aberdeen FC | D12: Scottish Premiership | E12: =INDEX(ClubLeague!B:B,MATCH(D12,ClubLeague!C:C,0)) -> 163 | F12: 63 | G12: 66 | H12: 63 | I12: =ROUND(AVERAGE(F12:H12),0) -> 64 | J12: \escudos_cl\Europa\Scottish Premiership\Aberdeen FC.png | K12: =_xlfn.CONCAT($A$1,J12) -> E:\imagenes\escudos_cl\Europa\Scottish Premiership\Aberdeen FC.png | L12: Escocia | M12: =INDEX(NationalTeams!B:B,MATCH(L12,NationalTeams!C:C,0)) -> 63 | O12: =_xlfn.CONCAT($O$1,$S$1,$B$1,$S$1," ",$Q$1,$C$2,$U$1,$E$2,$U$1,$I$2,$U$1,$K$2,$U$1,$M$2,$R$1,$P$1,$Q$1,$T$1,C12,$T$1,$U$1,E12,$U$1,I12,$U$1,$O$2,$Q$1,$T$1,K12,$T$1,$R$1,$U$1,M12,$R$1,$V$1) -> INSERT INTO "Clubs" (club_name,club_league_id,club_value,club_shield,club_country) VALUES ('Aberdeen FC',163,64,pg_read_binary_file('E:\imagenes\escudos_cl\Europa\Scottish Premiership\Aberdeen FC.png'),63);
B13: 11 | C13: Aberstwyth Town FC | D13: Cymru Second | E13: =INDEX(ClubLeague!B:B,MATCH(D13,ClubLeague!C:C,0)) -> 37 | F13: 58 | G13: 56 | H13: 55 | I13: =ROUND(AVERAGE(F13:H13),0) -> 56 | J13: \escudos_cl\Europa\Cymru South\Aberstwyth Town FC.png | K13: =_xlfn.CONCAT($A$1,J13) -> E:\imagenes\escudos_cl\Europa\Cymru South\Aberstwyth Town FC.png | L13: Gales | M13: =INDEX(NationalTeams!B:B,MATCH(L13,NationalTeams!C:C,0)) -> 76 | O13: =_xlfn.CONCAT($O$1,$S$1,$B$1,$S$1," ",$Q$1,$C$2,$U$1,$E$2,$U$1,$I$2,$U$1,$K$2,$U$1,$M$2,$R$1,$P$1,$Q$1,$T$1,C13,$T$1,$U$1,E13,$U$1,I13,$U$1,$O$2,$Q$1,$T$1,K13,$T$1,$R$1,$U$1,M13,$R$1,$V$1) -> INSERT INTO "Clubs" (club_name,club_league_id,club_value,club_shield,club_country) VALUES ('Aberstwyth Town FC',37,56,pg_read_binary_file('E:\imagenes\escudos_cl\Europa\Cymru South\Aberstwyth Town FC.png'),76);
B14: 12 | C14: Abha FC | D14: FD League | E14: =INDEX(ClubLeague!B:B,MATCH(D14,ClubLeague!C:C,0)) -> 57 | F14: 62 | G14: 57 | H14: 59 | I14: =ROUND(AVERAGE(F14:H14),0) -> 59 | J14: \escudos_cl\Asia\FD League\Abha FC.png | K14: =_xlfn.CONCAT($A$1,J14) -> E:\imagenes\escudos_cl\Asia\FD League\Abha FC.png | L14: Arabia Saudita | M14: =INDEX(NationalTeams!B:B,MATCH(L14,NationalTeams!C:C,0)) -> 10 | O14: =_xlfn.CONCAT($O$1,$S$1,$B$1,$S$1," ",$Q$1,$C$2,$U$1,$E$2,$U$1,$I$2,$U$1,$K$2,$U$1,$M$2,$R$1,$P$1,$Q$1,$T$1,C14,$T$1,$U$1,E14,$U$1,I14,$U$1,$O$2,$Q$1,$T$1,K14,$T$1,$R$1,$U$1,M14,$R$1,$V$1) -> INSERT INTO "Clubs" (club_name,club_league_id,club_value,club_shield,club_country) VALUES ('Abha FC',57,59,pg_read_binary_file('E:\imagenes\escudos_cl\Asia\FD League\Abha FC.png'),10);
... B3037: 3035 | C3037: ZPC Kariba FC | D3037: Zimbabwe Premier Soccer League | E3037: =INDEX(ClubLeague!B:B,MATCH(D3037,ClubLeague!C:C,0)) -> 211 | F3037: 49 | G3037: 54 | H3037: 49 | I3037: =ROUND(AVERAGE(F3037:H3037),0) -> 51 | J3037: \escudos_cl\Africa\Zimbabwe Premier Soccer League\ZPC Kariba FC.png | K3037: =_xlfn.CONCAT($A$1,J3037) -> E:\imagenes\escudos_cl\Africa\Zimbabwe Premier Soccer League\ZPC Kariba FC.png | L3037: Zimbaue | M3037: =INDEX(NationalTeams!B:B,MATCH(L3037,NationalTeams!C:C,0)) -> 223 | O3037: =_xlfn.CONCAT($O$1,$S$1,$B$1,$S$1," ",$Q$1,$C$2,$U$1,$E$2,$U$1,$I$2,$U$1,$K$2,$U$1,$M$2,$R$1,$P$1,$Q$1,$T$1,C3037,$T$1,$U$1,E3037,$U$1,I3037,$U$1,$O$2,$Q$1,$T$1,K3037,$T$1,$R$1,$U$1,M3037,$R$1,$V$1) -> INSERT INTO "Clubs" (club_name,club_league_id,club_value,club_shield,club_country) VALUES ('ZPC Kariba FC',211,51,pg_read_binary_file('E:\imagenes\escudos_cl\Africa\Zimbabwe Premier Soccer League\ZPC Kariba FC.png'),223);

Sheet ClubLeague
B1: ClubLeague | O1: INSERT INTO | P1: VALUES | Q1: ( | R1: ) | S1: " | T1: ' | U1: , | V1: ;
B2: club_league_id | C2: club_league_name | D2: club_country | E2: Region | F2: team_region_id | G2: club_country | H2: club_division | I2: club_prom_reg | J2: club_first_qual | K2: club_second_qual | L2: club_third_qual | M2: clas_direct
B3: 1 | C3: 1. Deild Karla | D3: Islandia | E3: Europa | F3: =INDEX(TeamRegion!B:B,MATCH(E3,TeamRegion!C:C,0)) -> 4 | G3: =INDEX(NationalTeams!B:B,MATCH(D3,NationalTeams!C:C,0)) -> 100 | H3: 2D | I3: 2 | J3: 0 | K3: 0 | L3: 0 | M3: N | O3: =_xlfn.CONCAT($O$1," ",$S$1,$B$1,$S$1," ",$Q$1,$C$2,$U$1,$F$2,$U$1,$G$2,$U$1,$H$2,$U$1,$I$2,$U$1,$J$2,$U$1,$K$2,$U$1,$L$2,$U$1,$M$2,$R$1,$P$1,$Q$1,$T$1,C3,$T$1,$U$1,F3,$U$1,G3,$U$1,$T$1,H3,$T$1,$U$1,I3,$U$1,J3,$U$1,K3,$U$1,L3,$U$1,$T$1,M3,$T$1,$R$1,$V$1) -> INSERT INTO "ClubLeague" (club_league_name,team_region_id,club_country,club_division,club_prom_reg,club_first_qual,club_second_qual,club_third_qual,clas_direct) VALUES ('1. Deild Karla',4,100,'2D',2,0,0,0,'N');
B4: 2 | C4: 2. Bundesliga | D4: Alemania | E4: Europa | F4: =INDEX(TeamRegion!B:B,MATCH(E4,TeamRegion!C:C,0)) -> 4 | G4: =INDEX(NationalTeams!B:B,MATCH(D4,NationalTeams!C:C,0)) -> 4 | H4: 2D | I4: 2 | J4: 0 | K4: 0 | L4: 0 | M4: N | O4: =_xlfn.CONCAT($O$1," ",$S$1,$B$1,$S$1," ",$Q$1,$C$2,$U$1,$F$2,$U$1,$G$2,$U$1,$H$2,$U$1,$I$2,$U$1,$J$2,$U$1,$K$2,$U$1,$L$2,$U$1,$M$2,$R$1,$P$1,$Q$1,$T$1,C4,$T$1,$U$1,F4,$U$1,G4,$U$1,$T$1,H4,$T$1,$U$1,I4,$U$1,J4,$U$1,K4,$U$1,L4,$U$1,$T$1,M4,$T$1,$R$1,$V$1) -> INSERT INTO "ClubLeague" (club_league_name,team_region_id,club_country,club_division,club_prom_reg,club_first_qual,club_second_qual,club_third_qual,clas_direct) VALUES ('2. Bundesliga',4,4,'2D',2,0,0,0,'N');
B5: 3 | C5: 2. HNL 2024-25 | D5: Croacia | E5: Europa | F5: =INDEX(TeamRegion!B:B,MATCH(E5,TeamRegion!C:C,0)) -> 4 | G5: =INDEX(NationalTeams!B:B,MATCH(D5,NationalTeams!C:C,0)) -> 53 | H5: 2D | I5: 2 | J5: 0 | K5: 0 | L5: 0 | M5: N | O5: =_xlfn.CONCAT($O$1," ",$S$1,$B$1,$S$1," ",$Q$1,$C$2,$U$1,$F$2,$U$1,$G$2,$U$1,$H$2,$U$1,$I$2,$U$1,$J$2,$U$1,$K$2,$U$1,$L$2,$U$1,$M$2,$R$1,$P$1,$Q$1,$T$1,C5,$T$1,$U$1,F5,$U$1,G5,$U$1,$T$1,H5,$T$1,$U$1,I5,$U$1,J5,$U$1,K5,$U$1,L5,$U$1,$T$1,M5,$T$1,$R$1,$V$1) -> INSERT INTO "ClubLeague" (club_league_name,team_region_id,club_country,club_division,club_prom_reg,club_first_qual,club_second_qual,club_third_qual,clas_direct) VALUES ('2. HNL 2024-25',4,53,'2D',2,0,0,0,'N');
B6: 4 | C6: 2. Liga | D6: Austria | E6: Europa | F6: =INDEX(TeamRegion!B:B,MATCH(E6,TeamRegion!C:C,0)) -> 4 | G6: =INDEX(NationalTeams!B:B,MATCH(D6,NationalTeams!C:C,0)) -> 17 | H6: 2D | I6: 2 | J6: 0 | K6: 0 | L6: 0 | M6: N | O6: =_xlfn.CONCAT($O$1," ",$S$1,$B$1,$S$1," ",$Q$1,$C$2,$U$1,$F$2,$U$1,$G$2,$U$1,$H$2,$U$1,$I$2,$U$1,$J$2,$U$1,$K$2,$U$1,$L$2,$U$1,$M$2,$R$1,$P$1,$Q$1,$T$1,C6,$T$1,$U$1,F6,$U$1,G6,$U$1,$T$1,H6,$T$1,$U$1,I6,$U$1,J6,$U$1,K6,$U$1,L6,$U$1,$T$1,M6,$T$1,$R$1,$V$1) -> INSERT INTO "ClubLeague" (club_league_name,team_region_id,club_country,club_division,club_prom_reg,club_first_qual,club_second_qual,club_third_qual,clas_direct) VALUES ('2. Liga',4,17,'2D',2,0,0,0,'N');
B7: 5 | C7: 3F Superliga | D7: Dinamarca | E7: Europa | F7: =INDEX(TeamRegion!B:B,MATCH(E7,TeamRegion!C:C,0)) -> 4 | G7: =INDEX(NationalTeams!B:B,MATCH(D7,NationalTeams!C:C,0)) -> 56 | H7: 1D | I7: 2 | J7: 1 | K7: 1 | L7: 1 | M7: Y | O7: =_xlfn.CONCAT($O$1," ",$S$1,$B$1,$S$1," ",$Q$1,$C$2,$U$1,$F$2,$U$1,$G$2,$U$1,$H$2,$U$1,$I$2,$U$1,$J$2,$U$1,$K$2,$U$1,$L$2,$U$1,$M$2,$R$1,$P$1,$Q$1,$T$1,C7,$T$1,$U$1,F7,$U$1,G7,$U$1,$T$1,H7,$T$1,$U$1,I7,$U$1,J7,$U$1,K7,$U$1,L7,$U$1,$T$1,M7,$T$1,$R$1,$V$1) -> INSERT INTO "ClubLeague" (club_league_name,team_region_id,club_country,club_division,club_prom_reg,club_first_qual,club_second_qual,club_third_qual,clas_direct) VALUES ('3F Superliga',4,56,'1D',2,1,1,1,'Y');
B8: 6 | C8: A League | D8: Australia | E8: Asia | F8: =INDEX(TeamRegion!B:B,MATCH(E8,TeamRegion!C:C,0)) -> 2 | G8: =INDEX(NationalTeams!B:B,MATCH(D8,NationalTeams!C:C,0)) -> 16 | H8: 1D | I8: 2 | J8: 1 | K8: 1 | L8: 0 | M8: Y | O8: =_xlfn.CONCAT($O$1," ",$S$1,$B$1,$S$1," ",$Q$1,$C$2,$U$1,$F$2,$U$1,$G$2,$U$1,$H$2,$U$1,$I$2,$U$1,$J$2,$U$1,$K$2,$U$1,$L$2,$U$1,$M$2,$R$1,$P$1,$Q$1,$T$1,C8,$T$1,$U$1,F8,$U$1,G8,$U$1,$T$1,H8,$T$1,$U$1,I8,$U$1,J8,$U$1,K8,$U$1,L8,$U$1,$T$1,M8,$T$1,$R$1,$V$1) -> INSERT INTO "ClubLeague" (club_league_name,team_region_id,club_country,club_division,club_prom_reg,club_first_qual,club_second_qual,club_third_qual,clas_direct) VALUES ('A League',2,16,'1D',2,1,1,0,'Y');
B9: 7 | C9: A Lyga | D9: Lituania | E9: Europa | F9: =INDEX(TeamRegion!B:B,MATCH(E9,TeamRegion!C:C,0)) -> 4 | G9: =INDEX(NationalTeams!B:B,MATCH(D9,NationalTeams!C:C,0)) -> 127 | H9: 1D | I9: 2 | J9: 1 | K9: 0 | L9: 1 | M9: N | O9: =_xlfn.CONCAT($O$1," ",$S$1,$B$1,$S$1," ",$Q$1,$C$2,$U$1,$F$2,$U$1,$G$2,$U$1,$H$2,$U$1,$I$2,$U$1,$J$2,$U$1,$K$2,$U$1,$L$2,$U$1,$M$2,$R$1,$P$1,$Q$1,$T$1,C9,$T$1,$U$1,F9,$U$1,G9,$U$1,$T$1,H9,$T$1,$U$1,I9,$U$1,J9,$U$1,K9,$U$1,L9,$U$1,$T$1,M9,$T$1,$R$1,$V$1) -> INSERT INTO "ClubLeague" (club_league_name,team_region_id,club_country,club_division,club_prom_reg,club_first_qual,club_second_qual,club_third_qual,clas_direct) VALUES ('A Lyga',4,127,'1D',2,1,0,1,'N');
B10: 8 | C10: Abissnet Superiore | D10: Albania | E10: Europa | F10: =INDEX(TeamRegion!B:B,MATCH(E10,TeamRegion!C:C,0)) -> 4 | G10: =INDEX(NationalTeams!B:B,MATCH(D10,NationalTeams!C:C,0)) -> 3 | H10: 1D | I10: 2 | J10: 1 | K10: 1 | L10: 1 | M10: N | O10: =_xlfn.CONCAT($O$1," ",$S$1,$B$1,$S$1," ",$Q$1,$C$2,$U$1,$F$2,$U$1,$G$2,$U$1,$H$2,$U$1,$I$2,$U$1,$J$2,$U$1,$K$2,$U$1,$L$2,$U$1,$M$2,$R$1,$P$1,$Q$1,$T$1,C10,$T$1,$U$1,F10,$U$1,G10,$U$1,$T$1,H10,$T$1,$U$1,I10,$U$1,J10,$U$1,K10,$U$1,L10,$U$1,$T$1,M10,$T$1,$R$1,$V$1) -> INSERT INTO "ClubLeague" (club_league_name,team_region_id,club_country,club_division,club_prom_reg,club_first_qual,club_second_qual,club_third_qual,clas_direct) VALUES ('Abissnet Superiore',4,3,'1D',2,1,1,1,'N');
B11: 9 | C11: Admiral Bundesliga | D11: Austria | E11: Europa | F11: =INDEX(TeamRegion!B:B,MATCH(E11,TeamRegion!C:C,0)) -> 4 | G11: =INDEX(NationalTeams!B:B,MATCH(D11,NationalTeams!C:C,0)) -> 17 | H11: 1D | I11: 2 | J11: 1 | K11: 2 | L11: 1 | M11: Y | O11: =_xlfn.CONCAT($O$1," ",$S$1,$B$1,$S$1," ",$Q$1,$C$2,$U$1,$F$2,$U$1,$G$2,$U$1,$H$2,$U$1,$I$2,$U$1,$J$2,$U$1,$K$2,$U$1,$L$2,$U$1,$M$2,$R$1,$P$1,$Q$1,$T$1,C11,$T$1,$U$1,F11,$U$1,G11,$U$1,$T$1,H11,$T$1,$U$1,I11,$U$1,J11,$U$1,K11,$U$1,L11,$U$1,$T$1,M11,$T$1,$R$1,$V$1) -> INSERT INTO "ClubLeague" (club_league_name,team_region_id,club_country,club_division,club_prom_reg,club_first_qual,club_second_qual,club_third_qual,clas_direct) VALUES ('Admiral Bundesliga',4,17,'1D',2,1,2,1,'Y');
B12: 10 | C12: Algerian Ligue 2 | D12: Argelia | E12: Africa | F12: =INDEX(TeamRegion!B:B,MATCH(E12,TeamRegion!C:C,0)) -> 1 | G12: =INDEX(NationalTeams!B:B,MATCH(D12,NationalTeams!C:C,0)) -> 11 | H12: 2D | I12: 2 | J12: 0 | K12: 0 | L12: 0 | M12: N | O12: =_xlfn.CONCAT($O$1," ",$S$1,$B$1,$S$1," ",$Q$1,$C$2,$U$1,$F$2,$U$1,$G$2,$U$1,$H$2,$U$1,$I$2,$U$1,$J$2,$U$1,$K$2,$U$1,$L$2,$U$1,$M$2,$R$1,$P$1,$Q$1,$T$1,C12,$T$1,$U$1,F12,$U$1,G12,$U$1,$T$1,H12,$T$1,$U$1,I12,$U$1,J12,$U$1,K12,$U$1,L12,$U$1,$T$1,M12,$T$1,$R$1,$V$1) -> INSERT INTO "ClubLeague" (club_league_name,team_region_id,club_country,club_division,club_prom_reg,club_first_qual,club_second_qual,club_third_qual,clas_direct) VALUES ('Algerian Ligue 2',1,11,'2D',2,0,0,0,'N');
B13: 11 | C13: Algerian Ligue Professionnelle 1 | D13: Argelia | E13: Africa | F13: =INDEX(TeamRegion!B:B,MATCH(E13,TeamRegion!C:C,0)) -> 1 | G13: =INDEX(NationalTeams!B:B,MATCH(D13,NationalTeams!C:C,0)) -> 11 | H13: 1D | I13: 2 | J13: 2 | K13: 2 | L13: 0 | M13: Y | O13: =_xlfn.CONCAT($O$1," ",$S$1,$B$1,$S$1," ",$Q$1,$C$2,$U$1,$F$2,$U$1,$G$2,$U$1,$H$2,$U$1,$I$2,$U$1,$J$2,$U$1,$K$2,$U$1,$L$2,$U$1,$M$2,$R$1,$P$1,$Q$1,$T$1,C13,$T$1,$U$1,F13,$U$1,G13,$U$1,$T$1,H13,$T$1,$U$1,I13,$U$1,J13,$U$1,K13,$U$1,L13,$U$1,$T$1,M13,$T$1,$R$1,$V$1) -> INSERT INTO "ClubLeague" (club_league_name,team_region_id,club_country,club_division,club_prom_reg,club_first_qual,club_second_qual,club_third_qual,clas_direct) VALUES ('Algerian Ligue Professionnelle 1',1,11,'1D',2,2,2,0,'Y');
B14: 12 | C14: Allsvenskan | D14: Suecia | E14: Europa | F14: =INDEX(TeamRegion!B:B,MATCH(E14,TeamRegion!C:C,0)) -> 4 | G14: =INDEX(NationalTeams!B:B,MATCH(D14,NationalTeams!C:C,0)) -> 196 | H14: 1D | I14: 2 | J14: 1 | K14: 1 | L14: 1 | M14: N | O14: =_xlfn.CONCAT($O$1," ",$S$1,$B$1,$S$1," ",$Q$1,$C$2,$U$1,$F$2,$U$1,$G$2,$U$1,$H$2,$U$1,$I$2,$U$1,$J$2,$U$1,$K$2,$U$1,$L$2,$U$1,$M$2,$R$1,$P$1,$Q$1,$T$1,C14,$T$1,$U$1,F14,$U$1,G14,$U$1,$T$1,H14,$T$1,$U$1,I14,$U$1,J14,$U$1,K14,$U$1,L14,$U$1,$T$1,M14,$T$1,$R$1,$V$1) -> INSERT INTO "ClubLeague" (club_league_name,team_region_id,club_country,club_division,club_prom_reg,club_first_qual,club_second_qual,club_third_qual,clas_direct) VALUES ('Allsvenskan',4,196,'1D',2,1,1,1,'N');
... B215: 213 | C215: League 1 CON | D215: Congo | E215: Africa | F215: =INDEX(TeamRegion!B:B,MATCH(E215,TeamRegion!C:C,0)) -> 1 | G215: =INDEX(NationalTeams!B:B,MATCH(D215,NationalTeams!C:C,0)) -> 48 | H215: 1D | I215: 1 | J215: 1 | K215: 0 | L215: 0 | M215: Y | O215: =_xlfn.CONCAT($O$1," ",$S$1,$B$1,$S$1," ",$Q$1,$C$2,$U$1,$F$2,$U$1,$G$2,$U$1,$H$2,$U$1,$I$2,$U$1,$J$2,$U$1,$K$2,$U$1,$L$2,$U$1,$M$2,$R$1,$P$1,$Q$1,$T$1,C215,$T$1,$U$1,F215,$U$1,G215,$U$1,$T$1,H215,$T$1,$U$1,I215,$U$1,J215,$U$1,K215,$U$1,L215,$U$1,$T$1,M215,$T$1,$R$1,$V$1) -> INSERT INTO "ClubLeague" (club_league_name,team_region_id,club_country,club_division,club_prom_reg,club_first_qual,club_second_qual,club_third_qual,clas_direct) VALUES ('League 1 CON',1,48,'1D',1,1,0,0,'Y');

Sheet TeamRanks
C1: TeamRanks | H1: INSERT INTO | I1: VALUES | J1: ( | K1: ) | L1: " | M1: ' | N1: , | O1: ;
B2: team | C2: team_id | D2: sport | E2: team_sport_id | F2: team_rank
B3: Afganistan | C3: =INDEX(NationalTeams!B:B,MATCH(B3,NationalTeams!C:C,0)) -> 1 | D3: Futbol Masculino | E3: =INDEX(TeamSports!B:B,MATCH(D3,TeamSports!C:C,0)) -> 21 | F3: =INDEX(RanksTable!C:C,MATCH(B3,RanksTable!B:B,0)) -> 7 | H3: =_xlfn.CONCAT($H$1,$L$1,$C$1,$L$1," ",$J$1,$C$2,$N$1,$E$2,$N$1,$F$2,$K$1,$I$1,$J$1,C3,$N$1,E3,$N$1,F3,$K$1,$O$1) -> INSERT INTO "TeamRanks" (team_id,team_sport_id,team_rank) VALUES (1,21,7);
B4: Africa Stars | C4: =INDEX(NationalTeams!B:B,MATCH(B4,NationalTeams!C:C,0)) -> 2 | D4: Futbol Masculino | E4: =INDEX(TeamSports!B:B,MATCH(D4,TeamSports!C:C,0)) -> 21 | F4: =INDEX(RanksTable!C:C,MATCH(B4,RanksTable!B:B,0)) -> 7 | H4: =_xlfn.CONCAT($H$1,$L$1,$C$1,$L$1," ",$J$1,$C$2,$N$1,$E$2,$N$1,$F$2,$K$1,$I$1,$J$1,C4,$N$1,E4,$N$1,F4,$K$1,$O$1) -> INSERT INTO "TeamRanks" (team_id,team_sport_id,team_rank) VALUES (2,21,7);
B5: Albania | C5: =INDEX(NationalTeams!B:B,MATCH(B5,NationalTeams!C:C,0)) -> 3 | D5: Futbol Masculino | E5: =INDEX(TeamSports!B:B,MATCH(D5,TeamSports!C:C,0)) -> 21 | F5: =INDEX(RanksTable!C:C,MATCH(B5,RanksTable!B:B,0)) -> 4 | H5: =_xlfn.CONCAT($H$1,$L$1,$C$1,$L$1," ",$J$1,$C$2,$N$1,$E$2,$N$1,$F$2,$K$1,$I$1,$J$1,C5,$N$1,E5,$N$1,F5,$K$1,$O$1) -> INSERT INTO "TeamRanks" (team_id,team_sport_id,team_rank) VALUES (3,21,4);
B6: Alemania | C6: =INDEX(NationalTeams!B:B,MATCH(B6,NationalTeams!C:C,0)) -> 4 | D6: Futbol Masculino | E6: =INDEX(TeamSports!B:B,MATCH(D6,TeamSports!C:C,0)) -> 21 | F6: =INDEX(RanksTable!C:C,MATCH(B6,RanksTable!B:B,0)) -> 1 | H6: =_xlfn.CONCAT($H$1,$L$1,$C$1,$L$1," ",$J$1,$C$2,$N$1,$E$2,$N$1,$F$2,$K$1,$I$1,$J$1,C6,$N$1,E6,$N$1,F6,$K$1,$O$1) -> INSERT INTO "TeamRanks" (team_id,team_sport_id,team_rank) VALUES (4,21,1);
B7: America Stars | C7: =INDEX(NationalTeams!B:B,MATCH(B7,NationalTeams!C:C,0)) -> 5 | D7: Futbol Masculino | E7: =INDEX(TeamSports!B:B,MATCH(D7,TeamSports!C:C,0)) -> 21 | F7: =INDEX(RanksTable!C:C,MATCH(B7,RanksTable!B:B,0)) -> 7 | H7: =_xlfn.CONCAT($H$1,$L$1,$C$1,$L$1," ",$J$1,$C$2,$N$1,$E$2,$N$1,$F$2,$K$1,$I$1,$J$1,C7,$N$1,E7,$N$1,F7,$K$1,$O$1) -> INSERT INTO "TeamRanks" (team_id,team_sport_id,team_rank) VALUES (5,21,7);
B8: Andorra | C8: =INDEX(NationalTeams!B:B,MATCH(B8,NationalTeams!C:C,0)) -> 6 | D8: Futbol Masculino | E8: =INDEX(TeamSports!B:B,MATCH(D8,TeamSports!C:C,0)) -> 21 | F8: =INDEX(RanksTable!C:C,MATCH(B8,RanksTable!B:B,0)) -> 7 | H8: =_xlfn.CONCAT($H$1,$L$1,$C$1,$L$1," ",$J$1,$C$2,$N$1,$E$2,$N$1,$F$2,$K$1,$I$1,$J$1,C8,$N$1,E8,$N$1,F8,$K$1,$O$1) -> INSERT INTO "TeamRanks" (team_id,team_sport_id,team_rank) VALUES (6,21,7);
B9: Angola | C9: =INDEX(NationalTeams!B:B,MATCH(B9,NationalTeams!C:C,0)) -> 7 | D9: Futbol Masculino | E9: =INDEX(TeamSports!B:B,MATCH(D9,TeamSports!C:C,0)) -> 21 | F9: =INDEX(RanksTable!C:C,MATCH(B9,RanksTable!B:B,0)) -> 4 | H9: =_xlfn.CONCAT($H$1,$L$1,$C$1,$L$1," ",$J$1,$C$2,$N$1,$E$2,$N$1,$F$2,$K$1,$I$1,$J$1,C9,$N$1,E9,$N$1,F9,$K$1,$O$1) -> INSERT INTO "TeamRanks" (team_id,team_sport_id,team_rank) VALUES (7,21,4);
B10: Anguila | C10: =INDEX(NationalTeams!B:B,MATCH(B10,NationalTeams!C:C,0)) -> 8 | D10: Futbol Masculino | E10: =INDEX(TeamSports!B:B,MATCH(D10,TeamSports!C:C,0)) -> 21 | F10: =INDEX(RanksTable!C:C,MATCH(B10,RanksTable!B:B,0)) -> 7 | H10: =_xlfn.CONCAT($H$1,$L$1,$C$1,$L$1," ",$J$1,$C$2,$N$1,$E$2,$N$1,$F$2,$K$1,$I$1,$J$1,C10,$N$1,E10,$N$1,F10,$K$1,$O$1) -> INSERT INTO "TeamRanks" (team_id,team_sport_id,team_rank) VALUES (8,21,7);
B11: Antigua y Barbuda | C11: =INDEX(NationalTeams!B:B,MATCH(B11,NationalTeams!C:C,0)) -> 9 | D11: Futbol Masculino | E11: =INDEX(TeamSports!B:B,MATCH(D11,TeamSports!C:C,0)) -> 21 | F11: =INDEX(RanksTable!C:C,MATCH(B11,RanksTable!B:B,0)) -> 7 | H11: =_xlfn.CONCAT($H$1,$L$1,$C$1,$L$1," ",$J$1,$C$2,$N$1,$E$2,$N$1,$F$2,$K$1,$I$1,$J$1,C11,$N$1,E11,$N$1,F11,$K$1,$O$1) -> INSERT INTO "TeamRanks" (team_id,team_sport_id,team_rank) VALUES (9,21,7);
B12: Arabia Saudita | C12: =INDEX(NationalTeams!B:B,MATCH(B12,NationalTeams!C:C,0)) -> 10 | D12: Futbol Masculino | E12: =INDEX(TeamSports!B:B,MATCH(D12,TeamSports!C:C,0)) -> 21 | F12: =INDEX(RanksTable!C:C,MATCH(B12,RanksTable!B:B,0)) -> 3 | H12: =_xlfn.CONCAT($H$1,$L$1,$C$1,$L$1," ",$J$1,$C$2,$N$1,$E$2,$N$1,$F$2,$K$1,$I$1,$J$1,C12,$N$1,E12,$N$1,F12,$K$1,$O$1) -> INSERT INTO "TeamRanks" (team_id,team_sport_id,team_rank) VALUES (10,21,3);
B13: Argelia | C13: =INDEX(NationalTeams!B:B,MATCH(B13,NationalTeams!C:C,0)) -> 11 | D13: Futbol Masculino | E13: =INDEX(TeamSports!B:B,MATCH(D13,TeamSports!C:C,0)) -> 21 | F13: =INDEX(RanksTable!C:C,MATCH(B13,RanksTable!B:B,0)) -> 3 | H13: =_xlfn.CONCAT($H$1,$L$1,$C$1,$L$1," ",$J$1,$C$2,$N$1,$E$2,$N$1,$F$2,$K$1,$I$1,$J$1,C13,$N$1,E13,$N$1,F13,$K$1,$O$1) -> INSERT INTO "TeamRanks" (team_id,team_sport_id,team_rank) VALUES (11,21,3);
B14: Argentina | C14: =INDEX(NationalTeams!B:B,MATCH(B14,NationalTeams!C:C,0)) -> 12 | D14: Futbol Masculino | E14: =INDEX(TeamSports!B:B,MATCH(D14,TeamSports!C:C,0)) -> 21 | F14: =INDEX(RanksTable!C:C,MATCH(B14,RanksTable!B:B,0)) -> 1 | H14: =_xlfn.CONCAT($H$1,$L$1,$C$1,$L$1," ",$J$1,$C$2,$N$1,$E$2,$N$1,$F$2,$K$1,$I$1,$J$1,C14,$N$1,E14,$N$1,F14,$K$1,$O$1) -> INSERT INTO "TeamRanks" (team_id,team_sport_id,team_rank) VALUES (12,21,1);
... B225: Zimbaue | C225: =INDEX(NationalTeams!B:B,MATCH(B225,NationalTeams!C:C,0)) -> 223 | D225: Futbol Masculino | E225: =INDEX(TeamSports!B:B,MATCH(D225,TeamSports!C:C,0)) -> 21 | F225: =INDEX(RanksTable!C:C,MATCH(B225,RanksTable!B:B,0)) -> 6 | H225: =_xlfn.CONCAT($H$1,$L$1,$C$1,$L$1," ",$J$1,$C$2,$N$1,$E$2,$N$1,$F$2,$K$1,$I$1,$J$1,C225,$N$1,E225,$N$1,F225,$K$1,$O$1) -> INSERT INTO "TeamRanks" (team_id,team_sport_id,team_rank) VALUES (223,21,6);
B226: Afganistan Fem | C226: =INDEX(NationalTeams!B:B,MATCH(B226,NationalTeams!C:C,0)) -> 224 | D226: Futbol Femenino | E226: =INDEX(TeamSports!B:B,MATCH(D226,TeamSports!C:C,0)) -> 22 | F226: =INDEX(RanksTable!D:D,MATCH(B226,RanksTable!B:B,0)) -> 7 | H226: =_xlfn.CONCAT($H$1,$L$1,$C$1,$L$1," ",$J$1,$C$2,$N$1,$E$2,$N$1,$F$2,$K$1,$I$1,$J$1,C226,$N$1,E226,$N$1,F226,$K$1,$O$1) -> INSERT INTO "TeamRanks" (team_id,team_sport_id,team_rank) VALUES (224,22,7);
B227: Africa Stars Fem | C227: =INDEX(NationalTeams!B:B,MATCH(B227,NationalTeams!C:C,0)) -> 225 | D227: Futbol Femenino | E227: =INDEX(TeamSports!B:B,MATCH(D227,TeamSports!C:C,0)) -> 22 | F227: =INDEX(RanksTable!D:D,MATCH(B227,RanksTable!B:B,0)) -> 7 | H227: =_xlfn.CONCAT($H$1,$L$1,$C$1,$L$1," ",$J$1,$C$2,$N$1,$E$2,$N$1,$F$2,$K$1,$I$1,$J$1,C227,$N$1,E227,$N$1,F227,$K$1,$O$1) -> INSERT INTO "TeamRanks" (team_id,team_sport_id,team_rank) VALUES (225,22,7);
B228: Albania Fem | C228: =INDEX(NationalTeams!B:B,MATCH(B228,NationalTeams!C:C,0)) -> 226 | D228: Futbol Femenino | E228: =INDEX(TeamSports!B:B,MATCH(D228,TeamSports!C:C,0)) -> 22 | F228: =INDEX(RanksTable!D:D,MATCH(B228,RanksTable!B:B,0)) -> 4 | H228: =_xlfn.CONCAT($H$1,$L$1,$C$1,$L$1," ",$J$1,$C$2,$N$1,$E$2,$N$1,$F$2,$K$1,$I$1,$J$1,C228,$N$1,E228,$N$1,F228,$K$1,$O$1) -> INSERT INTO "TeamRanks" (team_id,team_sport_id,team_rank) VALUES (226,22,4);
B229: Alemania Fem | C229: =INDEX(NationalTeams!B:B,MATCH(B229,NationalTeams!C:C,0)) -> 227 | D229: Futbol Femenino | E229: =INDEX(TeamSports!B:B,MATCH(D229,TeamSports!C:C,0)) -> 22 | F229: =INDEX(RanksTable!D:D,MATCH(B229,RanksTable!B:B,0)) -> 1 | H229: =_xlfn.CONCAT($H$1,$L$1,$C$1,$L$1," ",$J$1,$C$2,$N$1,$E$2,$N$1,$F$2,$K$1,$I$1,$J$1,C229,$N$1,E229,$N$1,F229,$K$1,$O$1) -> INSERT INTO "TeamRanks" (team_id,team_sport_id,team_rank) VALUES (227,22,1);
B230: America Stars Fem | C230: =INDEX(NationalTeams!B:B,MATCH(B230,NationalTeams!C:C,0)) -> 228 | D230: Futbol Femenino | E230: =INDEX(TeamSports!B:B,MATCH(D230,TeamSports!C:C,0)) -> 22 | F230: =INDEX(RanksTable!D:D,MATCH(B230,RanksTable!B:B,0)) -> 7 | H230: =_xlfn.CONCAT($H$1,$L$1,$C$1,$L$1," ",$J$1,$C$2,$N$1,$E$2,$N$1,$F$2,$K$1,$I$1,$J$1,C230,$N$1,E230,$N$1,F230,$K$1,$O$1) -> INSERT INTO "TeamRanks" (team_id,team_sport_id,team_rank) VALUES (228,22,7);
B231: Andorra Fem | C231: =INDEX(NationalTeams!B:B,MATCH(B231,NationalTeams!C:C,0)) -> 229 | D231: Futbol Femenino | E231: =INDEX(TeamSports!B:B,MATCH(D231,TeamSports!C:C,0)) -> 22 | F231: =INDEX(RanksTable!D:D,MATCH(B231,RanksTable!B:B,0)) -> 7 | H231: =_xlfn.CONCAT($H$1,$L$1,$C$1,$L$1," ",$J$1,$C$2,$N$1,$E$2,$N$1,$F$2,$K$1,$I$1,$J$1,C231,$N$1,E231,$N$1,F231,$K$1,$O$1) -> INSERT INTO "TeamRanks" (team_id,team_sport_id,team_rank) VALUES (229,22,7);
B232: Angola Fem | C232: =INDEX(NationalTeams!B:B,MATCH(B232,NationalTeams!C:C,0)) -> 230 | D232: Futbol Femenino | E232: =INDEX(TeamSports!B:B,MATCH(D232,TeamSports!C:C,0)) -> 22 | F232: =INDEX(RanksTable!D:D,MATCH(B232,RanksTable!B:B,0)) -> 7 | H232: =_xlfn.CONCAT($H$1,$L$1,$C$1,$L$1," ",$J$1,$C$2,$N$1,$E$2,$N$1,$F$2,$K$1,$I$1,$J$1,C232,$N$1,E232,$N$1,F232,$K$1,$O$1) -> INSERT INTO "TeamRanks" (team_id,team_sport_id,team_rank) VALUES (230,22,7);
B233: Anguila Fem | C233: =INDEX(NationalTeams!B:B,MATCH(B233,NationalTeams!C:C,0)) -> 231 | D233: Futbol Femenino | E233: =INDEX(TeamSports!B:B,MATCH(D233,TeamSports!C:C,0)) -> 22 | F233: =INDEX(RanksTable!D:D,MATCH(B233,RanksTable!B:B,0)) -> 7 | H233: =_xlfn.CONCAT($H$1,$L$1,$C$1,$L$1," ",$J$1,$C$2,$N$1,$E$2,$N$1,$F$2,$K$1,$I$1,$J$1,C233,$N$1,E233,$N$1,F233,$K$1,$O$1) -> INSERT INTO "TeamRanks" (team_id,team_sport_id,team_rank) VALUES (231,22,7);
B234: Antigua y Barbuda Fem | C234: =INDEX(NationalTeams!B:B,MATCH(B234,NationalTeams!C:C,0)) -> 232 | D234: Futbol Femenino | E234: =INDEX(TeamSports!B:B,MATCH(D234,TeamSports!C:C,0)) -> 22 | F234: =INDEX(RanksTable!D:D,MATCH(B234,RanksTable!B:B,0)) -> 7 | H234: =_xlfn.CONCAT($H$1,$L$1,$C$1,$L$1," ",$J$1,$C$2,$N$1,$E$2,$N$1,$F$2,$K$1,$I$1,$J$1,C234,$N$1,E234,$N$1,F234,$K$1,$O$1) -> INSERT INTO "TeamRanks" (team_id,team_sport_id,team_rank) VALUES (232,22,7);
B235: Arabia Saudita Fem | C235: =INDEX(NationalTeams!B:B,MATCH(B235,NationalTeams!C:C,0)) -> 233 | D235: Futbol Femenino | E235: =INDEX(TeamSports!B:B,MATCH(D235,TeamSports!C:C,0)) -> 22 | F235: =INDEX(RanksTable!D:D,MATCH(B235,RanksTable!B:B,0)) -> 7 | H235: =_xlfn.CONCAT($H$1,$L$1,$C$1,$L$1," ",$J$1,$C$2,$N$1,$E$2,$N$1,$F$2,$K$1,$I$1,$J$1,C235,$N$1,E235,$N$1,F235,$K$1,$O$1) -> INSERT INTO "TeamRanks" (team_id,team_sport_id,team_rank) VALUES (233,22,7);
B236: Argelia Fem | C236: =INDEX(NationalTeams!B:B,MATCH(B236,NationalTeams!C:C,0)) -> 234 | D236: Futbol Femenino | E236: =INDEX(TeamSports!B:B,MATCH(D236,TeamSports!C:C,0)) -> 22 | F236: =INDEX(RanksTable!D:D,MATCH(B236,RanksTable!B:B,0)) -> 4 | H236: =_xlfn.CONCAT($H$1,$L$1,$C$1,$L$1," ",$J$1,$C$2,$N$1,$E$2,$N$1,$F$2,$K$1,$I$1,$J$1,C236,$N$1,E236,$N$1,F236,$K$1,$O$1) -> INSERT INTO "TeamRanks" (team_id,team_sport_id,team_rank) VALUES (234,22,4);
B237: Argentina Fem | C237: =INDEX(NationalTeams!B:B,MATCH(B237,NationalTeams!C:C,0)) -> 235 | D237: Futbol Femenino | E237: =INDEX(TeamSports!B:B,MATCH(D237,TeamSports!C:C,0)) -> 22 | F237: =INDEX(RanksTable!D:D,MATCH(B237,RanksTable!B:B,0)) -> 2 | H237: =_xlfn.CONCAT($H$1,$L$1,$C$1,$L$1," ",$J$1,$C$2,$N$1,$E$2,$N$1,$F$2,$K$1,$I$1,$J$1,C237,$N$1,E237,$N$1,F237,$K$1,$O$1) -> INSERT INTO "TeamRanks" (team_id,team_sport_id,team_rank) VALUES (235,22,2);
... B448: Zimbaue Fem | C448: =INDEX(NationalTeams!B:B,MATCH(B448,NationalTeams!C:C,0)) -> 446 | D448: Futbol Femenino | E448: =INDEX(TeamSports!B:B,MATCH(D448,TeamSports!C:C,0)) -> 22 | F448: =INDEX(RanksTable!D:D,MATCH(B448,RanksTable!B:B,0)) -> 6 | H448: =_xlfn.CONCAT($H$1,$L$1,$C$1,$L$1," ",$J$1,$C$2,$N$1,$E$2,$N$1,$F$2,$K$1,$I$1,$J$1,C448,$N$1,E448,$N$1,F448,$K$1,$O$1) -> INSERT INTO "TeamRanks" (team_id,team_sport_id,team_rank) VALUES (446,22,6);
B449: Afganistan | C449: =INDEX(NationalTeams!B:B,MATCH(B449,NationalTeams!C:C,0)) -> 1 | D449: Futsal Masculino | E449: =INDEX(TeamSports!B:B,MATCH(D449,TeamSports!C:C,0)) -> 23 | F449: =INDEX(RanksTable!E:E,MATCH(B449,RanksTable!B:B,0)) -> 3 | H449: =_xlfn.CONCAT($H$1,$L$1,$C$1,$L$1," ",$J$1,$C$2,$N$1,$E$2,$N$1,$F$2,$K$1,$I$1,$J$1,C449,$N$1,E449,$N$1,F449,$K$1,$O$1) -> INSERT INTO "TeamRanks" (team_id,team_sport_id,team_rank) VALUES (1,23,3);
B450: Africa Stars | C450: =INDEX(NationalTeams!B:B,MATCH(B450,NationalTeams!C:C,0)) -> 2 | D450: Futsal Masculino | E450: =INDEX(TeamSports!B:B,MATCH(D450,TeamSports!C:C,0)) -> 23 | F450: =INDEX(RanksTable!E:E,MATCH(B450,RanksTable!B:B,0)) -> 7 | H450: =_xlfn.CONCAT($H$1,$L$1,$C$1,$L$1," ",$J$1,$C$2,$N$1,$E$2,$N$1,$F$2,$K$1,$I$1,$J$1,C450,$N$1,E450,$N$1,F450,$K$1,$O$1) -> INSERT INTO "TeamRanks" (team_id,team_sport_id,team_rank) VALUES (2,23,7);
B451: Albania | C451: =INDEX(NationalTeams!B:B,MATCH(B451,NationalTeams!C:C,0)) -> 3 | D451: Futsal Masculino | E451: =INDEX(TeamSports!B:B,MATCH(D451,TeamSports!C:C,0)) -> 23 | F451: =INDEX(RanksTable!E:E,MATCH(B451,RanksTable!B:B,0)) -> 6 | H451: =_xlfn.CONCAT($H$1,$L$1,$C$1,$L$1," ",$J$1,$C$2,$N$1,$E$2,$N$1,$F$2,$K$1,$I$1,$J$1,C451,$N$1,E451,$N$1,F451,$K$1,$O$1) -> INSERT INTO "TeamRanks" (team_id,team_sport_id,team_rank) VALUES (3,23,6);
B452: Alemania | C452: =INDEX(NationalTeams!B:B,MATCH(B452,NationalTeams!C:C,0)) -> 4 | D452: Futsal Masculino | E452: =INDEX(TeamSports!B:B,MATCH(D452,TeamSports!C:C,0)) -> 23 | F452: =INDEX(RanksTable!E:E,MATCH(B452,RanksTable!B:B,0)) -> 4 | H452: =_xlfn.CONCAT($H$1,$L$1,$C$1,$L$1," ",$J$1,$C$2,$N$1,$E$2,$N$1,$F$2,$K$1,$I$1,$J$1,C452,$N$1,E452,$N$1,F452,$K$1,$O$1) -> INSERT INTO "TeamRanks" (team_id,team_sport_id,team_rank) VALUES (4,23,4);
B453: America Stars | C453: =INDEX(NationalTeams!B:B,MATCH(B453,NationalTeams!C:C,0)) -> 5 | D453: Futsal Masculino | E453: =INDEX(TeamSports!B:B,MATCH(D453,TeamSports!C:C,0)) -> 23 | F453: =INDEX(RanksTable!E:E,MATCH(B453,RanksTable!B:B,0)) -> 7 | H453: =_xlfn.CONCAT($H$1,$L$1,$C$1,$L$1," ",$J$1,$C$2,$N$1,$E$2,$N$1,$F$2,$K$1,$I$1,$J$1,C453,$N$1,E453,$N$1,F453,$K$1,$O$1) -> INSERT INTO "TeamRanks" (team_id,team_sport_id,team_rank) VALUES (5,23,7);
B454: Andorra | C454: =INDEX(NationalTeams!B:B,MATCH(B454,NationalTeams!C:C,0)) -> 6 | D454: Futsal Masculino | E454: =INDEX(TeamSports!B:B,MATCH(D454,TeamSports!C:C,0)) -> 23 | F454: =INDEX(RanksTable!E:E,MATCH(B454,RanksTable!B:B,0)) -> 4 | H454: =_xlfn.CONCAT($H$1,$L$1,$C$1,$L$1," ",$J$1,$C$2,$N$1,$E$2,$N$1,$F$2,$K$1,$I$1,$J$1,C454,$N$1,E454,$N$1,F454,$K$1,$O$1) -> INSERT INTO "TeamRanks" (team_id,team_sport_id,team_rank) VALUES (6,23,4);
B455: Angola | C455: =INDEX(NationalTeams!B:B,MATCH(B455,NationalTeams!C:C,0)) -> 7 | D455: Futsal Masculino | E455: =INDEX(TeamSports!B:B,MATCH(D455,TeamSports!C:C,0)) -> 23 | F455: =INDEX(RanksTable!E:E,MATCH(B455,RanksTable!B:B,0)) -> 4 | H455: =_xlfn.CONCAT($H$1,$L$1,$C$1,$L$1," ",$J$1,$C$2,$N$1,$E$2,$N$1,$F$2,$K$1,$I$1,$J$1,C455,$N$1,E455,$N$1,F455,$K$1,$O$1) -> INSERT INTO "TeamRanks" (team_id,team_sport_id,team_rank) VALUES (7,23,4);
B456: Anguila | C456: =INDEX(NationalTeams!B:B,MATCH(B456,NationalTeams!C:C,0)) -> 8 | D456: Futsal Masculino | E456: =INDEX(TeamSports!B:B,MATCH(D456,TeamSports!C:C,0)) -> 23 | F456: =INDEX(RanksTable!E:E,MATCH(B456,RanksTable!B:B,0)) -> 7 | H456: =_xlfn.CONCAT($H$1,$L$1,$C$1,$L$1," ",$J$1,$C$2,$N$1,$E$2,$N$1,$F$2,$K$1,$I$1,$J$1,C456,$N$1,E456,$N$1,F456,$K$1,$O$1) -> INSERT INTO "TeamRanks" (team_id,team_sport_id,team_rank) VALUES (8,23,7);
B457: Antigua y Barbuda | C457: =INDEX(NationalTeams!B:B,MATCH(B457,NationalTeams!C:C,0)) -> 9 | D457: Futsal Masculino | E457: =INDEX(TeamSports!B:B,MATCH(D457,TeamSports!C:C,0)) -> 23 | F457: =INDEX(RanksTable!E:E,MATCH(B457,RanksTable!B:B,0)) -> 7 | H457: =_xlfn.CONCAT($H$1,$L$1,$C$1,$L$1," ",$J$1,$C$2,$N$1,$E$2,$N$1,$F$2,$K$1,$I$1,$J$1,C457,$N$1,E457,$N$1,F457,$K$1,$O$1) -> INSERT INTO "TeamRanks" (team_id,team_sport_id,team_rank) VALUES (9,23,7);
B458: Arabia Saudita | C458: =INDEX(NationalTeams!B:B,MATCH(B458,NationalTeams!C:C,0)) -> 10 | D458: Futsal Masculino | E458: =INDEX(TeamSports!B:B,MATCH(D458,TeamSports!C:C,0)) -> 23 | F458: =INDEX(RanksTable!E:E,MATCH(B458,RanksTable!B:B,0)) -> 4 | H458: =_xlfn.CONCAT($H$1,$L$1,$C$1,$L$1," ",$J$1,$C$2,$N$1,$E$2,$N$1,$F$2,$K$1,$I$1,$J$1,C458,$N$1,E458,$N$1,F458,$K$1,$O$1) -> INSERT INTO "TeamRanks" (team_id,team_sport_id,team_rank) VALUES (10,23,4);
B459: Argelia | C459: =INDEX(NationalTeams!B:B,MATCH(B459,NationalTeams!C:C,0)) -> 11 | D459: Futsal Masculino | E459: =INDEX(TeamSports!B:B,MATCH(D459,TeamSports!C:C,0)) -> 23 | F459: =INDEX(RanksTable!E:E,MATCH(B459,RanksTable!B:B,0)) -> 6 | H459: =_xlfn.CONCAT($H$1,$L$1,$C$1,$L$1," ",$J$1,$C$2,$N$1,$E$2,$N$1,$F$2,$K$1,$I$1,$J$1,C459,$N$1,E459,$N$1,F459,$K$1,$O$1) -> INSERT INTO "TeamRanks" (team_id,team_sport_id,team_rank) VALUES (11,23,6);
B460: Argentina | C460: =INDEX(NationalTeams!B:B,MATCH(B460,NationalTeams!C:C,0)) -> 12 | D460: Futsal Masculino | E460: =INDEX(TeamSports!B:B,MATCH(D460,TeamSports!C:C,0)) -> 23 | F460: =INDEX(RanksTable!E:E,MATCH(B460,RanksTable!B:B,0)) -> 1 | H460: =_xlfn.CONCAT($H$1,$L$1,$C$1,$L$1," ",$J$1,$C$2,$N$1,$E$2,$N$1,$F$2,$K$1,$I$1,$J$1,C460,$N$1,E460,$N$1,F460,$K$1,$O$1) -> INSERT INTO "TeamRanks" (team_id,team_sport_id,team_rank) VALUES (12,23,1);
... B671: Zimbaue | C671: =INDEX(NationalTeams!B:B,MATCH(B671,NationalTeams!C:C,0)) -> 223 | D671: Futsal Masculino | E671: =INDEX(TeamSports!B:B,MATCH(D671,TeamSports!C:C,0)) -> 23 | F671: =INDEX(RanksTable!E:E,MATCH(B671,RanksTable!B:B,0)) -> 7 | H671: =_xlfn.CONCAT($H$1,$L$1,$C$1,$L$1," ",$J$1,$C$2,$N$1,$E$2,$N$1,$F$2,$K$1,$I$1,$J$1,C671,$N$1,E671,$N$1,F671,$K$1,$O$1) -> INSERT INTO "TeamRanks" (team_id,team_sport_id,team_rank) VALUES (223,23,7);
B672: Afganistan Fem | C672: =INDEX(NationalTeams!B:B,MATCH(B672,NationalTeams!C:C,0)) -> 224 | D672: Futsal Femenino | E672: =INDEX(TeamSports!B:B,MATCH(D672,TeamSports!C:C,0)) -> 24 | F672: =INDEX(RanksTable!F:F,MATCH(B672,RanksTable!B:B,0)) -> 5 | H672: =_xlfn.CONCAT($H$1,$L$1,$C$1,$L$1," ",$J$1,$C$2,$N$1,$E$2,$N$1,$F$2,$K$1,$I$1,$J$1,C672,$N$1,E672,$N$1,F672,$K$1,$O$1) -> INSERT INTO "TeamRanks" (team_id,team_sport_id,team_rank) VALUES (224,24,5);
B673: Africa Stars Fem | C673: =INDEX(NationalTeams!B:B,MATCH(B673,NationalTeams!C:C,0)) -> 225 | D673: Futsal Femenino | E673: =INDEX(TeamSports!B:B,MATCH(D673,TeamSports!C:C,0)) -> 24 | F673: =INDEX(RanksTable!F:F,MATCH(B673,RanksTable!B:B,0)) -> 7 | H673: =_xlfn.CONCAT($H$1,$L$1,$C$1,$L$1," ",$J$1,$C$2,$N$1,$E$2,$N$1,$F$2,$K$1,$I$1,$J$1,C673,$N$1,E673,$N$1,F673,$K$1,$O$1) -> INSERT INTO "TeamRanks" (team_id,team_sport_id,team_rank) VALUES (225,24,7);
B674: Albania Fem | C674: =INDEX(NationalTeams!B:B,MATCH(B674,NationalTeams!C:C,0)) -> 226 | D674: Futsal Femenino | E674: =INDEX(TeamSports!B:B,MATCH(D674,TeamSports!C:C,0)) -> 24 | F674: =INDEX(RanksTable!F:F,MATCH(B674,RanksTable!B:B,0)) -> 7 | H674: =_xlfn.CONCAT($H$1,$L$1,$C$1,$L$1," ",$J$1,$C$2,$N$1,$E$2,$N$1,$F$2,$K$1,$I$1,$J$1,C674,$N$1,E674,$N$1,F674,$K$1,$O$1) -> INSERT INTO "TeamRanks" (team_id,team_sport_id,team_rank) VALUES (226,24,7);
B675: Alemania Fem | C675: =INDEX(NationalTeams!B:B,MATCH(B675,NationalTeams!C:C,0)) -> 227 | D675: Futsal Femenino | E675: =INDEX(TeamSports!B:B,MATCH(D675,TeamSports!C:C,0)) -> 24 | F675: =INDEX(RanksTable!F:F,MATCH(B675,RanksTable!B:B,0)) -> 7 | H675: =_xlfn.CONCAT($H$1,$L$1,$C$1,$L$1," ",$J$1,$C$2,$N$1,$E$2,$N$1,$F$2,$K$1,$I$1,$J$1,C675,$N$1,E675,$N$1,F675,$K$1,$O$1) -> INSERT INTO "TeamRanks" (team_id,team_sport_id,team_rank) VALUES (227,24,7);
B676: America Stars Fem | C676: =INDEX(NationalTeams!B:B,MATCH(B676,NationalTeams!C:C,0)) -> 228 | D676: Futsal Femenino | E676: =INDEX(TeamSports!B:B,MATCH(D676,TeamSports!C:C,0)) -> 24 | F676: =INDEX(RanksTable!F:F,MATCH(B676,RanksTable!B:B,0)) -> 7 | H676: =_xlfn.CONCAT($H$1,$L$1,$C$1,$L$1," ",$J$1,$C$2,$N$1,$E$2,$N$1,$F$2,$K$1,$I$1,$J$1,C676,$N$1,E676,$N$1,F676,$K$1,$O$1) -> INSERT INTO "TeamRanks" (team_id,team_sport_id,team_rank) VALUES (228,24,7);
B677: Andorra Fem | C677: =INDEX(NationalTeams!B:B,MATCH(B677,NationalTeams!C:C,0)) -> 229 | D677: Futsal Femenino | E677: =INDEX(TeamSports!B:B,MATCH(D677,TeamSports!C:C,0)) -> 24 | F677: =INDEX(RanksTable!F:F,MATCH(B677,RanksTable!B:B,0)) -> 7 | H677: =_xlfn.CONCAT($H$1,$L$1,$C$1,$L$1," ",$J$1,$C$2,$N$1,$E$2,$N$1,$F$2,$K$1,$I$1,$J$1,C677,$N$1,E677,$N$1,F677,$K$1,$O$1) -> INSERT INTO "TeamRanks" (team_id,team_sport_id,team_rank) VALUES (229,24,7);
B678: Angola Fem | C678: =INDEX(NationalTeams!B:B,MATCH(B678,NationalTeams!C:C,0)) -> 230 | D678: Futsal Femenino | E678: =INDEX(TeamSports!B:B,MATCH(D678,TeamSports!C:C,0)) -> 24 | F678: =INDEX(RanksTable!F:F,MATCH(B678,RanksTable!B:B,0)) -> 7 | H678: =_xlfn.CONCAT($H$1,$L$1,$C$1,$L$1," ",$J$1,$C$2,$N$1,$E$2,$N$1,$F$2,$K$1,$I$1,$J$1,C678,$N$1,E678,$N$1,F678,$K$1,$O$1) -> INSERT INTO "TeamRanks" (team_id,team_sport_id,team_rank) VALUES (230,24,7);
B679: Anguila Fem | C679: =INDEX(NationalTeams!B:B,MATCH(B679,NationalTeams!C:C,0)) -> 231 | D679: Futsal Femenino | E679: =INDEX(TeamSports!B:B,MATCH(D679,TeamSports!C:C,0)) -> 24 | F679: =INDEX(RanksTable!F:F,MATCH(B679,RanksTable!B:B,0)) -> 7 | H679: =_xlfn.CONCAT($H$1,$L$1,$C$1,$L$1," ",$J$1,$C$2,$N$1,$E$2,$N$1,$F$2,$K$1,$I$1,$J$1,C679,$N$1,E679,$N$1,F679,$K$1,$O$1) -> INSERT INTO "TeamRanks" (team_id,team_sport_id,team_rank) VALUES (231,24,7);
B680: Antigua y Barbuda Fem | C680: =INDEX(NationalTeams!B:B,MATCH(B680,NationalTeams!C:C,0)) -> 232 | D680: Futsal Femenino | E680: =INDEX(TeamSports!B:B,MATCH(D680,TeamSports!C:C,0)) -> 24 | F680: =INDEX(RanksTable!F:F,MATCH(B680,RanksTable!B:B,0)) -> 7 | H680: =_xlfn.CONCAT($H$1,$L$1,$C$1,$L$1," ",$J$1,$C$2,$N$1,$E$2,$N$1,$F$2,$K$1,$I$1,$J$1,C680,$N$1,E680,$N$1,F680,$K$1,$O$1) -> INSERT INTO "TeamRanks" (team_id,team_sport_id,team_rank) VALUES (232,24,7);
B681: Arabia Saudita Fem | C681: =INDEX(NationalTeams!B:B,MATCH(B681,NationalTeams!C:C,0)) -> 233 | D681: Futsal Femenino | E681: =INDEX(TeamSports!B:B,MATCH(D681,TeamSports!C:C,0)) -> 24 | F681: =INDEX(RanksTable!F:F,MATCH(B681,RanksTable!B:B,0)) -> 5 | H681: =_xlfn.CONCAT($H$1,$L$1,$C$1,$L$1," ",$J$1,$C$2,$N$1,$E$2,$N$1,$F$2,$K$1,$I$1,$J$1,C681,$N$1,E681,$N$1,F681,$K$1,$O$1) -> INSERT INTO "TeamRanks" (team_id,team_sport_id,team_rank) VALUES (233,24,5);
B682: Argelia Fem | C682: =INDEX(NationalTeams!B:B,MATCH(B682,NationalTeams!C:C,0)) -> 234 | D682: Futsal Femenino | E682: =INDEX(TeamSports!B:B,MATCH(D682,TeamSports!C:C,0)) -> 24 | F682: =INDEX(RanksTable!F:F,MATCH(B682,RanksTable!B:B,0)) -> 7 | H682: =_xlfn.CONCAT($H$1,$L$1,$C$1,$L$1," ",$J$1,$C$2,$N$1,$E$2,$N$1,$F$2,$K$1,$I$1,$J$1,C682,$N$1,E682,$N$1,F682,$K$1,$O$1) -> INSERT INTO "TeamRanks" (team_id,team_sport_id,team_rank) VALUES (234,24,7);
B683: Argentina Fem | C683: =INDEX(NationalTeams!B:B,MATCH(B683,NationalTeams!C:C,0)) -> 235 | D683: Futsal Femenino | E683: =INDEX(TeamSports!B:B,MATCH(D683,TeamSports!C:C,0)) -> 24 | F683: =INDEX(RanksTable!F:F,MATCH(B683,RanksTable!B:B,0)) -> 1 | H683: =_xlfn.CONCAT($H$1,$L$1,$C$1,$L$1," ",$J$1,$C$2,$N$1,$E$2,$N$1,$F$2,$K$1,$I$1,$J$1,C683,$N$1,E683,$N$1,F683,$K$1,$O$1) -> INSERT INTO "TeamRanks" (team_id,team_sport_id,team_rank) VALUES (235,24,1);
... B894: Zimbaue Fem | C894: =INDEX(NationalTeams!B:B,MATCH(B894,NationalTeams!C:C,0)) -> 446 | D894: Futsal Femenino | E894: =INDEX(TeamSports!B:B,MATCH(D894,TeamSports!C:C,0)) -> 24 | F894: =INDEX(RanksTable!F:F,MATCH(B894,RanksTable!B:B,0)) -> 7 | H894: =_xlfn.CONCAT($H$1,$L$1,$C$1,$L$1," ",$J$1,$C$2,$N$1,$E$2,$N$1,$F$2,$K$1,$I$1,$J$1,C894,$N$1,E894,$N$1,F894,$K$1,$O$1) -> INSERT INTO "TeamRanks" (team_id,team_sport_id,team_rank) VALUES (446,24,7);
B895: Afganistan | C895: =INDEX(NationalTeams!B:B,MATCH(B895,NationalTeams!C:C,0)) -> 1 | D895: Volleyball Masculino | E895: =INDEX(TeamSports!B:B,MATCH(D895,TeamSports!C:C,0)) -> 25 | F895: =INDEX(RanksTable!G:G,MATCH(B895,RanksTable!B:B,0)) -> 7 | H895: =_xlfn.CONCAT($H$1,$L$1,$C$1,$L$1," ",$J$1,$C$2,$N$1,$E$2,$N$1,$F$2,$K$1,$I$1,$J$1,C895,$N$1,E895,$N$1,F895,$K$1,$O$1) -> INSERT INTO "TeamRanks" (team_id,team_sport_id,team_rank) VALUES (1,25,7);
B896: Africa Stars | C896: =INDEX(NationalTeams!B:B,MATCH(B896,NationalTeams!C:C,0)) -> 2 | D896: Volleyball Masculino | E896: =INDEX(TeamSports!B:B,MATCH(D896,TeamSports!C:C,0)) -> 25 | F896: =INDEX(RanksTable!G:G,MATCH(B896,RanksTable!B:B,0)) -> 7 | H896: =_xlfn.CONCAT($H$1,$L$1,$C$1,$L$1," ",$J$1,$C$2,$N$1,$E$2,$N$1,$F$2,$K$1,$I$1,$J$1,C896,$N$1,E896,$N$1,F896,$K$1,$O$1) -> INSERT INTO "TeamRanks" (team_id,team_sport_id,team_rank) VALUES (2,25,7);
B897: Albania | C897: =INDEX(NationalTeams!B:B,MATCH(B897,NationalTeams!C:C,0)) -> 3 | D897: Volleyball Masculino | E897: =INDEX(TeamSports!B:B,MATCH(D897,TeamSports!C:C,0)) -> 25 | F897: =INDEX(RanksTable!G:G,MATCH(B897,RanksTable!B:B,0)) -> 7 | H897: =_xlfn.CONCAT($H$1,$L$1,$C$1,$L$1," ",$J$1,$C$2,$N$1,$E$2,$N$1,$F$2,$K$1,$I$1,$J$1,C897,$N$1,E897,$N$1,F897,$K$1,$O$1) -> INSERT INTO "TeamRanks" (team_id,team_sport_id,team_rank) VALUES (3,25,7);
B898: Alemania | C898: =INDEX(NationalTeams!B:B,MATCH(B898,NationalTeams!C:C,0)) -> 4 | D898: Volleyball Masculino | E898: =INDEX(TeamSports!B:B,MATCH(D898,TeamSports!C:C,0)) -> 25 | F898: =INDEX(RanksTable!G:G,MATCH(B898,RanksTable!B:B,0)) -> 2 | H898: =_xlfn.CONCAT($H$1,$L$1,$C$1,$L$1," ",$J$1,$C$2,$N$1,$E$2,$N$1,$F$2,$K$1,$I$1,$J$1,C898,$N$1,E898,$N$1,F898,$K$1,$O$1) -> INSERT INTO "TeamRanks" (team_id,team_sport_id,team_rank) VALUES (4,25,2);
B899: America Stars | C899: =INDEX(NationalTeams!B:B,MATCH(B899,NationalTeams!C:C,0)) -> 5 | D899: Volleyball Masculino | E899: =INDEX(TeamSports!B:B,MATCH(D899,TeamSports!C:C,0)) -> 25 | F899: =INDEX(RanksTable!G:G,MATCH(B899,RanksTable!B:B,0)) -> 7 | H899: =_xlfn.CONCAT($H$1,$L$1,$C$1,$L$1," ",$J$1,$C$2,$N$1,$E$2,$N$1,$F$2,$K$1,$I$1,$J$1,C899,$N$1,E899,$N$1,F899,$K$1,$O$1) -> INSERT INTO "TeamRanks" (team_id,team_sport_id,team_rank) VALUES (5,25,7);
B900: Andorra | C900: =INDEX(NationalTeams!B:B,MATCH(B900,NationalTeams!C:C,0)) -> 6 | D900: Volleyball Masculino | E900: =INDEX(TeamSports!B:B,MATCH(D900,TeamSports!C:C,0)) -> 25 | F900: =INDEX(RanksTable!G:G,MATCH(B900,RanksTable!B:B,0)) -> 7 | H900: =_xlfn.CONCAT($H$1,$L$1,$C$1,$L$1," ",$J$1,$C$2,$N$1,$E$2,$N$1,$F$2,$K$1,$I$1,$J$1,C900,$N$1,E900,$N$1,F900,$K$1,$O$1) -> INSERT INTO "TeamRanks" (team_id,team_sport_id,team_rank) VALUES (6,25,7);
B901: Angola | C901: =INDEX(NationalTeams!B:B,MATCH(B901,NationalTeams!C:C,0)) -> 7 | D901: Volleyball Masculino | E901: =INDEX(TeamSports!B:B,MATCH(D901,TeamSports!C:C,0)) -> 25 | F901: =INDEX(RanksTable!G:G,MATCH(B901,RanksTable!B:B,0)) -> 7 | H901: =_xlfn.CONCAT($H$1,$L$1,$C$1,$L$1," ",$J$1,$C$2,$N$1,$E$2,$N$1,$F$2,$K$1,$I$1,$J$1,C901,$N$1,E901,$N$1,F901,$K$1,$O$1) -> INSERT INTO "TeamRanks" (team_id,team_sport_id,team_rank) VALUES (7,25,7);
B902: Anguila | C902: =INDEX(NationalTeams!B:B,MATCH(B902,NationalTeams!C:C,0)) -> 8 | D902: Volleyball Masculino | E902: =INDEX(TeamSports!B:B,MATCH(D902,TeamSports!C:C,0)) -> 25 | F902: =INDEX(RanksTable!G:G,MATCH(B902,RanksTable!B:B,0)) -> 7 | H902: =_xlfn.CONCAT($H$1,$L$1,$C$1,$L$1," ",$J$1,$C$2,$N$1,$E$2,$N$1,$F$2,$K$1,$I$1,$J$1,C902,$N$1,E902,$N$1,F902,$K$1,$O$1) -> INSERT INTO "TeamRanks" (team_id,team_sport_id,team_rank) VALUES (8,25,7);
B903: Antigua y Barbuda | C903: =INDEX(NationalTeams!B:B,MATCH(B903,NationalTeams!C:C,0)) -> 9 | D903: Volleyball Masculino | E903: =INDEX(TeamSports!B:B,MATCH(D903,TeamSports!C:C,0)) -> 25 | F903: =INDEX(RanksTable!G:G,MATCH(B903,RanksTable!B:B,0)) -> 5 | H903: =_xlfn.CONCAT($H$1,$L$1,$C$1,$L$1," ",$J$1,$C$2,$N$1,$E$2,$N$1,$F$2,$K$1,$I$1,$J$1,C903,$N$1,E903,$N$1,F903,$K$1,$O$1) -> INSERT INTO "TeamRanks" (team_id,team_sport_id,team_rank) VALUES (9,25,5);
B904: Arabia Saudita | C904: =INDEX(NationalTeams!B:B,MATCH(B904,NationalTeams!C:C,0)) -> 10 | D904: Volleyball Masculino | E904: =INDEX(TeamSports!B:B,MATCH(D904,TeamSports!C:C,0)) -> 25 | F904: =INDEX(RanksTable!G:G,MATCH(B904,RanksTable!B:B,0)) -> 5 | H904: =_xlfn.CONCAT($H$1,$L$1,$C$1,$L$1," ",$J$1,$C$2,$N$1,$E$2,$N$1,$F$2,$K$1,$I$1,$J$1,C904,$N$1,E904,$N$1,F904,$K$1,$O$1) -> INSERT INTO "TeamRanks" (team_id,team_sport_id,team_rank) VALUES (10,25,5);
B905: Argelia | C905: =INDEX(NationalTeams!B:B,MATCH(B905,NationalTeams!C:C,0)) -> 11 | D905: Volleyball Masculino | E905: =INDEX(TeamSports!B:B,MATCH(D905,TeamSports!C:C,0)) -> 25 | F905: =INDEX(RanksTable!G:G,MATCH(B905,RanksTable!B:B,0)) -> 6 | H905: =_xlfn.CONCAT($H$1,$L$1,$C$1,$L$1," ",$J$1,$C$2,$N$1,$E$2,$N$1,$F$2,$K$1,$I$1,$J$1,C905,$N$1,E905,$N$1,F905,$K$1,$O$1) -> INSERT INTO "TeamRanks" (team_id,team_sport_id,team_rank) VALUES (11,25,6);
B906: Argentina | C906: =INDEX(NationalTeams!B:B,MATCH(B906,NationalTeams!C:C,0)) -> 12 | D906: Volleyball Masculino | E906: =INDEX(TeamSports!B:B,MATCH(D906,TeamSports!C:C,0)) -> 25 | F906: =INDEX(RanksTable!G:G,MATCH(B906,RanksTable!B:B,0)) -> 1 | H906: =_xlfn.CONCAT($H$1,$L$1,$C$1,$L$1," ",$J$1,$C$2,$N$1,$E$2,$N$1,$F$2,$K$1,$I$1,$J$1,C906,$N$1,E906,$N$1,F906,$K$1,$O$1) -> INSERT INTO "TeamRanks" (team_id,team_sport_id,team_rank) VALUES (12,25,1);
... B1117: Zimbaue | C1117: =INDEX(NationalTeams!B:B,MATCH(B1117,NationalTeams!C:C,0)) -> 223 | D1117: Volleyball Masculino | E1117: =INDEX(TeamSports!B:B,MATCH(D1117,TeamSports!C:C,0)) -> 25 | F1117: =INDEX(RanksTable!G:G,MATCH(B1117,RanksTable!B:B,0)) -> 7 | H1117: =_xlfn.CONCAT($H$1,$L$1,$C$1,$L$1," ",$J$1,$C$2,$N$1,$E$2,$N$1,$F$2,$K$1,$I$1,$J$1,C1117,$N$1,E1117,$N$1,F1117,$K$1,$O$1) -> INSERT INTO "TeamRanks" (team_id,team_sport_id,team_rank) VALUES (223,25,7);
B1118: Afganistan Fem | C1118: =INDEX(NationalTeams!B:B,MATCH(B1118,NationalTeams!C:C,0)) -> 224 | D1118: Volleyball Femenino | E1118: =INDEX(TeamSports!B:B,MATCH(D1118,TeamSports!C:C,0)) -> 47 | F1118: =INDEX(RanksTable!U:U,MATCH(B1118,RanksTable!B:B,0)) -> 7 | H1118: =_xlfn.CONCAT($H$1,$L$1,$C$1,$L$1," ",$J$1,$C$2,$N$1,$E$2,$N$1,$F$2,$K$1,$I$1,$J$1,C1118,$N$1,E1118,$N$1,F1118,$K$1,$O$1) -> INSERT INTO "TeamRanks" (team_id,team_sport_id,team_rank) VALUES (224,47,7);
B1119: Africa Stars Fem | C1119: =INDEX(NationalTeams!B:B,MATCH(B1119,NationalTeams!C:C,0)) -> 225 | D1119: Volleyball Femenino | E1119: =INDEX(TeamSports!B:B,MATCH(D1119,TeamSports!C:C,0)) -> 47 | F1119: =INDEX(RanksTable!U:U,MATCH(B1119,RanksTable!B:B,0)) -> 7 | H1119: =_xlfn.CONCAT($H$1,$L$1,$C$1,$L$1," ",$J$1,$C$2,$N$1,$E$2,$N$1,$F$2,$K$1,$I$1,$J$1,C1119,$N$1,E1119,$N$1,F1119,$K$1,$O$1) -> INSERT INTO "TeamRanks" (team_id,team_sport_id,team_rank) VALUES (225,47,7);
B1120: Albania Fem | C1120: =INDEX(NationalTeams!B:B,MATCH(B1120,NationalTeams!C:C,0)) -> 226 | D1120: Volleyball Femenino | E1120: =INDEX(TeamSports!B:B,MATCH(D1120,TeamSports!C:C,0)) -> 47 | F1120: =INDEX(RanksTable!U:U,MATCH(B1120,RanksTable!B:B,0)) -> 7 | H1120: =_xlfn.CONCAT($H$1,$L$1,$C$1,$L$1," ",$J$1,$C$2,$N$1,$E$2,$N$1,$F$2,$K$1,$I$1,$J$1,C1120,$N$1,E1120,$N$1,F1120,$K$1,$O$1) -> INSERT INTO "TeamRanks" (team_id,team_sport_id,team_rank) VALUES (226,47,7);
B1121: Alemania Fem | C1121: =INDEX(NationalTeams!B:B,MATCH(B1121,NationalTeams!C:C,0)) -> 227 | D1121: Volleyball Femenino | E1121: =INDEX(TeamSports!B:B,MATCH(D1121,TeamSports!C:C,0)) -> 47 | F1121: =INDEX(RanksTable!U:U,MATCH(B1121,RanksTable!B:B,0)) -> 2 | H1121: =_xlfn.CONCAT($H$1,$L$1,$C$1,$L$1," ",$J$1,$C$2,$N$1,$E$2,$N$1,$F$2,$K$1,$I$1,$J$1,C1121,$N$1,E1121,$N$1,F1121,$K$1,$O$1) -> INSERT INTO "TeamRanks" (team_id,team_sport_id,team_rank) VALUES (227,47,2);
B1122: America Stars Fem | C1122: =INDEX(NationalTeams!B:B,MATCH(B1122,NationalTeams!C:C,0)) -> 228 | D1122: Volleyball Femenino | E1122: =INDEX(TeamSports!B:B,MATCH(D1122,TeamSports!C:C,0)) -> 47 | F1122: =INDEX(RanksTable!U:U,MATCH(B1122,RanksTable!B:B,0)) -> 7 | H1122: =_xlfn.CONCAT($H$1,$L$1,$C$1,$L$1," ",$J$1,$C$2,$N$1,$E$2,$N$1,$F$2,$K$1,$I$1,$J$1,C1122,$N$1,E1122,$N$1,F1122,$K$1,$O$1) -> INSERT INTO "TeamRanks" (team_id,team_sport_id,team_rank) VALUES (228,47,7);
B1123: Andorra Fem | C1123: =INDEX(NationalTeams!B:B,MATCH(B1123,NationalTeams!C:C,0)) -> 229 | D1123: Volleyball Femenino | E1123: =INDEX(TeamSports!B:B,MATCH(D1123,TeamSports!C:C,0)) -> 47 | F1123: =INDEX(RanksTable!U:U,MATCH(B1123,RanksTable!B:B,0)) -> 7 | H1123: =_xlfn.CONCAT($H$1,$L$1,$C$1,$L$1," ",$J$1,$C$2,$N$1,$E$2,$N$1,$F$2,$K$1,$I$1,$J$1,C1123,$N$1,E1123,$N$1,F1123,$K$1,$O$1) -> INSERT INTO "TeamRanks" (team_id,team_sport_id,team_rank) VALUES (229,47,7);
B1124: Angola Fem | C1124: =INDEX(NationalTeams!B:B,MATCH(B1124,NationalTeams!C:C,0)) -> 230 | D1124: Volleyball Femenino | E1124: =INDEX(TeamSports!B:B,MATCH(D1124,TeamSports!C:C,0)) -> 47 | F1124: =INDEX(RanksTable!U:U,MATCH(B1124,RanksTable!B:B,0)) -> 7 | H1124: =_xlfn.CONCAT($H$1,$L$1,$C$1,$L$1," ",$J$1,$C$2,$N$1,$E$2,$N$1,$F$2,$K$1,$I$1,$J$1,C1124,$N$1,E1124,$N$1,F1124,$K$1,$O$1) -> INSERT INTO "TeamRanks" (team_id,team_sport_id,team_rank) VALUES (230,47,7);
B1125: Anguila Fem | C1125: =INDEX(NationalTeams!B:B,MATCH(B1125,NationalTeams!C:C,0)) -> 231 | D1125: Volleyball Femenino | E1125: =INDEX(TeamSports!B:B,MATCH(D1125,TeamSports!C:C,0)) -> 47 | F1125: =INDEX(RanksTable!U:U,MATCH(B1125,RanksTable!B:B,0)) -> 7 | H1125: =_xlfn.CONCAT($H$1,$L$1,$C$1,$L$1," ",$J$1,$C$2,$N$1,$E$2,$N$1,$F$2,$K$1,$I$1,$J$1,C1125,$N$1,E1125,$N$1,F1125,$K$1,$O$1) -> INSERT INTO "TeamRanks" (team_id,team_sport_id,team_rank) VALUES (231,47,7);
B1126: Antigua y Barbuda Fem | C1126: =INDEX(NationalTeams!B:B,MATCH(B1126,NationalTeams!C:C,0)) -> 232 | D1126: Volleyball Femenino | E1126: =INDEX(TeamSports!B:B,MATCH(D1126,TeamSports!C:C,0)) -> 47 | F1126: =INDEX(RanksTable!U:U,MATCH(B1126,RanksTable!B:B,0)) -> 5 | H1126: =_xlfn.CONCAT($H$1,$L$1,$C$1,$L$1," ",$J$1,$C$2,$N$1,$E$2,$N$1,$F$2,$K$1,$I$1,$J$1,C1126,$N$1,E1126,$N$1,F1126,$K$1,$O$1) -> INSERT INTO "TeamRanks" (team_id,team_sport_id,team_rank) VALUES (232,47,5);
B1127: Arabia Saudita Fem | C1127: =INDEX(NationalTeams!B:B,MATCH(B1127,NationalTeams!C:C,0)) -> 233 | D1127: Volleyball Femenino | E1127: =INDEX(TeamSports!B:B,MATCH(D1127,TeamSports!C:C,0)) -> 47 | F1127: =INDEX(RanksTable!U:U,MATCH(B1127,RanksTable!B:B,0)) -> 7 | H1127: =_xlfn.CONCAT($H$1,$L$1,$C$1,$L$1," ",$J$1,$C$2,$N$1,$E$2,$N$1,$F$2,$K$1,$I$1,$J$1,C1127,$N$1,E1127,$N$1,F1127,$K$1,$O$1) -> INSERT INTO "TeamRanks" (team_id,team_sport_id,team_rank) VALUES (233,47,7);
B1128: Argelia Fem | C1128: =INDEX(NationalTeams!B:B,MATCH(B1128,NationalTeams!C:C,0)) -> 234 | D1128: Volleyball Femenino | E1128: =INDEX(TeamSports!B:B,MATCH(D1128,TeamSports!C:C,0)) -> 47 | F1128: =INDEX(RanksTable!U:U,MATCH(B1128,RanksTable!B:B,0)) -> 6 | H1128: =_xlfn.CONCAT($H$1,$L$1,$C$1,$L$1," ",$J$1,$C$2,$N$1,$E$2,$N$1,$F$2,$K$1,$I$1,$J$1,C1128,$N$1,E1128,$N$1,F1128,$K$1,$O$1) -> INSERT INTO "TeamRanks" (team_id,team_sport_id,team_rank) VALUES (234,47,6);
B1129: Argentina Fem | C1129: =INDEX(NationalTeams!B:B,MATCH(B1129,NationalTeams!C:C,0)) -> 235 | D1129: Volleyball Femenino | E1129: =INDEX(TeamSports!B:B,MATCH(D1129,TeamSports!C:C,0)) -> 47 | F1129: =INDEX(RanksTable!U:U,MATCH(B1129,RanksTable!B:B,0)) -> 3 | H1129: =_xlfn.CONCAT($H$1,$L$1,$C$1,$L$1," ",$J$1,$C$2,$N$1,$E$2,$N$1,$F$2,$K$1,$I$1,$J$1,C1129,$N$1,E1129,$N$1,F1129,$K$1,$O$1) -> INSERT INTO "TeamRanks" (team_id,team_sport_id,team_rank) VALUES (235,47,3);
... B1340: Zimbaue Fem | C1340: =INDEX(NationalTeams!B:B,MATCH(B1340,NationalTeams!C:C,0)) -> 446 | D1340: Volleyball Femenino | E1340: =INDEX(TeamSports!B:B,MATCH(D1340,TeamSports!C:C,0)) -> 47 | F1340: =INDEX(RanksTable!U:U,MATCH(B1340,RanksTable!B:B,0)) -> 7 | H1340: =_xlfn.CONCAT($H$1,$L$1,$C$1,$L$1," ",$J$1,$C$2,$N$1,$E$2,$N$1,$F$2,$K$1,$I$1,$J$1,C1340,$N$1,E1340,$N$1,F1340,$K$1,$O$1) -> INSERT INTO "TeamRanks" (team_id,team_sport_id,team_rank) VALUES (446,47,7);
B1341: Afganistan | C1341: =INDEX(NationalTeams!B:B,MATCH(B1341,NationalTeams!C:C,0)) -> 1 | D1341: Basketball Masculino | E1341: =INDEX(TeamSports!B:B,MATCH(D1341,TeamSports!C:C,0)) -> 26 | F1341: =INDEX(RanksTable!H:H,MATCH(B1341,RanksTable!B:B,0)) -> 7 | H1341: =_xlfn.CONCAT($H$1,$L$1,$C$1,$L$1," ",$J$1,$C$2,$N$1,$E$2,$N$1,$F$2,$K$1,$I$1,$J$1,C1341,$N$1,E1341,$N$1,F1341,$K$1,$O$1) -> INSERT INTO "TeamRanks" (team_id,team_sport_id,team_rank) VALUES (1,26,7);
B1342: Africa Stars | C1342: =INDEX(NationalTeams!B:B,MATCH(B1342,NationalTeams!C:C,0)) -> 2 | D1342: Basketball Masculino | E1342: =INDEX(TeamSports!B:B,MATCH(D1342,TeamSports!C:C,0)) -> 26 | F1342: =INDEX(RanksTable!H:H,MATCH(B1342,RanksTable!B:B,0)) -> 7 | H1342: =_xlfn.CONCAT($H$1,$L$1,$C$1,$L$1," ",$J$1,$C$2,$N$1,$E$2,$N$1,$F$2,$K$1,$I$1,$J$1,C1342,$N$1,E1342,$N$1,F1342,$K$1,$O$1) -> INSERT INTO "TeamRanks" (team_id,team_sport_id,team_rank) VALUES (2,26,7);
B1343: Albania | C1343: =INDEX(NationalTeams!B:B,MATCH(B1343,NationalTeams!C:C,0)) -> 3 | D1343: Basketball Masculino | E1343: =INDEX(TeamSports!B:B,MATCH(D1343,TeamSports!C:C,0)) -> 26 | F1343: =INDEX(RanksTable!H:H,MATCH(B1343,RanksTable!B:B,0)) -> 5 | H1343: =_xlfn.CONCAT($H$1,$L$1,$C$1,$L$1," ",$J$1,$C$2,$N$1,$E$2,$N$1,$F$2,$K$1,$I$1,$J$1,C1343,$N$1,E1343,$N$1,F1343,$K$1,$O$1) -> INSERT INTO "TeamRanks" (team_id,team_sport_id,team_rank) VALUES (3,26,5);
B1344: Alemania | C1344: =INDEX(NationalTeams!B:B,MATCH(B1344,NationalTeams!C:C,0)) -> 4 | D1344: Basketball Masculino | E1344: =INDEX(TeamSports!B:B,MATCH(D1344,TeamSports!C:C,0)) -> 26 | F1344: =INDEX(RanksTable!H:H,MATCH(B1344,RanksTable!B:B,0)) -> 1 | H1344: =_xlfn.CONCAT($H$1,$L$1,$C$1,$L$1," ",$J$1,$C$2,$N$1,$E$2,$N$1,$F$2,$K$1,$I$1,$J$1,C1344,$N$1,E1344,$N$1,F1344,$K$1,$O$1) -> INSERT INTO "TeamRanks" (team_id,team_sport_id,team_rank) VALUES (4,26,1);
B1345: America Stars | C1345: =INDEX(NationalTeams!B:B,MATCH(B1345,NationalTeams!C:C,0)) -> 5 | D1345: Basketball Masculino | E1345: =INDEX(TeamSports!B:B,MATCH(D1345,TeamSports!C:C,0)) -> 26 | F1345: =INDEX(RanksTable!H:H,MATCH(B1345,RanksTable!B:B,0)) -> 7 | H1345: =_xlfn.CONCAT($H$1,$L$1,$C$1,$L$1," ",$J$1,$C$2,$N$1,$E$2,$N$1,$F$2,$K$1,$I$1,$J$1,C1345,$N$1,E1345,$N$1,F1345,$K$1,$O$1) -> INSERT INTO "TeamRanks" (team_id,team_sport_id,team_rank) VALUES (5,26,7);
B1346: Andorra | C1346: =INDEX(NationalTeams!B:B,MATCH(B1346,NationalTeams!C:C,0)) -> 6 | D1346: Basketball Masculino | E1346: =INDEX(TeamSports!B:B,MATCH(D1346,TeamSports!C:C,0)) -> 26 | F1346: =INDEX(RanksTable!H:H,MATCH(B1346,RanksTable!B:B,0)) -> 5 | H1346: =_xlfn.CONCAT($H$1,$L$1,$C$1,$L$1," ",$J$1,$C$2,$N$1,$E$2,$N$1,$F$2,$K$1,$I$1,$J$1,C1346,$N$1,E1346,$N$1,F1346,$K$1,$O$1) -> INSERT INTO "TeamRanks" (team_id,team_sport_id,team_rank) VALUES (6,26,5);
B1347: Angola | C1347: =INDEX(NationalTeams!B:B,MATCH(B1347,NationalTeams!C:C,0)) -> 7 | D1347: Basketball Masculino | E1347: =INDEX(TeamSports!B:B,MATCH(D1347,TeamSports!C:C,0)) -> 26 | F1347: =INDEX(RanksTable!H:H,MATCH(B1347,RanksTable!B:B,0)) -> 3 | H1347: =_xlfn.CONCAT($H$1,$L$1,$C$1,$L$1," ",$J$1,$C$2,$N$1,$E$2,$N$1,$F$2,$K$1,$I$1,$J$1,C1347,$N$1,E1347,$N$1,F1347,$K$1,$O$1) -> INSERT INTO "TeamRanks" (team_id,team_sport_id,team_rank) VALUES (7,26,3);
B1348: Anguila | C1348: =INDEX(NationalTeams!B:B,MATCH(B1348,NationalTeams!C:C,0)) -> 8 | D1348: Basketball Masculino | E1348: =INDEX(TeamSports!B:B,MATCH(D1348,TeamSports!C:C,0)) -> 26 | F1348: =INDEX(RanksTable!H:H,MATCH(B1348,RanksTable!B:B,0)) -> 7 | H1348: =_xlfn.CONCAT($H$1,$L$1,$C$1,$L$1," ",$J$1,$C$2,$N$1,$E$2,$N$1,$F$2,$K$1,$I$1,$J$1,C1348,$N$1,E1348,$N$1,F1348,$K$1,$O$1) -> INSERT INTO "TeamRanks" (team_id,team_sport_id,team_rank) VALUES (8,26,7);
B1349: Antigua y Barbuda | C1349: =INDEX(NationalTeams!B:B,MATCH(B1349,NationalTeams!C:C,0)) -> 9 | D1349: Basketball Masculino | E1349: =INDEX(TeamSports!B:B,MATCH(D1349,TeamSports!C:C,0)) -> 26 | F1349: =INDEX(RanksTable!H:H,MATCH(B1349,RanksTable!B:B,0)) -> 6 | H1349: =_xlfn.CONCAT($H$1,$L$1,$C$1,$L$1," ",$J$1,$C$2,$N$1,$E$2,$N$1,$F$2,$K$1,$I$1,$J$1,C1349,$N$1,E1349,$N$1,F1349,$K$1,$O$1) -> INSERT INTO "TeamRanks" (team_id,team_sport_id,team_rank) VALUES (9,26,6);
B1350: Arabia Saudita | C1350: =INDEX(NationalTeams!B:B,MATCH(B1350,NationalTeams!C:C,0)) -> 10 | D1350: Basketball Masculino | E1350: =INDEX(TeamSports!B:B,MATCH(D1350,TeamSports!C:C,0)) -> 26 | F1350: =INDEX(RanksTable!H:H,MATCH(B1350,RanksTable!B:B,0)) -> 4 | H1350: =_xlfn.CONCAT($H$1,$L$1,$C$1,$L$1," ",$J$1,$C$2,$N$1,$E$2,$N$1,$F$2,$K$1,$I$1,$J$1,C1350,$N$1,E1350,$N$1,F1350,$K$1,$O$1) -> INSERT INTO "TeamRanks" (team_id,team_sport_id,team_rank) VALUES (10,26,4);
B1351: Argelia | C1351: =INDEX(NationalTeams!B:B,MATCH(B1351,NationalTeams!C:C,0)) -> 11 | D1351: Basketball Masculino | E1351: =INDEX(TeamSports!B:B,MATCH(D1351,TeamSports!C:C,0)) -> 26 | F1351: =INDEX(RanksTable!H:H,MATCH(B1351,RanksTable!B:B,0)) -> 6 | H1351: =_xlfn.CONCAT($H$1,$L$1,$C$1,$L$1," ",$J$1,$C$2,$N$1,$E$2,$N$1,$F$2,$K$1,$I$1,$J$1,C1351,$N$1,E1351,$N$1,F1351,$K$1,$O$1) -> INSERT INTO "TeamRanks" (team_id,team_sport_id,team_rank) VALUES (11,26,6);
B1352: Argentina | C1352: =INDEX(NationalTeams!B:B,MATCH(B1352,NationalTeams!C:C,0)) -> 12 | D1352: Basketball Masculino | E1352: =INDEX(TeamSports!B:B,MATCH(D1352,TeamSports!C:C,0)) -> 26 | F1352: =INDEX(RanksTable!H:H,MATCH(B1352,RanksTable!B:B,0)) -> 1 | H1352: =_xlfn.CONCAT($H$1,$L$1,$C$1,$L$1," ",$J$1,$C$2,$N$1,$E$2,$N$1,$F$2,$K$1,$I$1,$J$1,C1352,$N$1,E1352,$N$1,F1352,$K$1,$O$1) -> INSERT INTO "TeamRanks" (team_id,team_sport_id,team_rank) VALUES (12,26,1);
... B1563: Zimbaue | C1563: =INDEX(NationalTeams!B:B,MATCH(B1563,NationalTeams!C:C,0)) -> 223 | D1563: Basketball Masculino | E1563: =INDEX(TeamSports!B:B,MATCH(D1563,TeamSports!C:C,0)) -> 26 | F1563: =INDEX(RanksTable!H:H,MATCH(B1563,RanksTable!B:B,0)) -> 6 | H1563: =_xlfn.CONCAT($H$1,$L$1,$C$1,$L$1," ",$J$1,$C$2,$N$1,$E$2,$N$1,$F$2,$K$1,$I$1,$J$1,C1563,$N$1,E1563,$N$1,F1563,$K$1,$O$1) -> INSERT INTO "TeamRanks" (team_id,team_sport_id,team_rank) VALUES (223,26,6);
B1564: Afganistan Fem | C1564: =INDEX(NationalTeams!B:B,MATCH(B1564,NationalTeams!C:C,0)) -> 224 | D1564: Basketball Femenino | E1564: =INDEX(TeamSports!B:B,MATCH(D1564,TeamSports!C:C,0)) -> 48 | F1564: =INDEX(RanksTable!V:V,MATCH(B1564,RanksTable!B:B,0)) -> 7 | H1564: =_xlfn.CONCAT($H$1,$L$1,$C$1,$L$1," ",$J$1,$C$2,$N$1,$E$2,$N$1,$F$2,$K$1,$I$1,$J$1,C1564,$N$1,E1564,$N$1,F1564,$K$1,$O$1) -> INSERT INTO "TeamRanks" (team_id,team_sport_id,team_rank) VALUES (224,48,7);
B1565: Africa Stars Fem | C1565: =INDEX(NationalTeams!B:B,MATCH(B1565,NationalTeams!C:C,0)) -> 225 | D1565: Basketball Femenino | E1565: =INDEX(TeamSports!B:B,MATCH(D1565,TeamSports!C:C,0)) -> 48 | F1565: =INDEX(RanksTable!V:V,MATCH(B1565,RanksTable!B:B,0)) -> 7 | H1565: =_xlfn.CONCAT($H$1,$L$1,$C$1,$L$1," ",$J$1,$C$2,$N$1,$E$2,$N$1,$F$2,$K$1,$I$1,$J$1,C1565,$N$1,E1565,$N$1,F1565,$K$1,$O$1) -> INSERT INTO "TeamRanks" (team_id,team_sport_id,team_rank) VALUES (225,48,7);
B1566: Albania Fem | C1566: =INDEX(NationalTeams!B:B,MATCH(B1566,NationalTeams!C:C,0)) -> 226 | D1566: Basketball Femenino | E1566: =INDEX(TeamSports!B:B,MATCH(D1566,TeamSports!C:C,0)) -> 48 | F1566: =INDEX(RanksTable!V:V,MATCH(B1566,RanksTable!B:B,0)) -> 5 | H1566: =_xlfn.CONCAT($H$1,$L$1,$C$1,$L$1," ",$J$1,$C$2,$N$1,$E$2,$N$1,$F$2,$K$1,$I$1,$J$1,C1566,$N$1,E1566,$N$1,F1566,$K$1,$O$1) -> INSERT INTO "TeamRanks" (team_id,team_sport_id,team_rank) VALUES (226,48,5);
B1567: Alemania Fem | C1567: =INDEX(NationalTeams!B:B,MATCH(B1567,NationalTeams!C:C,0)) -> 227 | D1567: Basketball Femenino | E1567: =INDEX(TeamSports!B:B,MATCH(D1567,TeamSports!C:C,0)) -> 48 | F1567: =INDEX(RanksTable!V:V,MATCH(B1567,RanksTable!B:B,0)) -> 2 | H1567: =_xlfn.CONCAT($H$1,$L$1,$C$1,$L$1," ",$J$1,$C$2,$N$1,$E$2,$N$1,$F$2,$K$1,$I$1,$J$1,C1567,$N$1,E1567,$N$1,F1567,$K$1,$O$1) -> INSERT INTO "TeamRanks" (team_id,team_sport_id,team_rank) VALUES (227,48,2);
B1568: America Stars Fem | C1568: =INDEX(NationalTeams!B:B,MATCH(B1568,NationalTeams!C:C,0)) -> 228 | D1568: Basketball Femenino | E1568: =INDEX(TeamSports!B:B,MATCH(D1568,TeamSports!C:C,0)) -> 48 | F1568: =INDEX(RanksTable!V:V,MATCH(B1568,RanksTable!B:B,0)) -> 7 | H1568: =_xlfn.CONCAT($H$1,$L$1,$C$1,$L$1," ",$J$1,$C$2,$N$1,$E$2,$N$1,$F$2,$K$1,$I$1,$J$1,C1568,$N$1,E1568,$N$1,F1568,$K$1,$O$1) -> INSERT INTO "TeamRanks" (team_id,team_sport_id,team_rank) VALUES (228,48,7);
B1569: Andorra Fem | C1569: =INDEX(NationalTeams!B:B,MATCH(B1569,NationalTeams!C:C,0)) -> 229 | D1569: Basketball Femenino | E1569: =INDEX(TeamSports!B:B,MATCH(D1569,TeamSports!C:C,0)) -> 48 | F1569: =INDEX(RanksTable!V:V,MATCH(B1569,RanksTable!B:B,0)) -> 6 | H1569: =_xlfn.CONCAT($H$1,$L$1,$C$1,$L$1," ",$J$1,$C$2,$N$1,$E$2,$N$1,$F$2,$K$1,$I$1,$J$1,C1569,$N$1,E1569,$N$1,F1569,$K$1,$O$1) -> INSERT INTO "TeamRanks" (team_id,team_sport_id,team_rank) VALUES (229,48,6);
B1570: Angola Fem | C1570: =INDEX(NationalTeams!B:B,MATCH(B1570,NationalTeams!C:C,0)) -> 230 | D1570: Basketball Femenino | E1570: =INDEX(TeamSports!B:B,MATCH(D1570,TeamSports!C:C,0)) -> 48 | F1570: =INDEX(RanksTable!V:V,MATCH(B1570,RanksTable!B:B,0)) -> 4 | H1570: =_xlfn.CONCAT($H$1,$L$1,$C$1,$L$1," ",$J$1,$C$2,$N$1,$E$2,$N$1,$F$2,$K$1,$I$1,$J$1,C1570,$N$1,E1570,$N$1,F1570,$K$1,$O$1) -> INSERT INTO "TeamRanks" (team_id,team_sport_id,team_rank) VALUES (230,48,4);
...

Sheet SportsRecords
B1: SportsRecords | O1: INSERT INTO | P1: VALUES | Q1: ( | R1: ) | S1: " | T1: ' | U1: , | V1: ;
B2: sp_record_id | C2: sp_record_name | E2: sp_record_best | I2: sp_record_last | J2: campo_busqueda | K2: sport_class | L2: sport_rules | M2: team_sport_id
B3: SP_001 | C3: 100m Masculino | E3: 9.58 | I3: 10.538 | J3: Atletismo | K3: T | M3: =INDEX(TeamSports!B:B,MATCH(J3,TeamSports!C:C,0)) -> 1 | O3: =_xlfn.CONCAT($O$1,$S$1,$B$1,$S$1," ",$Q$1,$B$2,$U$1,$C$2,$U$1,$E$2,$U$1,$I$2,$U$1,$K$2,$U$1,$M$2,$R$1,$P$1,$Q$1,$T$1,B3,$T$1,$U$1,$T$1,C3,$T$1,$U$1,SUBSTITUTE(E3,",","."),$U$1,SUBSTITUTE(I3,",","."),$U$1,$T$1,K3,$T$1,$U$1,M3,$R$1,$V$1) -> INSERT INTO "SportsRecords" (sp_record_id,sp_record_name,sp_record_best,sp_record_last,sport_class,team_sport_id) VALUES ('SP_001','100m Masculino',9.58,10.538,'T',1);
B4: SP_002 | C4: 200m Masculino | E4: 19.19 | I4: 21.109 | J4: Atletismo | K4: T | M4: =INDEX(TeamSports!B:B,MATCH(J4,TeamSports!C:C,0)) -> 1 | O4: =_xlfn.CONCAT($O$1,$S$1,$B$1,$S$1," ",$Q$1,$B$2,$U$1,$C$2,$U$1,$E$2,$U$1,$I$2,$U$1,$K$2,$U$1,$M$2,$R$1,$P$1,$Q$1,$T$1,B4,$T$1,$U$1,$T$1,C4,$T$1,$U$1,SUBSTITUTE(E4,",","."),$U$1,SUBSTITUTE(I4,",","."),$U$1,$T$1,K4,$T$1,$U$1,M4,$R$1,$V$1) -> INSERT INTO "SportsRecords" (sp_record_id,sp_record_name,sp_record_best,sp_record_last,sport_class,team_sport_id) VALUES ('SP_002','200m Masculino',19.19,21.109,'T',1);
B5: SP_003 | C5: 400m Masculino | E5: 43.03 | I5: 47.333 | J5: Atletismo | K5: T | M5: =INDEX(TeamSports!B:B,MATCH(J5,TeamSports!C:C,0)) -> 1 | O5: =_xlfn.CONCAT($O$1,$S$1,$B$1,$S$1," ",$Q$1,$B$2,$U$1,$C$2,$U$1,$E$2,$U$1,$I$2,$U$1,$K$2,$U$1,$M$2,$R$1,$P$1,$Q$1,$T$1,B5,$T$1,$U$1,$T$1,C5,$T$1,$U$1,SUBSTITUTE(E5,",","."),$U$1,SUBSTITUTE(I5,",","."),$U$1,$T$1,K5,$T$1,$U$1,M5,$R$1,$V$1) -> INSERT INTO "SportsRecords" (sp_record_id,sp_record_name,sp_record_best,sp_record_last,sport_class,team_sport_id) VALUES ('SP_003','400m Masculino',43.03,47.333,'T',1);
B6: SP_004 | C6: 800m Masculino | E6: 100.91 | I6: 111.001 | J6: Atletismo | K6: T | M6: =INDEX(TeamSports!B:B,MATCH(J6,TeamSports!C:C,0)) -> 1 | O6: =_xlfn.CONCAT($O$1,$S$1,$B$1,$S$1," ",$Q$1,$B$2,$U$1,$C$2,$U$1,$E$2,$U$1,$I$2,$U$1,$K$2,$U$1,$M$2,$R$1,$P$1,$Q$1,$T$1,B6,$T$1,$U$1,$T$1,C6,$T$1,$U$1,SUBSTITUTE(E6,",","."),$U$1,SUBSTITUTE(I6,",","."),$U$1,$T$1,K6,$T$1,$U$1,M6,$R$1,$V$1) -> INSERT INTO "SportsRecords" (sp_record_id,sp_record_name,sp_record_best,sp_record_last,sport_class,team_sport_id) VALUES ('SP_004','800m Masculino',100.91,111.001,'T',1);
B7: SP_005 | C7: 1500m Masculino | E7: 206 | I7: 226.6 | J7: Atletismo | K7: T | M7: =INDEX(TeamSports!B:B,MATCH(J7,TeamSports!C:C,0)) -> 1 | O7: =_xlfn.CONCAT($O$1,$S$1,$B$1,$S$1," ",$Q$1,$B$2,$U$1,$C$2,$U$1,$E$2,$U$1,$I$2,$U$1,$K$2,$U$1,$M$2,$R$1,$P$1,$Q$1,$T$1,B7,$T$1,$U$1,$T$1,C7,$T$1,$U$1,SUBSTITUTE(E7,",","."),$U$1,SUBSTITUTE(I7,",","."),$U$1,$T$1,K7,$T$1,$U$1,M7,$R$1,$V$1) -> INSERT INTO "SportsRecords" (sp_record_id,sp_record_name,sp_record_best,sp_record_last,sport_class,team_sport_id) VALUES ('SP_005','1500m Masculino',206,226.6,'T',1);
B8: SP_006 | C8: 5000m Masculino | E8: 755.36 | I8: 830.896 | J8: Atletismo | K8: T | M8: =INDEX(TeamSports!B:B,MATCH(J8,TeamSports!C:C,0)) -> 1 | O8: =_xlfn.CONCAT($O$1,$S$1,$B$1,$S$1," ",$Q$1,$B$2,$U$1,$C$2,$U$1,$E$2,$U$1,$I$2,$U$1,$K$2,$U$1,$M$2,$R$1,$P$1,$Q$1,$T$1,B8,$T$1,$U$1,$T$1,C8,$T$1,$U$1,SUBSTITUTE(E8,",","."),$U$1,SUBSTITUTE(I8,",","."),$U$1,$T$1,K8,$T$1,$U$1,M8,$R$1,$V$1) -> INSERT INTO "SportsRecords" (sp_record_id,sp_record_name,sp_record_best,sp_record_last,sport_class,team_sport_id) VALUES ('SP_006','5000m Masculino',755.36,830.896,'T',1);
B9: SP_007 | C9: 10000m Masculino | E9: 1571 | I9: 1728.1 | J9: Atletismo | K9: T | M9: =INDEX(TeamSports!B:B,MATCH(J9,TeamSports!C:C,0)) -> 1 | O9: =_xlfn.CONCAT($O$1,$S$1,$B$1,$S$1," ",$Q$1,$B$2,$U$1,$C$2,$U$1,$E$2,$U$1,$I$2,$U$1,$K$2,$U$1,$M$2,$R$1,$P$1,$Q$1,$T$1,B9,$T$1,$U$1,$T$1,C9,$T$1,$U$1,SUBSTITUTE(E9,",","."),$U$1,SUBSTITUTE(I9,",","."),$U$1,$T$1,K9,$T$1,$U$1,M9,$R$1,$V$1) -> INSERT INTO "SportsRecords" (sp_record_id,sp_record_name,sp_record_best,sp_record_last,sport_class,team_sport_id) VALUES ('SP_007','10000m Masculino',1571,1728.1,'T',1);
B10: SP_008 | C10: 110m Vallas Masculino | E10: 12.8 | I10: 14.08 | J10: Atletismo | K10: T | M10: =INDEX(TeamSports!B:B,MATCH(J10,TeamSports!C:C,0)) -> 1 | O10: =_xlfn.CONCAT($O$1,$S$1,$B$1,$S$1," ",$Q$1,$B$2,$U$1,$C$2,$U$1,$E$2,$U$1,$I$2,$U$1,$K$2,$U$1,$M$2,$R$1,$P$1,$Q$1,$T$1,B10,$T$1,$U$1,$T$1,C10,$T$1,$U$1,SUBSTITUTE(E10,",","."),$U$1,SUBSTITUTE(I10,",","."),$U$1,$T$1,K10,$T$1,$U$1,M10,$R$1,$V$1) -> INSERT INTO "SportsRecords" (sp_record_id,sp_record_name,sp_record_best,sp_record_last,sport_class,team_sport_id) VALUES ('SP_008','110m Vallas Masculino',12.8,14.08,'T',1);
B11: SP_009 | C11: 400m Vallas Masculino | E11: 45.94 | I11: 50.534 | J11: Atletismo | K11: T | M11: =INDEX(TeamSports!B:B,MATCH(J11,TeamSports!C:C,0)) -> 1 | O11: =_xlfn.CONCAT($O$1,$S$1,$B$1,$S$1," ",$Q$1,$B$2,$U$1,$C$2,$U$1,$E$2,$U$1,$I$2,$U$1,$K$2,$U$1,$M$2,$R$1,$P$1,$Q$1,$T$1,B11,$T$1,$U$1,$T$1,C11,$T$1,$U$1,SUBSTITUTE(E11,",","."),$U$1,SUBSTITUTE(I11,",","."),$U$1,$T$1,K11,$T$1,$U$1,M11,$R$1,$V$1) -> INSERT INTO "SportsRecords" (sp_record_id,sp_record_name,sp_record_best,sp_record_last,sport_class,team_sport_id) VALUES ('SP_009','400m Vallas Masculino',45.94,50.534,'T',1);
B12: SP_010 | C12: 3000m Obstáculos Masculino | E12: 472.11 | I12: 519.321 | J12: Atletismo | K12: T | M12: =INDEX(TeamSports!B:B,MATCH(J12,TeamSports!C:C,0)) -> 1 | O12: =_xlfn.CONCAT($O$1,$S$1,$B$1,$S$1," ",$Q$1,$B$2,$U$1,$C$2,$U$1,$E$2,$U$1,$I$2,$U$1,$K$2,$U$1,$M$2,$R$1,$P$1,$Q$1,$T$1,B12,$T$1,$U$1,$T$1,C12,$T$1,$U$1,SUBSTITUTE(E12,",","."),$U$1,SUBSTITUTE(I12,",","."),$U$1,$T$1,K12,$T$1,$U$1,M12,$R$1,$V$1) -> INSERT INTO "SportsRecords" (sp_record_id,sp_record_name,sp_record_best,sp_record_last,sport_class,team_sport_id) VALUES ('SP_010','3000m Obstáculos Masculino',472.11,519.321,'T',1);
B13: SP_011 | C13: 20km Marcha Masculino | E13: 4570 | I13: 5027 | J13: Atletismo | K13: T | M13: =INDEX(TeamSports!B:B,MATCH(J13,TeamSports!C:C,0)) -> 1 | O13: =_xlfn.CONCAT($O$1,$S$1,$B$1,$S$1," ",$Q$1,$B$2,$U$1,$C$2,$U$1,$E$2,$U$1,$I$2,$U$1,$K$2,$U$1,$M$2,$R$1,$P$1,$Q$1,$T$1,B13,$T$1,$U$1,$T$1,C13,$T$1,$U$1,SUBSTITUTE(E13,",","."),$U$1,SUBSTITUTE(I13,",","."),$U$1,$T$1,K13,$T$1,$U$1,M13,$R$1,$V$1) -> INSERT INTO "SportsRecords" (sp_record_id,sp_record_name,sp_record_best,sp_record_last,sport_class,team_sport_id) VALUES ('SP_011','20km Marcha Masculino',4570,5027,'T',1);
B14: SP_012 | C14: 35km Marcha Masculino | E14: 8443 | I14: 9287.3 | J14: Atletismo | K14: T | M14: =INDEX(TeamSports!B:B,MATCH(J14,TeamSports!C:C,0)) -> 1 | O14: =_xlfn.CONCAT($O$1,$S$1,$B$1,$S$1," ",$Q$1,$B$2,$U$1,$C$2,$U$1,$E$2,$U$1,$I$2,$U$1,$K$2,$U$1,$M$2,$R$1,$P$1,$Q$1,$T$1,B14,$T$1,$U$1,$T$1,C14,$T$1,$U$1,SUBSTITUTE(E14,",","."),$U$1,SUBSTITUTE(I14,",","."),$U$1,$T$1,K14,$T$1,$U$1,M14,$R$1,$V$1) -> INSERT INTO "SportsRecords" (sp_record_id,sp_record_name,sp_record_best,sp_record_last,sport_class,team_sport_id) VALUES ('SP_012','35km Marcha Masculino',8443,9287.3,'T',1);
... B95: SP_093 | C95: Trampolín masculino | E95: 0 | I95: 0 | J95: Gimnasia en Trampolin | K95: P | M95: =INDEX(TeamSports!B:B,MATCH(J95,TeamSports!C:C,0)) -> 9 | O95: =_xlfn.CONCAT($O$1,$S$1,$B$1,$S$1," ",$Q$1,$B$2,$U$1,$C$2,$U$1,$E$2,$U$1,$I$2,$U$1,$K$2,$U$1,$M$2,$R$1,$P$1,$Q$1,$T$1,B95,$T$1,$U$1,$T$1,C95,$T$1,$U$1,SUBSTITUTE(E95,",","."),$U$1,SUBSTITUTE(I95,",","."),$U$1,$T$1,K95,$T$1,$U$1,M95,$R$1,$V$1) -> INSERT INTO "SportsRecords" (sp_record_id,sp_record_name,sp_record_best,sp_record_last,sport_class,team_sport_id) VALUES ('SP_093','Trampolín masculino',0,0,'P',9);
B96: SP_094 | C96: Trampolín por equipo masculino | E96: 0 | F96: 0 | G96: 0 | H96: 0 | I96: 0 | J96: Gimnasia en Trampolin | K96: P | M96: =INDEX(TeamSports!B:B,MATCH(J96,TeamSports!C:C,0)) -> 9 | O96: =_xlfn.CONCAT($O$1,$S$1,$B$1,$S$1," ",$Q$1,$B$2,$U$1,$C$2,$U$1,$E$2,$U$1,$I$2,$U$1,$K$2,$U$1,$M$2,$R$1,$P$1,$Q$1,$T$1,B96,$T$1,$U$1,$T$1,C96,$T$1,$U$1,SUBSTITUTE(E96,",","."),$U$1,SUBSTITUTE(I96,",","."),$U$1,$T$1,K96,$T$1,$U$1,M96,$R$1,$V$1) -> INSERT INTO "SportsRecords" (sp_record_id,sp_record_name,sp_record_best,sp_record_last,sport_class,team_sport_id) VALUES ('SP_094','Trampolín por equipo masculino',0,0,'P',9);
B97: SP_095 | C97: Trampolín sincronizado masculino | E97: 0 | F97: 0 | G97: 0 | H97: 0 | I97: 0 | J97: Gimnasia en Trampolin | K97: P | M97: =INDEX(TeamSports!B:B,MATCH(J97,TeamSports!C:C,0)) -> 9 | O97: =_xlfn.CONCAT($O$1,$S$1,$B$1,$S$1," ",$Q$1,$B$2,$U$1,$C$2,$U$1,$E$2,$U$1,$I$2,$U$1,$K$2,$U$1,$M$2,$R$1,$P$1,$Q$1,$T$1,B97,$T$1,$U$1,$T$1,C97,$T$1,$U$1,SUBSTITUTE(E97,",","."),$U$1,SUBSTITUTE(I97,",","."),$U$1,$T$1,K97,$T$1,$U$1,M97,$R$1,$V$1) -> INSERT INTO "SportsRecords" (sp_record_id,sp_record_name,sp_record_best,sp_record_last,sport_class,team_sport_id) VALUES ('SP_095','Trampolín sincronizado masculino',0,0,'P',9);
B98: SP_096 | C98: Acrobático masculino | E98: 0 | F98: 0 | G98: 0 | H98: 0 | I98: 0 | J98: Gimnasia en Trampolin | K98: P | M98: =INDEX(TeamSports!B:B,MATCH(J98,TeamSports!C:C,0)) -> 9 | O98: =_xlfn.CONCAT($O$1,$S$1,$B$1,$S$1," ",$Q$1,$B$2,$U$1,$C$2,$U$1,$E$2,$U$1,$I$2,$U$1,$K$2,$U$1,$M$2,$R$1,$P$1,$Q$1,$T$1,B98,$T$1,$U$1,$T$1,C98,$T$1,$U$1,SUBSTITUTE(E98,",","."),$U$1,SUBSTITUTE(I98,",","."),$U$1,$T$1,K98,$T$1,$U$1,M98,$R$1,$V$1) -> INSERT INTO "SportsRecords" (sp_record_id,sp_record_name,sp_record_best,sp_record_last,sport_class,team_sport_id) VALUES ('SP_096','Acrobático masculino',0,0,'P',9);
B99: SP_097 | C99: Acrobático por equipo masculino | E99: 0 | F99: 0 | G99: 0 | H99: 0 | I99: 0 | J99: Gimnasia en Trampolin | K99: P | M99: =INDEX(TeamSports!B:B,MATCH(J99,TeamSports!C:C,0)) -> 9 | O99: =_xlfn.CONCAT($O$1,$S$1,$B$1,$S$1," ",$Q$1,$B$2,$U$1,$C$2,$U$1,$E$2,$U$1,$I$2,$U$1,$K$2,$U$1,$M$2,$R$1,$P$1,$Q$1,$T$1,B99,$T$1,$U$1,$T$1,C99,$T$1,$U$1,SUBSTITUTE(E99,",","."),$U$1,SUBSTITUTE(I99,",","."),$U$1,$T$1,K99,$T$1,$U$1,M99,$R$1,$V$1) -> INSERT INTO "SportsRecords" (sp_record_id,sp_record_name,sp_record_best,sp_record_last,sport_class,team_sport_id) VALUES ('SP_097','Acrobático por equipo masculino',0,0,'P',9);
B100: SP_098 | C100: Trampolín femenino | E100: 0 | F100: 0 | G100: 0 | H100: 0 | I100: 0 | J100: Gimnasia en Trampolin | K100: P | M100: =INDEX(TeamSports!B:B,MATCH(J100,TeamSports!C:C,0)) -> 9 | O100: =_xlfn.CONCAT($O$1,$S$1,$B$1,$S$1," ",$Q$1,$B$2,$U$1,$C$2,$U$1,$E$2,$U$1,$I$2,$U$1,$K$2,$U$1,$M$2,$R$1,$P$1,$Q$1,$T$1,B100,$T$1,$U$1,$T$1,C100,$T$1,$U$1,SUBSTITUTE(E100,",","."),$U$1,SUBSTITUTE(I100,",","."),$U$1,$T$1,K100,$T$1,$U$1,M100,$R$1,$V$1) -> INSERT INTO "SportsRecords" (sp_record_id,sp_record_name,sp_record_best,sp_record_last,sport_class,team_sport_id) VALUES ('SP_098','Trampolín femenino',0,0,'P',9);
B101: SP_099 | C101: Trampolín por equipo femenino | E101: 0 | F101: 0 | G101: 0 | H101: 0 | I101: 0 | J101: Gimnasia en Trampolin | K101: P | M101: =INDEX(TeamSports!B:B,MATCH(J101,TeamSports!C:C,0)) -> 9 | O101: =_xlfn.CONCAT($O$1,$S$1,$B$1,$S$1," ",$Q$1,$B$2,$U$1,$C$2,$U$1,$E$2,$U$1,$I$2,$U$1,$K$2,$U$1,$M$2,$R$1,$P$1,$Q$1,$T$1,B101,$T$1,$U$1,$T$1,C101,$T$1,$U$1,SUBSTITUTE(E101,",","."),$U$1,SUBSTITUTE(I101,",","."),$U$1,$T$1,K101,$T$1,$U$1,M101,$R$1,$V$1) -> INSERT INTO "SportsRecords" (sp_record_id,sp_record_name,sp_record_best,sp_record_last,sport_class,team_sport_id) VALUES ('SP_099','Trampolín por equipo femenino',0,0,'P',9);
B102: SP_100 | C102: Trampolín sincronizado femenino | E102: 0 | F102: 0 | G102: 0 | H102: 0 | I102: 0 | J102: Gimnasia en Trampolin | K102: P | M102: =INDEX(TeamSports!B:B,MATCH(J102,TeamSports!C:C,0)) -> 9 | O102: =_xlfn.CONCAT($O$1,$S$1,$B$1,$S$1," ",$Q$1,$B$2,$U$1,$C$2,$U$1,$E$2,$U$1,$I$2,$U$1,$K$2,$U$1,$M$2,$R$1,$P$1,$Q$1,$T$1,B102,$T$1,$U$1,$T$1,C102,$T$1,$U$1,SUBSTITUTE(E102,",","."),$U$1,SUBSTITUTE(I102,",","."),$U$1,$T$1,K102,$T$1,$U$1,M102,$R$1,$V$1) -> INSERT INTO "SportsRecords" (sp_record_id,sp_record_name,sp_record_best,sp_record_last,sport_class,team_sport_id) VALUES ('SP_100','Trampolín sincronizado femenino',0,0,'P',9);
B103: SP_101 | C103: Acrobático femenino | E103: 0 | F103: 0 | G103: 0 | H103: 0 | I103: 0 | J103: Gimnasia en Trampolin | K103: P | M103: =INDEX(TeamSports!B:B,MATCH(J103,TeamSports!C:C,0)) -> 9 | O103: =_xlfn.CONCAT($O$1,$S$1,$B$1,$S$1," ",$Q$1,$B$2,$U$1,$C$2,$U$1,$E$2,$U$1,$I$2,$U$1,$K$2,$U$1,$M$2,$R$1,$P$1,$Q$1,$T$1,B103,$T$1,$U$1,$T$1,C103,$T$1,$U$1,SUBSTITUTE(E103,",","."),$U$1,SUBSTITUTE(I103,",","."),$U$1,$T$1,K103,$T$1,$U$1,M103,$R$1,$V$1) -> INSERT INTO "SportsRecords" (sp_record_id,sp_record_name,sp_record_best,sp_record_last,sport_class,team_sport_id) VALUES ('SP_101','Acrobático femenino',0,0,'P',9);
B104: SP_102 | C104: Acrobático por equipo femenino | E104: 0 | F104: 0 | G104: 0 | H104: 0 | I104: 0 | J104: Gimnasia en Trampolin | K104: P | M104: =INDEX(TeamSports!B:B,MATCH(J104,TeamSports!C:C,0)) -> 9 | O104: =_xlfn.CONCAT($O$1,$S$1,$B$1,$S$1," ",$Q$1,$B$2,$U$1,$C$2,$U$1,$E$2,$U$1,$I$2,$U$1,$K$2,$U$1,$M$2,$R$1,$P$1,$Q$1,$T$1,B104,$T$1,$U$1,$T$1,C104,$T$1,$U$1,SUBSTITUTE(E104,",","."),$U$1,SUBSTITUTE(I104,",","."),$U$1,$T$1,K104,$T$1,$U$1,M104,$R$1,$V$1) -> INSERT INTO "SportsRecords" (sp_record_id,sp_record_name,sp_record_best,sp_record_last,sport_class,team_sport_id) VALUES ('SP_102','Acrobático por equipo femenino',0,0,'P',9);
B105: SP_103 | C105: Concurso completo | E105: 0 | I105: 0 | J105: Gimnasia Ritmica | K105: P | M105: =INDEX(TeamSports!B:B,MATCH(J105,TeamSports!C:C,0)) -> 10 | O105: =_xlfn.CONCAT($O$1,$S$1,$B$1,$S$1," ",$Q$1,$B$2,$U$1,$C$2,$U$1,$E$2,$U$1,$I$2,$U$1,$K$2,$U$1,$M$2,$R$1,$P$1,$Q$1,$T$1,B105,$T$1,$U$1,$T$1,C105,$T$1,$U$1,SUBSTITUTE(E105,",","."),$U$1,SUBSTITUTE(I105,",","."),$U$1,$T$1,K105,$T$1,$U$1,M105,$R$1,$V$1) -> INSERT INTO "SportsRecords" (sp_record_id,sp_record_name,sp_record_best,sp_record_last,sport_class,team_sport_id) VALUES ('SP_103','Concurso completo',0,0,'P',10);
B106: SP_104 | C106: Aro | E106: 0 | I106: 0 | J106: Gimnasia Ritmica | K106: P | M106: =INDEX(TeamSports!B:B,MATCH(J106,TeamSports!C:C,0)) -> 10 | O106: =_xlfn.CONCAT($O$1,$S$1,$B$1,$S$1," ",$Q$1,$B$2,$U$1,$C$2,$U$1,$E$2,$U$1,$I$2,$U$1,$K$2,$U$1,$M$2,$R$1,$P$1,$Q$1,$T$1,B106,$T$1,$U$1,$T$1,C106,$T$1,$U$1,SUBSTITUTE(E106,",","."),$U$1,SUBSTITUTE(I106,",","."),$U$1,$T$1,K106,$T$1,$U$1,M106,$R$1,$V$1) -> INSERT INTO "SportsRecords" (sp_record_id,sp_record_name,sp_record_best,sp_record_last,sport_class,team_sport_id) VALUES ('SP_104','Aro',0,0,'P',10);
B107: SP_105 | C107: Pelota | E107: 0 | I107: 0 | J107: Gimnasia Ritmica | K107: P | M107: =INDEX(TeamSports!B:B,MATCH(J107,TeamSports!C:C,0)) -> 10 | O107: =_xlfn.CONCAT($O$1,$S$1,$B$1,$S$1," ",$Q$1,$B$2,$U$1,$C$2,$U$1,$E$2,$U$1,$I$2,$U$1,$K$2,$U$1,$M$2,$R$1,$P$1,$Q$1,$T$1,B107,$T$1,$U$1,$T$1,C107,$T$1,$U$1,SUBSTITUTE(E107,",","."),$U$1,SUBSTITUTE(I107,",","."),$U$1,$T$1,K107,$T$1,$U$1,M107,$R$1,$V$1) -> INSERT INTO "SportsRecords" (sp_record_id,sp_record_name,sp_record_best,sp_record_last,sport_class,team_sport_id) VALUES ('SP_105','Pelota',0,0,'P',10);
B108: SP_106 | C108: Mazas | E108: 0 | I108: 0 | J108: Gimnasia Ritmica | K108: P | M108: =INDEX(TeamSports!B:B,MATCH(J108,TeamSports!C:C,0)) -> 10 | O108: =_xlfn.CONCAT($O$1,$S$1,$B$1,$S$1," ",$Q$1,$B$2,$U$1,$C$2,$U$1,$E$2,$U$1,$I$2,$U$1,$K$2,$U$1,$M$2,$R$1,$P$1,$Q$1,$T$1,B108,$T$1,$U$1,$T$1,C108,$T$1,$U$1,SUBSTITUTE(E108,",","."),$U$1,SUBSTITUTE(I108,",","."),$U$1,$T$1,K108,$T$1,$U$1,M108,$R$1,$V$1) -> INSERT INTO "SportsRecords" (sp_record_id,sp_record_name,sp_record_best,sp_record_last,sport_class,team_sport_id) VALUES ('SP_106','Mazas',0,0,'P',10);
B109: SP_107 | C109: Cinta | E109: 0 | I109: 0 | J109: Gimnasia Ritmica | K109: P | M109: =INDEX(TeamSports!B:B,MATCH(J109,TeamSports!C:C,0)) -> 10 | O109: =_xlfn.CONCAT($O$1,$S$1,$B$1,$S$1," ",$Q$1,$B$2,$U$1,$C$2,$U$1,$E$2,$U$1,$I$2,$U$1,$K$2,$U$1,$M$2,$R$1,$P$1,$Q$1,$T$1,B109,$T$1,$U$1,$T$1,C109,$T$1,$U$1,SUBSTITUTE(E109,",","."),$U$1,SUBSTITUTE(I109,",","."),$U$1,$T$1,K109,$T$1,$U$1,M109,$R$1,$V$1) -> INSERT INTO "SportsRecords" (sp_record_id,sp_record_name,sp_record_best,sp_record_last,sport_class,team_sport_id) VALUES ('SP_107','Cinta',0,0,'P',10);
B110: SP_108 | C110: Solo rutina técnica Masculina | E110: 0 | I110: 0 | J110: Nado Sincronizado | K110: P | M110: =INDEX(TeamSports!B:B,MATCH(J110,TeamSports!C:C,0)) -> 12 | O110: =_xlfn.CONCAT($O$1,$S$1,$B$1,$S$1," ",$Q$1,$B$2,$U$1,$C$2,$U$1,$E$2,$U$1,$I$2,$U$1,$K$2,$U$1,$M$2,$R$1,$P$1,$Q$1,$T$1,B110,$T$1,$U$1,$T$1,C110,$T$1,$U$1,SUBSTITUTE(E110,",","."),$U$1,SUBSTITUTE(I110,",","."),$U$1,$T$1,K110,$T$1,$U$1,M110,$R$1,$V$1) -> INSERT INTO "SportsRecords" (sp_record_id,sp_record_name,sp_record_best,sp_record_last,sport_class,team_sport_id) VALUES ('SP_108','Solo rutina técnica Masculina',0,0,'P',12);
B111: SP_109 | C111: Solo prueba libre Masculina | E111: 0 | I111: 0 | J111: Nado Sincronizado | K111: P | M111: =INDEX(TeamSports!B:B,MATCH(J111,TeamSports!C:C,0)) -> 12 | O111: =_xlfn.CONCAT($O$1,$S$1,$B$1,$S$1," ",$Q$1,$B$2,$U$1,$C$2,$U$1,$E$2,$U$1,$I$2,$U$1,$K$2,$U$1,$M$2,$R$1,$P$1,$Q$1,$T$1,B111,$T$1,$U$1,$T$1,C111,$T$1,$U$1,SUBSTITUTE(E111,",","."),$U$1,SUBSTITUTE(I111,",","."),$U$1,$T$1,K111,$T$1,$U$1,M111,$R$1,$V$1) -> INSERT INTO "SportsRecords" (sp_record_id,sp_record_name,sp_record_best,sp_record_last,sport_class,team_sport_id) VALUES ('SP_109','Solo prueba libre Masculina',0,0,'P',12);
B112: SP_110 | C112: Solo rutina técnica Femenina | E112: 0 | I112: 0 | J112: Nado Sincronizado | K112: P | M112: =INDEX(TeamSports!B:B,MATCH(J112,TeamSports!C:C,0)) -> 12 | O112: =_xlfn.CONCAT($O$1,$S$1,$B$1,$S$1," ",$Q$1,$B$2,$U$1,$C$2,$U$1,$E$2,$U$1,$I$2,$U$1,$K$2,$U$1,$M$2,$R$1,$P$1,$Q$1,$T$1,B112,$T$1,$U$1,$T$1,C112,$T$1,$U$1,SUBSTITUTE(E112,",","."),$U$1,SUBSTITUTE(I112,",","."),$U$1,$T$1,K112,$T$1,$U$1,M112,$R$1,$V$1) -> INSERT INTO "SportsRecords" (sp_record_id,sp_record_name,sp_record_best,sp_record_last,sport_class,team_sport_id) VALUES ('SP_110','Solo rutina técnica Femenina',0,0,'P',12);
B113: SP_111 | C113: Solo prueba libre Femenina | E113: 0 | I113: 0 | J113: Nado Sincronizado | K113: P | M113: =INDEX(TeamSports!B:B,MATCH(J113,TeamSports!C:C,0)) -> 12 | O113: =_xlfn.CONCAT($O$1,$S$1,$B$1,$S$1," ",$Q$1,$B$2,$U$1,$C$2,$U$1,$E$2,$U$1,$I$2,$U$1,$K$2,$U$1,$M$2,$R$1,$P$1,$Q$1,$T$1,B113,$T$1,$U$1,$T$1,C113,$T$1,$U$1,SUBSTITUTE(E113,",","."),$U$1,SUBSTITUTE(I113,",","."),$U$1,$T$1,K113,$T$1,$U$1,M113,$R$1,$V$1) -> INSERT INTO "SportsRecords" (sp_record_id,sp_record_name,sp_record_best,sp_record_last,sport_class,team_sport_id) VALUES ('SP_111','Solo prueba libre Femenina',0,0,'P',12);
B114: SP_112 | C114: Dúo rutina técnica Femenina | E114: 0 | I114: 0 | J114: Nado Sincronizado | K114: P | M114: =INDEX(TeamSports!B:B,MATCH(J114,TeamSports!C:C,0)) -> 12 | O114: =_xlfn.CONCAT($O$1,$S$1,$B$1,$S$1," ",$Q$1,$B$2,$U$1,$C$2,$U$1,$E$2,$U$1,$I$2,$U$1,$K$2,$U$1,$M$2,$R$1,$P$1,$Q$1,$T$1,B114,$T$1,$U$1,$T$1,C114,$T$1,$U$1,SUBSTITUTE(E114,",","."),$U$1,SUBSTITUTE(I114,",","."),$U$1,$T$1,K114,$T$1,$U$1,M114,$R$1,$V$1) -> INSERT INTO "SportsRecords" (sp_record_id,sp_record_name,sp_record_best,sp_record_last,sport_class,team_sport_id) VALUES ('SP_112','Dúo rutina técnica Femenina',0,0,'P',12);
B115: SP_113 | C115: Dúo prueba libre Femenina | E115: 0 | I115: 0 | J115: Nado Sincronizado | K115: P | M115: =INDEX(TeamSports!B:B,MATCH(J115,TeamSports!C:C,0)) -> 12 | O115: =_xlfn.CONCAT($O$1,$S$1,$B$1,$S$1," ",$Q$1,$B$2,$U$1,$C$2,$U$1,$E$2,$U$1,$I$2,$U$1,$K$2,$U$1,$M$2,$R$1,$P$1,$Q$1,$T$1,B115,$T$1,$U$1,$T$1,C115,$T$1,$U$1,SUBSTITUTE(E115,",","."),$U$1,SUBSTITUTE(I115,",","."),$U$1,$T$1,K115,$T$1,$U$1,M115,$R$1,$V$1) -> INSERT INTO "SportsRecords" (sp_record_id,sp_record_name,sp_record_best,sp_record_last,sport_class,team_sport_id) VALUES ('SP_113','Dúo prueba libre Femenina',0,0,'P',12);
B116: SP_114 | C116: Dúo rutina técnica Mixta | E116: 0 | I116: 0 | J116: Nado Sincronizado | K116: P | M116: =INDEX(TeamSports!B:B,MATCH(J116,TeamSports!C:C,0)) -> 12 | O116: =_xlfn.CONCAT($O$1,$S$1,$B$1,$S$1," ",$Q$1,$B$2,$U$1,$C$2,$U$1,$E$2,$U$1,$I$2,$U$1,$K$2,$U$1,$M$2,$R$1,$P$1,$Q$1,$T$1,B116,$T$1,$U$1,$T$1,C116,$T$1,$U$1,SUBSTITUTE(E116,",","."),$U$1,SUBSTITUTE(I116,",","."),$U$1,$T$1,K116,$T$1,$U$1,M116,$R$1,$V$1) -> INSERT INTO "SportsRecords" (sp_record_id,sp_record_name,sp_record_best,sp_record_last,sport_class,team_sport_id) VALUES ('SP_114','Dúo rutina técnica Mixta',0,0,'P',12);
... B230: SP_228 | C230: Una vuelta ruta senior femenina | E230: 41.666 | I230: 45.8326 | J230: Patinaje | K230: T | M230: =INDEX(TeamSports!B:B,MATCH(J230,TeamSports!C:C,0)) -> 14 | O230: =_xlfn.CONCAT($O$1,$S$1,$B$1,$S$1," ",$Q$1,$B$2,$U$1,$C$2,$U$1,$E$2,$U$1,$I$2,$U$1,$K$2,$U$1,$M$2,$R$1,$P$1,$Q$1,$T$1,B230,$T$1,$U$1,$T$1,C230,$T$1,$U$1,SUBSTITUTE(E230,",","."),$U$1,SUBSTITUTE(I230,",","."),$U$1,$T$1,K230,$T$1,$U$1,M230,$R$1,$V$1) -> INSERT INTO "SportsRecords" (sp_record_id,sp_record_name,sp_record_best,sp_record_last,sport_class,team_sport_id) VALUES ('SP_228','Una vuelta ruta senior femenina',41.666,45.8326,'T',14);
B231: SP_229 | C231: 10000m ruta puntos senior femenino | E231: 905.161 | I231: 995.6771 | J231: Patinaje | K231: T | M231: =INDEX(TeamSports!B:B,MATCH(J231,TeamSports!C:C,0)) -> 14 | O231: =_xlfn.CONCAT($O$1,$S$1,$B$1,$S$1," ",$Q$1,$B$2,$U$1,$C$2,$U$1,$E$2,$U$1,$I$2,$U$1,$K$2,$U$1,$M$2,$R$1,$P$1,$Q$1,$T$1,B231,$T$1,$U$1,$T$1,C380,$T$1,$U$1,SUBSTITUTE(E380,",","."),$U$1,SUBSTITUTE(I380,",","."),$U$1,$T$1,K380,$T$1,$U$1,M380,$R$1,$V$1) -> INSERT INTO "SportsRecords" (sp_record_id,sp_record_name,sp_record_best,sp_record_last,sport_class,team_sport_id) VALUES ('SP_229','100M',8.802,13.999,'T',39);
B232: SP_230 | C232: 15000m ruta eliminación senior femenino | E232: 1425.515 | I232: 1568.0665 | J232: Patinaje | K232: T | M232: =INDEX(TeamSports!B:B,MATCH(J232,TeamSports!C:C,0)) -> 14 | O232: =_xlfn.CONCAT($O$1,$S$1,$B$1,$S$1," ",$Q$1,$B$2,$U$1,$C$2,$U$1,$E$2,$U$1,$I$2,$U$1,$K$2,$U$1,$M$2,$R$1,$P$1,$Q$1,$T$1,B232,$T$1,$U$1,$T$1,C381,$T$1,$U$1,SUBSTITUTE(E381,",","."),$U$1,SUBSTITUTE(I381,",","."),$U$1,$T$1,K381,$T$1,$U$1,M381,$R$1,$V$1) -> INSERT INTO "SportsRecords" (sp_record_id,sp_record_name,sp_record_best,sp_record_last,sport_class,team_sport_id) VALUES ('SP_230','100ML',39.218,50.999,'T',39);
B233: SP_231 | C233: Maratón femenina | E233: 4132.844 | I233: 4546.1284 | J233: Patinaje | K233: T | M233: =INDEX(TeamSports!B:B,MATCH(J233,TeamSports!C:C,0)) -> 14 | O233: =_xlfn.CONCAT($O$1,$S$1,$B$1,$S$1," ",$Q$1,$B$2,$U$1,$C$2,$U$1,$E$2,$U$1,$I$2,$U$1,$K$2,$U$1,$M$2,$R$1,$P$1,$Q$1,$T$1,B233,$T$1,$U$1,$T$1,C382,$T$1,$U$1,SUBSTITUTE(E382,",","."),$U$1,SUBSTITUTE(I382,",","."),$U$1,$T$1,K382,$T$1,$U$1,M382,$R$1,$V$1) -> INSERT INTO "SportsRecords" (sp_record_id,sp_record_name,sp_record_best,sp_record_last,sport_class,team_sport_id) VALUES ('SP_231','110MV',12.025,18.999,'T',39);
B234: SP_232 | C234: Park masculino | E234: 100 | I234: 0 | J234: Skateboarding | K234: P | M234: =INDEX(TeamSports!B:B,MATCH(J234,TeamSports!C:C,0)) -> 18 | O234: =_xlfn.CONCAT($O$1,$S$1,$B$1,$S$1," ",$Q$1,$B$2,$U$1,$C$2,$U$1,$E$2,$U$1,$I$2,$U$1,$K$2,$U$1,$M$2,$R$1,$P$1,$Q$1,$T$1,B234,$T$1,$U$1,$T$1,C383,$T$1,$U$1,SUBSTITUTE(E383,",","."),$U$1,SUBSTITUTE(I383,",","."),$U$1,$T$1,K383,$T$1,$U$1,M383,$R$1,$V$1) -> INSERT INTO "SportsRecords" (sp_record_id,sp_record_name,sp_record_best,sp_record_last,sport_class,team_sport_id) VALUES ('SP_232','200MEI',119.451,180.999,'T',39);
B235: SP_233 | C235: Street masculino | E235: 100 | I235: 0 | J235: Skateboarding | K235: P | M235: =INDEX(TeamSports!B:B,MATCH(J235,TeamSports!C:C,0)) -> 18 | O235: =_xlfn.CONCAT($O$1,$S$1,$B$1,$S$1," ",$Q$1,$B$2,$U$1,$C$2,$U$1,$E$2,$U$1,$I$2,$U$1,$K$2,$U$1,$M$2,$R$1,$P$1,$Q$1,$T$1,B235,$T$1,$U$1,$T$1,C384,$T$1,$U$1,SUBSTITUTE(E384,",","."),$U$1,SUBSTITUTE(I384,",","."),$U$1,$T$1,K384,$T$1,$U$1,M384,$R$1,$V$1) -> INSERT INTO "SportsRecords" (sp_record_id,sp_record_name,sp_record_best,sp_record_last,sport_class,team_sport_id) VALUES ('SP_233','4X100R',35.513,50.999,'T',39);
B236: SP_234 | C236: Park femenino | E236: 100 | I236: 0 | J236: Skateboarding | K236: P | M236: =INDEX(TeamSports!B:B,MATCH(J236,TeamSports!C:C,0)) -> 18 | O236: =_xlfn.CONCAT($O$1,$S$1,$B$1,$S$1," ",$Q$1,$B$2,$U$1,$C$2,$U$1,$E$2,$U$1,$I$2,$U$1,$K$2,$U$1,$M$2,$R$1,$P$1,$Q$1,$T$1,B236,$T$1,$U$1,$T$1,C385,$T$1,$U$1,SUBSTITUTE(E385,",","."),$U$1,SUBSTITUTE(I385,",","."),$U$1,$T$1,K385,$T$1,$U$1,M385,$R$1,$V$1) -> INSERT INTO "SportsRecords" (sp_record_id,sp_record_name,sp_record_best,sp_record_last,sport_class,team_sport_id) VALUES ('SP_234','BMX',40.43,70.999,'T',39);
B237: SP_235 | C237: Street femenino | E237: 100 | I237: 0 | J237: Skateboarding | K237: P | M237: =INDEX(TeamSports!B:B,MATCH(J237,TeamSports!C:C,0)) -> 18 | O237: =_xlfn.CONCAT($O$1,$S$1,$B$1,$S$1," ",$Q$1,$B$2,$U$1,$C$2,$U$1,$E$2,$U$1,$I$2,$U$1,$K$2,$U$1,$M$2,$R$1,$P$1,$Q$1,$T$1,B237,$T$1,$U$1,$T$1,C386,$T$1,$U$1,SUBSTITUTE(E386,",","."),$U$1,SUBSTITUTE(I386,",","."),$U$1,$T$1,K386,$T$1,$U$1,M386,$R$1,$V$1) -> INSERT INTO "SportsRecords" (sp_record_id,sp_record_name,sp_record_best,sp_record_last,sport_class,team_sport_id) VALUES ('SP_235','ESCALADA DEPORTIVA',7.803,15.999,'T',39);
B238: SP_236 | C238: K1 200m masculino | E238: 35 | I238: 40.25 | J238: Piraguismo | K238: T | M238: =INDEX(TeamSports!B:B,MATCH(J238,TeamSports!C:C,0)) -> 15 | O238: =_xlfn.CONCAT($O$1,$S$1,$B$1,$S$1," ",$Q$1,$B$2,$U$1,$C$2,$U$1,$E$2,$U$1,$I$2,$U$1,$K$2,$U$1,$M$2,$R$1,$P$1,$Q$1,$T$1,B238,$T$1,$U$1,$T$1,C387,$T$1,$U$1,SUBSTITUTE(E387,",","."),$U$1,SUBSTITUTE(I387,",","."),$U$1,$T$1,K387,$T$1,$U$1,M387,$R$1,$V$1) -> INSERT INTO "SportsRecords" (sp_record_id,sp_record_name,sp_record_best,sp_record_last,sport_class,team_sport_id) VALUES ('SP_236','LANZAMIENTO DE MARTILLO',99.221,75,'T',39);
B239: SP_237 | C239: K1 500m masculino | E239: 96.5 | I239: 110.975 | J239: Piraguismo | K239: T | M239: =INDEX(TeamSports!B:B,MATCH(J239,TeamSports!C:C,0)) -> 15 | O239: =_xlfn.CONCAT($O$1,$S$1,$B$1,$S$1," ",$Q$1,$B$2,$U$1,$C$2,$U$1,$E$2,$U$1,$I$2,$U$1,$K$2,$U$1,$M$2,$R$1,$P$1,$Q$1,$T$1,B239,$T$1,$U$1,$T$1,C388,$T$1,$U$1,SUBSTITUTE(E388,",","."),$U$1,SUBSTITUTE(I388,",","."),$U$1,$T$1,K388,$T$1,$U$1,M388,$R$1,$V$1) -> INSERT INTO "SportsRecords" (sp_record_id,sp_record_name,sp_record_best,sp_record_last,sport_class,team_sport_id) VALUES ('SP_237','SALTO DE LONGITUD',10.116,7.5,'T',39);
B240: SP_238 | C240: K2 1000m masculino | E240: 195.25 | I240: 224.5375 | J240: Piraguismo | K240: T | M240: =INDEX(TeamSports!B:B,MATCH(J240,TeamSports!C:C,0)) -> 15 | O240: =_xlfn.CONCAT($O$1,$S$1,$B$1,$S$1," ",$Q$1,$B$2,$U$1,$C$2,$U$1,$E$2,$U$1,$I$2,$U$1,$K$2,$U$1,$M$2,$R$1,$P$1,$Q$1,$T$1,B240,$T$1,$U$1,$T$1,C389,$T$1,$U$1,SUBSTITUTE(E389,",","."),$U$1,SUBSTITUTE(I389,",","."),$U$1,$T$1,K389,$T$1,$U$1,M389,$R$1,$V$1) -> INSERT INTO "SportsRecords" (sp_record_id,sp_record_name,sp_record_best,sp_record_last,sport_class,team_sport_id) VALUES ('SP_238','Blizzard Blitz',134.56,164.99,'T',40);
B241: SP_239 | C241: C1 200m masculino | E241: 39.2 | I241: 45.08 | J241: Piraguismo | K241: T | M241: =INDEX(TeamSports!B:B,MATCH(J241,TeamSports!C:C,0)) -> 15 | O241: =_xlfn.CONCAT($O$1,$S$1,$B$1,$S$1," ",$Q$1,$B$2,$U$1,$C$2,$U$1,$E$2,$U$1,$I$2,$U$1,$K$2,$U$1,$M$2,$R$1,$P$1,$Q$1,$T$1,B241,$T$1,$U$1,$T$1,C390,$T$1,$U$1,SUBSTITUTE(E390,",","."),$U$1,SUBSTITUTE(I390,",","."),$U$1,$T$1,K390,$T$1,$U$1,M390,$R$1,$V$1) -> INSERT INTO "SportsRecords" (sp_record_id,sp_record_name,sp_record_best,sp_record_last,sport_class,team_sport_id) VALUES ('SP_239','Canyon Chasm',123.96,153.99,'T',40);
B242: SP_240 | C242: C1 500m masculino | E242: 99.4 | I242: 114.31 | J242: Piraguismo | K242: T | M242: =INDEX(TeamSports!B:B,MATCH(J242,TeamSports!C:C,0)) -> 15 | O242: =_xlfn.CONCAT($O$1,$S$1,$B$1,$S$1," ",$Q$1,$B$2,$U$1,$C$2,$U$1,$E$2,$U$1,$I$2,$U$1,$K$2,$U$1,$M$2,$R$1,$P$1,$Q$1,$T$1,B242,$T$1,$U$1,$T$1,C391,$T$1,$U$1,SUBSTITUTE(E391,",","."),$U$1,SUBSTITUTE(I391,",","."),$U$1,$T$1,K391,$T$1,$U$1,M391,$R$1,$V$1) -> INSERT INTO "SportsRecords" (sp_record_id,sp_record_name,sp_record_best,sp_record_last,sport_class,team_sport_id) VALUES ('SP_240','Congo Course',128.48,158.99,'T',40);
... B379: SP_377 | C379: Team Cross Mixto | E379: 72.5 | I379: 83.375 | J379: Snowboard de Velocidad | K379: H | M379: =INDEX(TeamSports!B:B,MATCH(J379,TeamSports!C:C,0)) -> 66 | O379: =_xlfn.CONCAT($O$1,$S$1,$B$1,$S$1," ",$Q$1,$B$2,$U$1,$C$2,$U$1,$E$2,$U$1,$I$2,$U$1,$K$2,$U$1,$M$2,$R$1,$P$1,$Q$1,$T$1,B379,$T$1,$U$1,$T$1,C528,$T$1,$U$1,SUBSTITUTE(E528,",","."),$U$1,SUBSTITUTE(I528,",","."),$U$1,$T$1,K528,$T$1,$U$1,M528,$R$1,$V$1) -> INSERT INTO "SportsRecords" (sp_record_id,sp_record_name,sp_record_best,sp_record_last,sport_class,team_sport_id) VALUES ('SP_377','Planta Tm',66,87,'T',43);
B380: SP_378 | C380: 100M | D380: =VALUE(SUBSTITUTE(F380,".",","))/1000 -> 8.802 | E380: =D380 -> 8.802 | F380: 8802 | G380: =VALUE(SUBSTITUTE(H380,".",","))/1000 -> 13.999 | H380: 13999 | I380: =G380 -> 13.999 | J380: Tokyo | K380: T | M380: =INDEX(TeamSports!B:B,MATCH(J380,TeamSports!C:C,0)) -> 39 | O380: =_xlfn.CONCAT($O$1,$S$1,$B$1,$S$1," ",$Q$1,$B$2,$U$1,$C$2,$U$1,$E$2,$U$1,$I$2,$U$1,$K$2,$U$1,$M$2,$R$1,$P$1,$Q$1,$T$1,B380,$T$1,$U$1,$T$1,C529,$T$1,$U$1,SUBSTITUTE(E529,",","."),$U$1,SUBSTITUTE(I529,",","."),$U$1,$T$1,K529,$T$1,$U$1,M529,$R$1,$V$1) -> INSERT INTO "SportsRecords" (sp_record_id,sp_record_name,sp_record_best,sp_record_last,sport_class,team_sport_id) VALUES ('SP_378','Presa Dp',23,29,'T',43);
B381: SP_379 | C381: 100ML | D381: =VALUE(SUBSTITUTE(F381,".",","))/1000 -> 39.218 | E381: =D381 -> 39.218 | F381: 39218 | G381: =VALUE(SUBSTITUTE(H381,".",","))/1000 -> 50.999 | H381: 50999 | I381: =G381 -> 50.999 | J381: Tokyo | K381: T | M381: =INDEX(TeamSports!B:B,MATCH(J381,TeamSports!C:C,0)) -> 39 | O381: =_xlfn.CONCAT($O$1,$S$1,$B$1,$S$1," ",$Q$1,$B$2,$U$1,$C$2,$U$1,$E$2,$U$1,$I$2,$U$1,$K$2,$U$1,$M$2,$R$1,$P$1,$Q$1,$T$1,B381,$T$1,$U$1,$T$1,C530,$T$1,$U$1,SUBSTITUTE(E530,",","."),$U$1,SUBSTITUTE(I530,",","."),$U$1,$T$1,K530,$T$1,$U$1,M530,$R$1,$V$1) -> INSERT INTO "SportsRecords" (sp_record_id,sp_record_name,sp_record_best,sp_record_last,sport_class,team_sport_id) VALUES ('SP_379','Presa Mt',14,13,'T',43);
B382: SP_380 | C382: 110MV | D382: =VALUE(SUBSTITUTE(F382,".",","))/1000 -> 12.025 | E382: =D382 -> 12.025 | F382: 12025 | G382: =VALUE(SUBSTITUTE(H382,".",","))/1000 -> 18.999 | H382: 18999 | I382: =G382 -> 18.999 | J382: Tokyo | K382: T | M382: =INDEX(TeamSports!B:B,MATCH(J382,TeamSports!C:C,0)) -> 39 | O382: =_xlfn.CONCAT($O$1,$S$1,$B$1,$S$1," ",$Q$1,$B$2,$U$1,$C$2,$U$1,$E$2,$U$1,$I$2,$U$1,$K$2,$U$1,$M$2,$R$1,$P$1,$Q$1,$T$1,B382,$T$1,$U$1,$T$1,C531,$T$1,$U$1,SUBSTITUTE(E531,",","."),$U$1,SUBSTITUTE(I531,",","."),$U$1,$T$1,K531,$T$1,$U$1,M531,$R$1,$V$1) -> INSERT INTO "SportsRecords" (sp_record_id,sp_record_name,sp_record_best,sp_record_last,sport_class,team_sport_id) VALUES ('SP_380','Presa Pt',100,85,'T',43);
B383: SP_381 | C383: 200MEI | D383: =VALUE(SUBSTITUTE(F383,".",","))/1000 -> 119.451 | E383: =D383 -> 119.451 | F383: 119451 | G383: =VALUE(SUBSTITUTE(H383,".",","))/1000 -> 180.999 | H383: 180999 | I383: =G383 -> 180.999 | J383: Tokyo | K383: T | M383: =INDEX(TeamSports!B:B,MATCH(J383,TeamSports!C:C,0)) -> 39 | O383: =_xlfn.CONCAT($O$1,$S$1,$B$1,$S$1," ",$Q$1,$B$2,$U$1,$C$2,$U$1,$E$2,$U$1,$I$2,$U$1,$K$2,$U$1,$M$2,$R$1,$P$1,$Q$1,$T$1,B383,$T$1,$U$1,$T$1,C532,$T$1,$U$1,SUBSTITUTE(E532,",","."),$U$1,SUBSTITUTE(I532,",","."),$U$1,$T$1,K532,$T$1,$U$1,M532,$R$1,$V$1) -> INSERT INTO "SportsRecords" (sp_record_id,sp_record_name,sp_record_best,sp_record_last,sport_class,team_sport_id) VALUES ('SP_381','Presa Tm',60,75,'T',43);
B384: SP_382 | C384: 4X100R | D384: =VALUE(SUBSTITUTE(F384,".",","))/1000 -> 35.513 | E384: =D384 -> 35.513 | F384: 35513 | G384: =VALUE(SUBSTITUTE(H384,".",","))/1000 -> 50.999 | H384: 50999 | I384: =G384 -> 50.999 | J384: Tokyo | K384: T | M384: =INDEX(TeamSports!B:B,MATCH(J384,TeamSports!C:C,0)) -> 39 | O384: =_xlfn.CONCAT($O$1,$S$1,$B$1,$S$1," ",$Q$1,$B$2,$U$1,$C$2,$U$1,$E$2,$U$1,$I$2,$U$1,$K$2,$U$1,$M$2,$R$1,$P$1,$Q$1,$T$1,B384,$T$1,$U$1,$T$1,C533,$T$1,$U$1,SUBSTITUTE(E533,",","."),$U$1,SUBSTITUTE(I533,",","."),$U$1,$T$1,K533,$T$1,$U$1,M533,$R$1,$V$1) -> INSERT INTO "SportsRecords" (sp_record_id,sp_record_name,sp_record_best,sp_record_last,sport_class,team_sport_id) VALUES ('SP_382','Silo Dp',47,64,'T',43);
B385: SP_383 | C385: BMX | D385: =VALUE(SUBSTITUTE(F385,".",","))/1000 -> 40.43 | E385: =D385 -> 40.43 | F385: 40430 | G385: =VALUE(SUBSTITUTE(H385,".",","))/1000 -> 70.999 | H385: 70999 | I385: =G385 -> 70.999 | J385: Tokyo | K385: T | M385: =INDEX(TeamSports!B:B,MATCH(J385,TeamSports!C:C,0)) -> 39 | O385: =_xlfn.CONCAT($O$1,$S$1,$B$1,$S$1," ",$Q$1,$B$2,$U$1,$C$2,$U$1,$E$2,$U$1,$I$2,$U$1,$K$2,$U$1,$M$2,$R$1,$P$1,$Q$1,$T$1,B385,$T$1,$U$1,$T$1,C534,$T$1,$U$1,SUBSTITUTE(E534,",","."),$U$1,SUBSTITUTE(I534,",","."),$U$1,$T$1,K534,$T$1,$U$1,M534,$R$1,$V$1) -> INSERT INTO "SportsRecords" (sp_record_id,sp_record_name,sp_record_best,sp_record_last,sport_class,team_sport_id) VALUES ('SP_383','Silo Mt',28,22,'T',43);
B386: SP_384 | C386: ESCALADA DEPORTIVA | D386: =VALUE(SUBSTITUTE(F386,".",","))/1000 -> 7.803 | E386: =D386 -> 7.803 | F386: 7803 | G386: =VALUE(SUBSTITUTE(H386,".",","))/1000 -> 15.999 | H386: 15999 | I386: =G386 -> 15.999 | J386: Tokyo | K386: T | M386: =INDEX(TeamSports!B:B,MATCH(J386,TeamSports!C:C,0)) -> 39 | O386: =_xlfn.CONCAT($O$1,$S$1,$B$1,$S$1," ",$Q$1,$B$2,$U$1,$C$2,$U$1,$E$2,$U$1,$I$2,$U$1,$K$2,$U$1,$M$2,$R$1,$P$1,$Q$1,$T$1,B386,$T$1,$U$1,$T$1,C535,$T$1,$U$1,SUBSTITUTE(E535,",","."),$U$1,SUBSTITUTE(I535,",","."),$U$1,$T$1,K535,$T$1,$U$1,M535,$R$1,$V$1) -> INSERT INTO "SportsRecords" (sp_record_id,sp_record_name,sp_record_best,sp_record_last,sport_class,team_sport_id) VALUES ('SP_384','Silo Pt',89,70,'T',43);
B387: SP_385 | C387: LANZAMIENTO DE MARTILLO | D387: =VALUE(SUBSTITUTE(F387,".",","))/1000 -> 99.221 | E387: =D387 -> 99.221 | F387: 99221 | G387: =VALUE(SUBSTITUTE(H387,".",","))/1000 -> 75 | H387: 75000 | I387: =G387 -> 75 | J387: Tokyo | K387: T | M387: =INDEX(TeamSports!B:B,MATCH(J387,TeamSports!C:C,0)) -> 39 | O387: =_xlfn.CONCAT($O$1,$S$1,$B$1,$S$1," ",$Q$1,$B$2,$U$1,$C$2,$U$1,$E$2,$U$1,$I$2,$U$1,$K$2,$U$1,$M$2,$R$1,$P$1,$Q$1,$T$1,B387,$T$1,$U$1,$T$1,C536,$T$1,$U$1,SUBSTITUTE(E536,",","."),$U$1,SUBSTITUTE(I536,",","."),$U$1,$T$1,K536,$T$1,$U$1,M536,$R$1,$V$1) -> INSERT INTO "SportsRecords" (sp_record_id,sp_record_name,sp_record_best,sp_record_last,sport_class,team_sport_id) VALUES ('SP_385','Silo Tm',70,78,'T',43);
B388: SP_386 | C388: SALTO DE LONGITUD | D388: =VALUE(SUBSTITUTE(F388,".",","))/1000 -> 10.116 | E388: =D388 -> 10.116 | F388: 10116 | G388: =VALUE(SUBSTITUTE(H388,".",","))/1000 -> 7.5 | H388: 7500 | I388: =G388 -> 7.5 | J388: Tokyo | K388: T | M388: =INDEX(TeamSports!B:B,MATCH(J388,TeamSports!C:C,0)) -> 39 | O388: =_xlfn.CONCAT($O$1,$S$1,$B$1,$S$1," ",$Q$1,$B$2,$U$1,$C$2,$U$1,$E$2,$U$1,$I$2,$U$1,$K$2,$U$1,$M$2,$R$1,$P$1,$Q$1,$T$1,B388,$T$1,$U$1,$T$1,C537,$T$1,$U$1,SUBSTITUTE(E537,",","."),$U$1,SUBSTITUTE(I537,",","."),$U$1,$T$1,K537,$T$1,$U$1,M537,$R$1,$V$1) -> INSERT INTO "SportsRecords" (sp_record_id,sp_record_name,sp_record_best,sp_record_last,sport_class,team_sport_id) VALUES ('SP_386','Superficie Dp',3,5,'T',43);
B389: SP_387 | C389: Blizzard Blitz | D389: =VALUE(SUBSTITUTE(F389,".",","))/1000 -> 134.56 | E389: =D389 -> 134.56 | F389: 134560 | G389: =VALUE(SUBSTITUTE(H389,".",","))/1000 -> 164.99 | H389: 164990 | I389: =G389 -> 164.99 | J389: Excitebike | K389: T | M389: =INDEX(TeamSports!B:B,MATCH(J389,TeamSports!C:C,0)) -> 40 | O389: =_xlfn.CONCAT($O$1,$S$1,$B$1,$S$1," ",$Q$1,$B$2,$U$1,$C$2,$U$1,$E$2,$U$1,$I$2,$U$1,$K$2,$U$1,$M$2,$R$1,$P$1,$Q$1,$T$1,B389,$T$1,$U$1,$T$1,C538,$T$1,$U$1,SUBSTITUTE(E538,",","."),$U$1,SUBSTITUTE(I538,",","."),$U$1,$T$1,K538,$T$1,$U$1,M538,$R$1,$V$1) -> INSERT INTO "SportsRecords" (sp_record_id,sp_record_name,sp_record_best,sp_record_last,sport_class,team_sport_id) VALUES ('SP_387','Superficie II Dp',2,6,'T',43);
B390: SP_388 | C390: Canyon Chasm | D390: =VALUE(SUBSTITUTE(F390,".",","))/1000 -> 123.96 | E390: =D390 -> 123.96 | F390: 123960 | G390: =VALUE(SUBSTITUTE(H390,".",","))/1000 -> 153.99 | H390: 153990 | I390: =G390 -> 153.99 | J390: Excitebike | K390: T | M390: =INDEX(TeamSports!B:B,MATCH(J390,TeamSports!C:C,0)) -> 40 | O390: =_xlfn.CONCAT($O$1,$S$1,$B$1,$S$1," ",$Q$1,$B$2,$U$1,$C$2,$U$1,$E$2,$U$1,$I$2,$U$1,$K$2,$U$1,$M$2,$R$1,$P$1,$Q$1,$T$1,B390,$T$1,$U$1,$T$1,C539,$T$1,$U$1,SUBSTITUTE(E539,",","."),$U$1,SUBSTITUTE(I539,",","."),$U$1,$T$1,K539,$T$1,$U$1,M539,$R$1,$V$1) -> INSERT INTO "SportsRecords" (sp_record_id,sp_record_name,sp_record_best,sp_record_last,sport_class,team_sport_id) VALUES ('SP_388','Superficie II Mt',6,2,'T',43);
B391: SP_389 | C391: Congo Course | D391: =VALUE(SUBSTITUTE(F391,".",","))/1000 -> 128.48 | E391: =D391 -> 128.48 | F391: 128480 | G391: =VALUE(SUBSTITUTE(H391,".",","))/1000 -> 158.99 | H391: 158990 | I391: =G391 -> 158.99 | J391: Excitebike | K391: T | M391: =INDEX(TeamSports!B:B,MATCH(J391,TeamSports!C:C,0)) -> 40 | O391: =_xlfn.CONCAT($O$1,$S$1,$B$1,$S$1," ",$Q$1,$B$2,$U$1,$C$2,$U$1,$E$2,$U$1,$I$2,$U$1,$K$2,$U$1,$M$2,$R$1,$P$1,$Q$1,$T$1,B391,$T$1,$U$1,$T$1,C540,$T$1,$U$1,SUBSTITUTE(E540,",","."),$U$1,SUBSTITUTE(I540,",","."),$U$1,$T$1,K540,$T$1,$U$1,M540,$R$1,$V$1) -> INSERT INTO "SportsRecords" (sp_record_id,sp_record_name,sp_record_best,sp_record_last,sport_class,team_sport_id) VALUES ('SP_389','Superficie II Pt',87.5,66.7,'T',43);
... B438: SP_436 | C438: U Monza, Italia | D438: =VALUE(SUBSTITUTE(F438,".",","))/1000 -> 83.41 | E438: =D438 -> 83.41 | F438: 83410 | G438: =VALUE(SUBSTITUTE(H438,".",","))/1000 -> 113.99 | H438: 113990 | I438: =G438 -> 113.99 | J438: Formula1 | K438: T | M438: =INDEX(TeamSports!B:B,MATCH(J438,TeamSports!C:C,0)) -> 41 | O438: =_xlfn.CONCAT($O$1,$S$1,$B$1,$S$1," ",$Q$1,$B$2,$U$1,$C$2,$U$1,$E$2,$U$1,$I$2,$U$1,$K$2,$U$1,$M$2,$R$1,$P$1,$Q$1,$T$1,B438,$T$1,$U$1,$T$1,C587,$T$1,$U$1,SUBSTITUTE(E587,",","."),$U$1,SUBSTITUTE(I587,",","."),$U$1,$T$1,K587,$T$1,$U$1,M587,$R$1,$V$1) -> INSERT INTO "SportsRecords" (sp_record_id,sp_record_name,sp_record_best,sp_record_last,sport_class,team_sport_id) VALUES ('SP_436','Homerun Contest',1655.9,500,'T',45);
B439: SP_437 | C439: U Nurburgring, Luxemburgo | D439: =VALUE(SUBSTITUTE(F439,".",","))/1000 -> 76.81 | E439: =D439 -> 76.81 | F439: 76810 | G439: =VALUE(SUBSTITUTE(H439,".",","))/1000 -> 106.99 | H439: 106990 | I439: =G439 -> 106.99 | J439: Formula1 | K439: T | M439: =INDEX(TeamSports!B:B,MATCH(J439,TeamSports!C:C,0)) -> 41
B440: SP_438 | C440: U Silverstone, Reino Unido | D440: =VALUE(SUBSTITUTE(F440,".",","))/1000 -> 78.9 | E440: =D440 -> 78.9 | F440: 78900 | G440: =VALUE(SUBSTITUTE(H440,".",","))/1000 -> 108.99 | H440: 108990 | I440: =G440 -> 108.99 | J440: Formula1 | K440: T | M440: =INDEX(TeamSports!B:B,MATCH(J440,TeamSports!C:C,0)) -> 41
B441: SP_439 | C441: U Spa Francochamps, Belgica | D441: =VALUE(SUBSTITUTE(F441,".",","))/1000 -> 110.82 | E441: =D441 -> 110.82 | F441: 110820 | G441: =VALUE(SUBSTITUTE(H441,".",","))/1000 -> 140.99 | H441: 140990 | I441: =G441 -> 140.99 | J441: Formula1 | K441: T | M441: =INDEX(TeamSports!B:B,MATCH(J441,TeamSports!C:C,0)) -> 41
B442: SP_440 | C442: U Suzuka, Japon | D442: =VALUE(SUBSTITUTE(F442,".",","))/1000 -> 96.32 | E442: =D442 -> 96.32 | F442: 96320 | G442: =VALUE(SUBSTITUTE(H442,".",","))/1000 -> 126.99 | H442: 126990 | I442: =G442 -> 126.99 | J442: Formula1 | K442: T | M442: =INDEX(TeamSports!B:B,MATCH(J442,TeamSports!C:C,0)) -> 41
B443: SP_441 | C443: Big Blue | D443: =VALUE(SUBSTITUTE(F443,".",","))/1000 -> 37.71 | E443: =D443 -> 37.71 | F443: 37710 | G443: =VALUE(SUBSTITUTE(H443,".",","))/1000 -> 47.999 | H443: 47999 | I443: =G443 -> 47.999 | J443: F-Zero | K443: T | M443: =INDEX(TeamSports!B:B,MATCH(J443,TeamSports!C:C,0)) -> 42
B444: SP_442 | C444: Big Blue 2 | D444: =VALUE(SUBSTITUTE(F444,".",","))/1000 -> 29.365 | E444: =D444 -> 29.365 | F444: 29365 | G444: =VALUE(SUBSTITUTE(H444,".",","))/1000 -> 39.999 | H444: 39999 | I444: =G444 -> 39.999 | J444: F-Zero | K444: T | M444: =INDEX(TeamSports!B:B,MATCH(J444,TeamSports!C:C,0)) -> 42
B445: SP_443 | C445: Big Hand | D445: =VALUE(SUBSTITUTE(F445,".",","))/1000 -> 65.565 | E445: =D445 -> 65.565 | F445: 65565 | G445: =VALUE(SUBSTITUTE(H445,".",","))/1000 -> 75.999 | H445: 75999 | I445: =G445 -> 75.999 | J445: F-Zero | K445: T | M445: =INDEX(TeamSports!B:B,MATCH(J445,TeamSports!C:C,0)) -> 42
B446: SP_444 | C446: Copas | D446: =VALUE(SUBSTITUTE(F446,".",","))/1000 -> 600 | E446: =D446 -> 600 | F446: 600000 | G446: =VALUE(SUBSTITUTE(H446,".",","))/1000 -> 300 | H446: 300000 | I446: =G446 -> 300 | J446: F-Zero | K446: T | M446: =INDEX(TeamSports!B:B,MATCH(J446,TeamSports!C:C,0)) -> 42
B447: SP_445 | C447: Death Race E | D447: =VALUE(SUBSTITUTE(F447,".",","))/1000 -> 29 | E447: =D447 -> 29 | F447: 29000 | G447: =VALUE(SUBSTITUTE(H447,".",","))/1000 -> 19 | H447: 19000 | I447: =G447 -> 19 | J447: F-Zero | K447: T | M447: =INDEX(TeamSports!B:B,MATCH(J447,TeamSports!C:C,0)) -> 42
B448: SP_446 | C448: Death Race T | D448: =VALUE(SUBSTITUTE(F448,".",","))/1000 -> 25.67 | E448: =D448 -> 25.67 | F448: 25670 | G448: =VALUE(SUBSTITUTE(H448,".",","))/1000 -> 35.67 | H448: 35670 | I448: =G448 -> 35.67 | J448: F-Zero | K448: T | M448: =INDEX(TeamSports!B:B,MATCH(J448,TeamSports!C:C,0)) -> 42
B449: SP_447 | C449: Devils Forest | D449: =VALUE(SUBSTITUTE(F449,".",","))/1000 -> 38.075 | E449: =D449 -> 38.075 | F449: 38075 | G449: =VALUE(SUBSTITUTE(H449,".",","))/1000 -> 48.999 | H449: 48999 | I449: =G449 -> 48.999 | J449: F-Zero | K449: T | M449: =INDEX(TeamSports!B:B,MATCH(J449,TeamSports!C:C,0)) -> 42
B450: SP_448 | C450: Devils Forest 2 | D450: =VALUE(SUBSTITUTE(F450,".",","))/1000 -> 35.544 | E450: =D450 -> 35.544 | F450: 35544 | G450: =VALUE(SUBSTITUTE(H450,".",","))/1000 -> 45.999 | H450: 45999 | I450: =G450 -> 45.999 | J450: F-Zero | K450: T | M450: =INDEX(TeamSports!B:B,MATCH(J450,TeamSports!C:C,0)) -> 42
... B587: SP_585 | C587: Homerun Contest | D587: =VALUE(SUBSTITUTE(F587,".",","))/1000 -> 1655.9 | E587: =D587 -> 1655.9 | F587: 1655900 | G587: =VALUE(SUBSTITUTE(H587,".",","))/1000 -> 500 | H587: 500000 | I587: =G587 -> 500 | J587: Super Smash | K587: T | M587: =INDEX(TeamSports!B:B,MATCH(J587,TeamSports!C:C,0)) -> 45

Sheet RanksChart
B1: Futbol Masculino | C1: RNK | D1: POS | E1: Futbol Femenino | F1: RNK | G1: POS | H1: Futsal Masculino | I1: RNK | J1: POS | K1: Futsal Femenino | L1: RNK | M1: POS | N1: Volleyball | O1: RNK | P1: POS | Q1: Basketball | R1: RNK | S1: POS | T1: Beisbol | U1: RNK | V1: POS | W1: Badminton | X1: RNK | Y1: POS | Z1: Curling | AA1: RNK | AB1: POS | AC1: Tenis | AD1: RNK | AE1: POS | AF1: Rugby | AG1: RNK | AH1: POS | AI1: Squash | AJ1: RNK | AK1: POS | AL1: Voley Playa | AM1: RNK | AN1: POS | AO1: Tenis de Mesa | AP1: RNK | AQ1: POS | AR1: Balonmano | AS1: RNK | AT1: POS | AU1: Hockey | AV1: RNK | AW1: POS | AX1: Tiro con Arco | AY1: RNK | AZ1: POS | BA1: Esgrima | BB1: RNK | BC1: POS | BD1: Volleyball Femenino | BE1: RNK | BF1: POS | BG1: Basketball Femenino | BH1: RNK | BI1: POS | BJ1: Beisbol Femenino | BK1: RNK | BL1: POS | BM1: Badminton Femenino | BN1: RNK | BO1: POS | BP1: Curling Femenino | BQ1: RNK | BR1: POS | BS1: Tenis Femenino | BT1: RNK | BU1: POS | BV1: Rugby Femenino | BW1: RNK | BX1: POS | BY1: Squash Femenino | BZ1: RNK | CA1: POS | CB1: Voley Playa Femenino | CC1: RNK | CD1: POS | CE1: Tenis de Mesa Femenino | CF1: RNK | CG1: POS | CH1: Balonmano Femenino | CI1: RNK | CJ1: POS | CK1: Hockey Femenino | CL1: RNK | CM1: POS | CN1: Tiro con Arco Femenino | CO1: RNK | CP1: POS | CQ1: Esgrima Femenino | CR1: RNK | CS1: POS
B2: Espania | C2: 1 | D2: 1 | E2: Espania Fem | F2: 1 | G2: 1 | H2: Brasil | I2: 1 | J2: 1 | K2: Brasil Fem | L2: 1 | M2: 1 | N2: Polonia | O2: 1 | P2: 1 | Q2: Estados Unidos | R2: 1 | S2: 1 | T2: Japon | U2: 1 | V2: 1 | W2: China | X2: 1 | Y2: 1 | Z2: Escocia | AA2: 1 | AB2: 1 | AC2: Espania | AD2: 1 | AE2: 1 | AF2: Sudafrica | AG2: 1 | AH2: 1 | AI2: Egipto | AJ2: 1 | AK2: 1 | AL2: Noruega | AM2: 1 | AN2: 1 | AO2: China | AP2: 1 | AQ2: 1 | AR2: Francia | AS2: 1 | AT2: 1 | AU2: Paises Bajos | AV2: 1 | AW2: 1 | AX2: Corea del Sur | AY2: 1 | AZ2: 1 | BA2: Japon | BB2: 1 | BC2: 1 | BD2: Italia Fem | BE2: 1 | BF2: 1 | BG2: Estados Unidos Fem | BH2: 1 | BI2: 1 | BJ2: Japon Fem | BK2: 1 | BL2: 1 | BM2: China Fem | BN2: 1 | BO2: 1 | BP2: Suiza Fem | BQ2: 1 | BR2: 1 | BS2: Rusia Fem | BT2: 1 | BU2: 1 | BV2: Inglaterra Fem | BW2: 1 | BX2: 1 | BY2: Egipto Fem | BZ2: 1 | CA2: 1 | CB2: Brasil Fem | CC2: 1 | CD2: 1 | CE2: China Fem | CF2: 1 | CG2: 1 | CH2: Rusia Fem | CI2: 1 | CJ2: 1 | CK2: Paises Bajos Fem | CL2: 1 | CM2: 1 | CN2: Corea del Sur Fem | CO2: 1 | CP2: 1 | CQ2: Italia Fem | CR2: 1 | CS2: 1
B3: Argentina | C3: 1 | D3: 2 | E3: Estados Unidos Fem | F3: 1 | G3: 2 | H3: Portugal | I3: 1 | J3: 2 | K3: Espania Fem | L3: 1 | M3: 2 | N3: Italia | O3: 1 | P3: 2 | Q3: Alemania | R3: 1 | S3: 2 | T3: Taiwan | U3: 1 | V3: 2 | W3: Indonesia | X3: 1 | Y3: 2 | Z3: Canada | AA3: 1 | AB3: 2 | AC3: Italia | AD3: 1 | AE3: 2 | AF3: Nueva Zelanda | AG3: 1 | AH3: 2 | AI3: Nueva Zelanda | AJ3: 1 | AK3: 2 | AL3: Suecia | AM3: 1 | AN3: 2 | AO3: Brasil | AP3: 1 | AQ3: 2 | AR3: Suecia | AS3: 1 | AT3: 2 | AU3: Belgica | AV3: 1 | AW3: 2 | AX3: Francia | AY3: 1 | AZ3: 2 | BA3: Hungria | BB3: 1 | BC3: 2 | BD3: Brasil Fem | BE3: 1 | BF3: 2 | BG3: Australia Fem | BH3: 1 | BI3: 2 | BJ3: Estados Unidos Fem | BK3: 1 | BL3: 2 | BM3: Indonesia Fem | BN3: 1 | BO3: 2 | BP3: Canada Fem | BQ3: 1 | BR3: 2 | BS3: Polonia Fem | BT3: 1 | BU3: 2 | BV3: Canada Fem | BW3: 1 | BX3: 2 | BY3: Estados Unidos Fem | BZ3: 1 | CA3: 2 | CB3: Estados Unidos Fem | CC3: 1 | CD3: 2 | CE3: Macao Fem | CF3: 1 | CG3: 2 | CH3: Noruega Fem | CI3: 1 | CJ3: 2 | CK3: Argentina Fem | CL3: 1 | CM3: 2 | CN3: Taiwan Fem | CO3: 1 | CP3: 2 | CQ3: Francia Fem | CR3: 1 | CS3: 2
B4: Francia | C4: 1 | D4: 3 | E4: Alemania Fem | F4: 1 | G4: 3 | H4: Espania | I4: 1 | J4: 3 | K4: Portugal Fem | L4: 1 | M4: 3 | N4: Brasil | O4: 1 | P4: 3 | Q4: Serbia | R4: 1 | S4: 3 | T4: Estados Unidos | U4: 1 | V4: 3 | W4: Corea del Sur | X4: 1 | Y4: 3 | Z4: Suecia | AA4: 1 | AB4: 3 | AC4: Alemania | AD4: 1 | AE4: 3 | AF4: Inglaterra | AG4: 1 | AH4: 3 | AI4: Peru | AJ4: 1 | AK4: 3 | AL4: Brasil | AM4: 1 | AN4: 3 | AO4: Suecia | AP4: 1 | AQ4: 3 | AR4: Dinamarca | AS4: 2 | AT4: 3 | AU4: Alemania | AV4: 1 | AW4: 3 | AX4: Estados Unidos | AY4: 1 | AZ4: 3 | BA4: Suiza | BB4: 1 | BC4: 3 | BD4: Turquia Fem | BE4: 1 | BF4: 3 | BG4: Francia Fem | BH4: 1 | BI4: 3 | BJ4: Canada Fem | BK4: 1 | BL4: 3 | BM4: Corea del Sur Fem | BN4: 1 | BO4: 3 | BP4: Corea del Sur Fem | BQ4: 1 | BR4: 3 | BS4: Estados Unidos Fem | BT4: 1 | BU4: 3 | BV4: Nueva Zelanda Fem | BW4: 1 | BX4: 3 | BY4: Malasia Fem | BZ4: 2 | CA4: 3 | CB4: Letonia Fem | CC4: 1 | CD4: 3 | CE4: Japon Fem | CF4: 1 | CG4: 3 | CH4: Alemania Fem | CI4: 2 | CJ4: 3 | CK4: Belgica Fem | CL4: 1 | CM4: 3 | CN4: China Fem | CO4: 1 | CP4: 3 | CQ4: Corea del Sur Fem | CR4: 1 | CS4: 3
B5: Inglaterra | C5: 1 | D5: 4 | E5: Inglaterra Fem | F5: 1 | G5: 4 | H5: Argentina | I5: 1 | J5: 4 | K5: Argentina Fem | L5: 1 | M5: 4 | N5: Francia | O5: 1 | P5: 4 | Q5: Francia | R5: 1 | S5: 4 | T5: Corea del Sur | U5: 1 | V5: 4 | W5: Dinamarca | X5: 2 | Y5: 4 | Z5: Suiza | AA5: 1 | AB5: 4 | AC5: Serbia | AD5: 1 | AE5: 4 | AF5: Irlanda | AG5: 1 | AH5: 4 | AI5: Gales | AJ5: 2 | AK5: 4 | AL5: Paises Bajos | AM5: 1 | AN5: 4 | AO5: Japon | AP5: 1 | AQ5: 4 | AR5: Rumania | AS5: 2 | AT5: 4 | AU5: Argentina | AV5: 1 | AW5: 4 | AX5: India | AY5: 1 | AZ5: 4 | BA5: Francia | BB5: 1 | BC5: 4 | BD5: Polonia Fem | BE5: 1 | BF5: 4 | BG5: China Fem | BH5: 1 | BI5: 4 | BJ5: Mexico Fem | BK5: 2 | BL5: 4 | BM5: Dinamarca Fem | BN5: 2 | BO5: 4 | BP5: Suecia Fem | BQ5: 1 | BR5: 4 | BS5: Kazajistan Fem | BT5: 1 | BU5: 4 | BV5: Francia Fem | BW5: 1 | BX5: 4 | BY5: Japon Fem | BZ5: 2 | CA5: 4 | CB5: Alemania Fem | CC5: 1 | CD5: 4 | CE5: Corea del Sur Fem | CF5: 1 | CG5: 4 | CH5: Francia Fem | CI5: 2 | CJ5: 4 | CK5: China Fem | CL5: 1 | CM5: 4 | CN5: Estados Unidos Fem | CO5: 1 | CP5: 4 | CQ5: Estados Unidos Fem | CR5: 1 | CS5: 4
B6: Brasil | C6: 1 | D6: 5 | E6: Suecia Fem | F6: 1 | G6: 5 | H6: Iran | I6: 1 | J6: 5 | K6: Italia Fem | L6: 1 | M6: 5 | N6: Estados Unidos | O6: 1 | P6: 5 | Q6: Canada | R6: 1 | S6: 5 | T6: Venezuela | U6: 1 | V6: 5 | W6: Japon | X6: 2 | Y6: 5 | Z6: Italia | AA6: 1 | AB6: 5 | AC6: Australia | AD6: 2 | AE6: 5 | AF6: Francia | AG6: 1 | AH6: 5 | AI6: Inglaterra | AJ6: 2 | AK6: 5 | AL6: Qatar | AM6: 1 | AN6: 5 | AO6: Francia | AP6: 1 | AQ6: 5 | AR6: Alemania | AS6: 3 | AT6: 5 | AU6: Australia | AV6: 1 | AW6: 5 | AX6: Japon | AY6: 1 | AZ6: 5 | BA6: Italia | BB6: 1 | BC6: 5 | BD6: Japon Fem | BE6: 1 | BF6: 5 | BG6: Belgica Fem | BH6: 1 | BI6: 5 | BJ6: Venezuela Fem | BK6: 2 | BL6: 5 | BM6: Japon Fem | BN6: 2 | BO6: 5 | BP6: Japon Fem | BQ6: 2 | BR6: 5 | BS6: Italia Fem | BT6: 2 | BU6: 5 | BV6: Irlanda Fem | BW6: 1 | BX6: 5 | BY6: Belgica Fem | BZ6: 3 | CA6: 5 | CB6: Italia Fem | CC6: 2 | CD6: 5 | CE6: Alemania Fem | CF6: 1 | CG6: 5 | CH6: Hungria Fem | CI6: 3 | CJ6: 5 | CK6: Espania Fem | CL6: 1 | CM6: 5 | CN6: Japon Fem | CO6: 1 | CP6: 5 | CQ6: Estonia Fem | CR6: 1 | CS6: 5
B7: Portugal | C7: 1 | D7: 6 | E7: Brasil Fem | F7: 1 | G7: 6 | H7: Marruecos | I7: 1 | J7: 6 | K7: Japon Fem | L7: 1 | M7: 6 | N7: Eslovenia | O7: 1 | P7: 6 | Q7: Australia | R7: 1 | S7: 6 | T7: Mexico | U7: 2 | V7: 6 | W7: Tailandia | X7: 2 | Y7: 6 | Z7: Estados Unidos | AA7: 2 | AB7: 6 | AC7: Canada | AD7: 2 | AE7: 6 | AF7: Argentina | AG7: 1 | AH7: 6 | AI7: Francia | AJ7: 2 | AK7: 6 | AL7: Republica Checa | AM7: 2 | AN7: 6 | AO7: Taiwan | AP7: 2 | AQ7: 6 | AR7: Rusia | AS7: 3 | AT7: 6 | AU7: Espania | AV7: 1 | AW7: 6 | AX7: China | AY7: 1 | AZ7: 6 | BA7: Kazajistan | BB7: 1 | BC7: 6 | BD7: China Fem | BE7: 1 | BF7: 6 | BG7: Espania Fem | BH7: 1 | BI7: 6 | BJ7: Taiwan Fem | BK7: 2 | BL7: 6 | BM7: Tailandia Fem | BN7: 2 | BO7: 6 | BP7: Escocia Fem | BQ7: 2 | BR7: 6 | BS7: Suiza Fem | BT7: 2 | BU7: 6 | BV7: Escocia Fem | BW7: 2 | BX7: 6 | BY7: Inglaterra Fem | BZ7: 3 | CA7: 6 | CB7: Canada Fem | CC7: 2 | CD7: 6 | CE7: Brasil Fem | CF7: 2 | CG7: 6 | CH7: Serbia Fem | CI7: 3 | CJ7: 6 | CK7: Australia Fem | CL7: 2 | CM7: 6 | CN7: Italia Fem | CO7: 1 | CP7: 6 | CQ7: China Fem | CR7: 2 | CS7: 6
B8: Paises Bajos | C8: 1 | D8: 7 | E8: Francia Fem | F8: 1 | G8: 7 | H8: Rusia | I8: 1 | J8: 7 | K8: Colombia Fem | L8: 1 | M8: 7 | N8: Japon | O8: 1 | P8: 7 | Q8: Espania | R8: 1 | S8: 7 | T8: Puerto Rico | U8: 2 | V8: 7 | W8: Espania | X8: 3 | Y8: 7 | Z8: Alemania | AA8: 2 | AB8: 7 | AC8: Estados Unidos | AD8: 2 | AE8: 7 | AF8: Australia | AG8: 1 | AH8: 7 | AI8: Mexico | AJ8: 3 | AK8: 7 | AL8: Letonia | AM8: 2 | AN8: 7 | AO8: Alemania | AP8: 2 | AQ8: 7 | AR8: Espania | AS8: 3 | AT8: 7 | AU8: Inglaterra | AV8: 1 | AW8: 7 | AX8: Alemania | AY8: 1 | AZ8: 7 | BA8: Israel | BB8: 1 | BC8: 7 | BD8: Estados Unidos Fem | BE8: 1 | BF8: 7 | BG8: Canada Fem | BH8: 1 | BI8: 7 | BJ8: Cuba Fem | BK8: 3 | BL8: 7 | BM8: Espania Fem | BN8: 3 | BO8: 7 | BP8: Noruega Fem | BQ8: 2 | BR8: 7 | BS8: Ucrania Fem | BT8: 2 | BU8: 7 | BV8: Australia Fem | BW8: 2 | BX8: 7 | BY8: Francia Fem | BZ8: 3 | CA8: 7 | CB8: Suiza Fem | CC8: 2 | CD8: 7 | CE8: Puerto Rico Fem | CF8: 2 | CG8: 7 | CH8: Croacia Fem | CI8: 3 | CJ8: 7 | CK8: Alemania Fem | CL8: 2 | CM8: 7 | CN8: India Fem | CO8: 1 | CP8: 7 | CQ8: Polonia Fem | CR8: 2 | CS8: 7
B9: Belgica | C9: 1 | D9: 8 | E9: Japon Fem | F9: 1 | G9: 8 | H9: Ucrania | I9: 1 | J9: 8 | K9: Tailandia Fem | L9: 1 | M9: 8 | N9: Argentina | O9: 1 | P9: 8 | Q9: Argentina | R9: 1 | S9: 8 | T9: Panama | U9: 2 | V9: 8 | W9: Inglaterra | X9: 3 | Y9: 8 | Z9: Noruega | AA9: 2 | AB9: 8 | AC9: Kazajistan | AD9: 2 | AE9: 8 | AF9: Fiji | AG9: 1 | AH9: 8 | AI9: Malasia | AJ9: 3 | AK9: 8 | AL9: Polonia | AM9: 2 | AN9: 8 | AO9: Corea del Sur | AP9: 2 | AQ9: 8 | AR9: Croacia | AS9: 4 | AT9: 8 | AU9: India | AV9: 1 | AW9: 8 | AX9: Espania | AY9: 1 | AZ9: 8 | BA9: Ucrania | BB9: 2 | BC9: 8 | BD9: Paises Bajos Fem | BE9: 1 | BF9: 8 | BG9: Nigeria Fem | BH9: 1 | BI9: 8 | BJ9: Hong Kong Fem | BK9: 3 | BL9: 8 | BM9: Inglaterra Fem | BN9: 3 | BO9: 8 | BP9: Dinamarca Fem | BQ9: 2 | BR9: 8 | BS9: Republica Checa Fem | BT9: 2 | BU9: 8 | BV9: Estados Unidos Fem | BW9: 2 | BX9: 8 | BY9: Gales Fem | BZ9: 4 | CA9: 8 | CB9: Austria Fem | CC9: 2 | CD9: 8 | CE9: Taiwan Fem | CF9: 2 | CG9: 8 | CH9: Dinamarca Fem | CI9: 4 | CJ9: 8 | CK9: Inglaterra Fem | CL9: 2 | CM9: 8 | CN9: Alemania Fem | CO9: 1 | CP9: 8 | CQ9: Hungria Fem | CR9: 2 | CS9: 8
B10: Alemania | C10: 1 | D10: 9 | E10: Corea del Norte Fem | F10: 1 | G10: 9 | H10: Kazajistan | I10: 1 | J10: 9 | K10: Rusia Fem | L10: 2 | M10: 9 | N10: Bulgaria | O10: 1 | P10: 9 | Q10: Lituania | R10: 1 | S10: 9 | T10: Paises Bajos | U10: 2 | V10: 9 | W10: Malasia | X10: 3 | Y10: 9 | Z10: China | AA10: 2 | AB10: 9 | AC10: Inglaterra | AD10: 3 | AE10: 9 | AF10: Escocia | AG10: 1 | AH10: 9 | AI10: Suiza | AJ10: 3 | AK10: 9 | AL10: Cuba | AM10: 2 | AN10: 9 | AO10: Eslovenia | AP10: 2 | AQ10: 9 | AR10: Republica Checa | AS10: 4 | AT10: 9 | AU10: Francia | AV10: 1 | AW10: 9 | AX10: Brasil | AY10: 2 | AZ10: 9 | BA10: Paises Bajos | BB10: 2 | BC10: 9 | BD10: Serbia Fem | BE10: 2 | BF10: 9 | BG10: Brasil Fem | BH10: 1 | BI10: 9 | BJ10: Puerto Rico Fem | BK10: 3 | BL10: 9 | BM10: Malasia Fem | BN10: 3 | BO10: 9 | BP10: Italia Fem | BQ10: 3 | BR10: 9 | BS10: Dinamarca Fem | BT10: 3 | BU10: 9 | BV10: Italia Fem | BW10: 2 | BX10: 9 | BY10: Escocia Fem | BZ10: 4 | CA10: 9 | CB10: Francia Fem | CC10: 3 | CD10: 9 | CE10: Egipto Fem | CF10: 2 | CG10: 9 | CH10: Rumania Fem | CI10: 4 | CJ10: 9 | CK10: Nueva Zelanda Fem | CL10: 2 | CM10: 9 | CN10: Espania Fem | CO10: 2 | CP10: 9 | CQ10: Ucrania Fem | CR10: 2 | CS10: 9
B11: Croacia | C11: 1 | D11: 10 | E11: Canada Fem | F11: 1 | G11: 10 | H11: Francia | I11: 1 | J11: 10 | K11: Iran Fem | L11: 2 | M11: 10 | N11: Canada | O11: 1 | P11: 10 | Q11: Brasil | R11: 1 | S11: 10 | T11: Cuba | U11: 2 | V11: 10 | W11: India | X11: 3 | Y11: 10 | Z11: Japon | AA11: 2 | AB11: 10 | AC11: Rusia | AD11: 3 | AE11: 10 | AF11: Italia | AG11: 1 | AH11: 10 | AI11: Escocia | AJ11: 3 | AK11: 10 | AL11: Alemania | AM11: 2 | AN11: 10 | AO11: Dinamarca | AP11: 2 | AQ11: 10 | AR11: Eslovaquia | AS11: 4 | AT11: 10 | AU11: Nueva Zelanda | AV11: 1 | AW11: 10 | AX11: Taiwan | AY11: 2 | AZ11: 10 | BA11: Egipto | BB11: 2 | BC11: 10 | BD11: Alemania Fem | BE11: 2 | BF11: 10 | BG11: Serbia Fem | BH11: 1 | BI11: 10 | BJ11: Australia Fem | BK11: 3 | BL11: 10 | BM11: India Fem | BN11: 3 | BO11: 10 | BP11: Estados Unidos Fem | BQ11: 3 | BR11: 10 | BS11: Japon Fem | BT11: 3 | BU11: 10 | BV11: Sudafrica Fem | BW11: 2 | BX11: 10 | BY11: India Fem | BZ11: 4 | CA11: 10 | CB11: Finlandia Fem | CC11: 3 | CD11: 10 | CE11: Francia Fem | CF11: 2 | CG11: 10 | CH11: Republica Checa Fem | CI11: 4 | CJ11: 10 | CK11: India Fem | CL11: 2 | CM11: 10 | CN11: Malasia Fem | CO11: 2 | CP11: 10 | CQ11: Suiza Fem | CR11: 2 | CS11: 10
B12: Marruecos | C12: 1 | D12: 11 | E12: Paises Bajos Fem | F12: 1 | G12: 11 | H12: Tailandia | I12: 2 | J12: 11 | K12: Vietnam Fem | L12: 2 | M12: 11 | N12: Alemania | O12: 2 | P12: 11 | Q12: Turquia | R12: 2 | S12: 11 | T12: Australia | U12: 3 | V12: 11 | W12: Suecia | X12: 4 | Y12: 11 | Z12: Republica Checa | AA12: 3 | AB12: 11 | AC12: Noruega | AD12: 3 | AE12: 11 | AF12: Gales | AG12: 2 | AH12: 11 | AI12: Colombia | AJ12: 4 | AK12: 11 | AL12: Argentina | AM12: 3 | AN12: 11 | AO12: Estados Unidos | AP12: 2 | AQ12: 11 | AR12: Serbia | AS12: 5 | AT12: 11 | AU12: Irlanda | AV12: 2 | AW12: 11 | AX12: Italia | AY12: 2 | AZ12: 11 | BA12: China | BB12: 2 | BC12: 11 | BD12: Republica Dominicana Fem | BE12: 2 | BF12: 11 | BG12: Japon Fem | BH12: 2 | BI12: 11 | BJ12: Indonesia Fem | BK12: 3 | BL12: 11 | BM12: Suecia Fem | BN12: 4 | BO12: 11 | BP12: China Fem | BQ12: 3 | BR12: 11 | BS12: Canada Fem | BT12: 3 | BU12: 11 | BV12: Japon Fem | BW12: 3 | BX12: 11 | BY12: Hong Kong Fem | BZ12: 5 | CA12: 11 | CB12: Ucrania Fem | CC12: 3 | CD12: 11 | CE12: Rumania Fem | CF12: 3 | CG12: 11 | CH12: Eslovaquia Fem | CI12: 5 | CJ12: 11 | CK12: Japon Fem | CL12: 3 | CM12: 11 | CN12: Mexico Fem | CO12: 2 | CP12: 11 | CQ12: Canada Fem | CR12: 3 | CS12: 11
B13: Italia | C13: 1 | D13: 12 | E13: Noruega Fem | F13: 1 | G13: 12 | H13: Paraguay | I13: 2 | J13: 12 | K13: Paraguay Fem | L13: 2 | M13: 12 | N13: Cuba | O13: 2 | P13: 12 | Q13: Letonia | R13: 2 | S13: 12 | T13: Republica Dominicana | U13: 3 | V13: 12 | W13: Singapur | X13: 4 | Y13: 12 | Z13: Corea del Sur | AA13: 3 | AB13: 12 | AC13: Dinamarca | AD13: 3 | AE13: 12 | AF13: Japon | AG13: 2 | AH13: 12 | AI13: Qatar | AJ13: 4 | AK13: 12 | AL13: Francia | AM13: 3 | AN13: 12 | AO13: Croacia | AP13: 2 | AQ13: 12 | AR13: Noruega | AS13: 5 | AT13: 12 | AU13: Sudafrica | AV13: 2 | AW13: 12 | AX13: Turquia | AY13: 2 | AZ13: 12 | BA13: Venezuela | BB13: 2 | BC13: 12 | BD13: Canada Fem | BE13: 2 | BF13: 12 | BG13: Alemania Fem | BH13: 2 | BI13: 12 | BJ13: Corea del Sur Fem | BK13: 3 | BL13: 12 | BM13: Singapur Fem | BN13: 4 | BO13: 12 | BP13: Turquia Fem | BQ13: 3 | BR13: 12 | BS13: Belgica Fem | BT13: 3 | BU13: 12 | BV13: Gales Fem | BW13: 3 | BX13: 12 | BY13: Canada Fem | BZ13: 5 | CA13: 12 | CB13: Paises Bajos Fem | CC13: 3 | CD13: 12 | CE13: Austria Fem | CF13: 3 | CG13: 12 | CH13: Paises Bajos Fem | CI13: 5 | CJ13: 12 | CK13: Estados Unidos Fem | CL13: 3 | CM13: 12 | CN13: Francia Fem | CO13: 2 | CP13: 12 | CQ13: Rusia Fem | CR13: 3 | CS13: 12
... B17: Uruguay | C17: 2 | D17: 16 | E17: Islandia Fem | F17: 2 | G17: 16 | H17: Italia | I17: 2 | J17: 16 | K17: Taiwan Fem | L17: 3 | M17: 16 | N17: Iran | O17: 2 | P17: 16 | Q17: Puerto Rico | R17: 2 | S17: 16 | T17: Nicaragua | U17: 3 | V17: 16 | W17: Paises Bajos | X17: 5 | Y17: 16 | Z17: Finlandia | AA17: 3 | AB17: 16 | AC17: Brasil | AD17: 3 | AE17: 16 | AF17: Estados Unidos | AG17: 2 | AH17: 16 | AI17: Alemania | AJ17: 5 | AK17: 16 | AL17: Australia | AM17: 3 | AN17: 16 | AO17: Polonia | AP17: 2 | AQ17: 16 | AR17: Qatar | AS17: 6 | AT17: 16 | AU17: Corea del Sur | AV17: 2 | AW17: 16 | AX17: Ucrania | AY17: 2 | AZ17: 16 | BA17: Corea del Sur | BB17: 3 | BC17: 16 | BD17: Ucrania Fem | BE17: 2 | BF17: 16 | BG17: Turquia Fem | BH17: 2 | BI17: 16 | BJ17: Tailandia Fem | BK17: 4 | BL17: 16 | BM17: Paises Bajos Fem | BN17: 5 | BO17: 16 | BP17: Hungria Fem | BQ17: 3 | BR17: 16 | BS17: Inglaterra Fem | BT17: 3 | BU17: 16 | BV17: Hong Kong Fem | BW17: 3 | BX17: 16 | BY17: Sudafrica Fem | BZ17: 6 | CA17: 16 | CB17: Nueva Zelanda Fem | CC17: 3 | CD17: 16 | CE17: India Fem | CF17: 3 | CG17: 16 | CH17: Austria Fem | CI17: 6 | CJ17: 16 | CK17: Corea del Sur Fem | CL17: 3 | CM17: 16 | CN17: Eslovenia Fem | CO17: 2 | CP17: 16 | CQ17: Israel Fem | CR17: 3 | CS17: 16
B18: Suiza | C18: 2 | D18: 17 | E18: China Fem | F18: 2 | G18: 17 | H18: Republica Checa | I18: 2 | J18: 17 | K18: Finlandia Fem | L18: 3 | M18: 17 | N18: Ucrania | O18: 2 | P18: 17 | Q18: Finlandia | R18: 2 | S18: 17 | T18: China | U18: 3 | V18: 17 | W18: Escocia | X18: 5 | Y18: 17 | Z18: Austria | AA18: 3 | AB18: 17 | AC18: Belgica | AD18: 3 | AE18: 17 | AF18: Chile | AG18: 2 | AH18: 17 | AI18: Hong Kong | AJ18: 5 | AK18: 17 | AL18: Portugal | AM18: 3 | AN18: 17 | AO18: Australia | AP18: 2 | AQ18: 17 | AR18: Eslovenia | AS18: 6 | AT18: 17 | AU18: Egipto | AV18: 2 | AW18: 17 | AX18: Belgica | AY18: 3 | AZ18: 17 | BA18: Republica Checa | BB18: 3 | BC18: 17 | BD18: Argentina Fem | BE18: 3 | BF18: 17 | BG18: Republica Checa Fem | BH18: 2 | BI18: 17 | BJ18: Pakistan Fem | BK18: 4 | BL18: 17 | BM18: Escocia Fem | BN18: 5 | BO18: 17 | BP18: Nueva Zelanda Fem | BQ18: 3 | BR18: 17 | BS18: Australia Fem | BT18: 3 | BU18: 17 | BV18: Paises Bajos Fem | BW18: 3 | BX18: 17 | BY18: Alemania Fem | BZ18: 6 | CA18: 17 | CB18: Puerto Rico Fem | CC18: 3 | CD18: 17 | CE18: Suecia Fem | CF18: 3 | CG18: 17 | CJ18: 17 | CK18: Francia Fem | CL18: 3 | CM18: 17 | CN18: Indonesia Fem | CO18: 3 | CP18: 17 | CQ18: Suecia Fem | CR18: 3 | CS18: 17
B19: Japon | C19: 2 | D19: 18 | E19: Belgica Fem | F19: 2 | G19: 18 | H19: Venezuela | I19: 2 | J19: 18 | K19: Indonesia Fem | L19: 3 | M19: 18 | N19: Republica Checa | O19: 2 | P19: 18 | Q19: Montenegro | R19: 2 | S19: 18 | T19: Alemania | U19: 3 | V19: 18 | W19: Alemania | X19: 5 | Y19: 18 | Z19: Espania | AA19: 3 | AB19: 18 | AC19: Bulgaria | AD19: 3 | AE19: 18 | AF19: Tonga | AG19: 2 | AH19: 18 | AI19: Hungria | AJ19: 5 | AK19: 18 | AL19: Suiza | AM19: 3 | AN19: 18 | AO19: Rumania | AP19: 3 | AQ19: 18 | AT19: 18 | AU19: Japon | AV19: 2 | AW19: 18 | AX19: Colombia | AY19: 3 | AZ19: 18 | BA19: Canada | BB19: 3 | BC19: 18 | BD19: Tailandia Fem | BE19: 3 | BF19: 18 | BG19: Mali Fem | BH19: 2 | BI19: 18 | BJ19: Republica Checa Fem | BK19: 4 | BL19: 18 | BM19: Alemania Fem | BN19: 5 | BO19: 18 | BP19: Lituania Fem | BQ19: 3 | BR19: 18 | BS19: Francia Fem | BT19: 3 | BU19: 18 | BV19: Rusia Fem | BW19: 3 | BX19: 18 | BY19: Mexico Fem | BZ19: 6 | CA19: 18 | CB19: Paraguay Fem | CC19: 3 | CD19: 18 | CE19: Canada Fem | CF19: 3 | CG19: 18 | CJ19: 18 | CK19: Italia Fem | CL19: 3 | CM19: 18 | CN19: Brasil Fem | CO19: 3 | CP19: 18 | CQ19: Rumania Fem | CR19: 3 | CS19: 18
B20: Senegal | C20: 2 | D20: 19 | E20: Austria Fem | F20: 2 | G20: 19 | H20: Polonia | I20: 2 | J20: 19 | K20: Suecia Fem | L20: 3 | M20: 19 | N20: Finlandia | O20: 2 | P20: 19 | Q20: Polonia | R20: 2 | S20: 19 | T20: Inglaterra | U20: 3 | V20: 19 | W20: Francia | X20: 6 | Y20: 19 | Z20: Nueva Zelanda | AA20: 3 | AB20: 19 | AC20: Portugal | AD20: 4 | AE20: 19 | AF20: Samoa | AG20: 2 | AH20: 19 | AI20: Japon | AJ20: 6 | AK20: 19 | AL20: Italia | AM20: 3 | AN20: 19 | AO20: Hong Kong | AP20: 3 | AQ20: 19 | AT20: 19 | AU20: Canada | AV20: 2 | AW20: 19 | AX20: Israel | AY20: 3 | AZ20: 19 | BA20: Polonia | BB20: 3 | BC20: 19 | BD20: Mexico Fem | BE20: 3 | BF20: 19 | BG20: Colombia Fem | BH20: 2 | BI20: 19 | BJ20: China Fem | BK20: 5 | BL20: 19 | BM20: Francia Fem | BN20: 6 | BO20: 19 | BP20: Letonia Fem | BQ20: 4 | BR20: 19 | BS20: Rumania Fem | BT20: 4 | BU20: 19 | BV20: Kazajistan Fem | BW20: 3 | BX20: 19 | CA20: 19 | CB20: Polonia Fem | CC20: 3 | CD20: 19 | CE20: Gales Fem | CF20: 3 | CG20: 19 | CJ20: 19 | CK20: Uruguay Fem | CL20: 3 | CM20: 19 | CN20: Kazajistan Fem | CO20: 3 | CP20: 19 | CQ20: Kazajistan Fem | CR20: 3 | CS20: 19
B21: Iran | C21: 2 | D21: 20 | E21: Colombia Fem | F21: 2 | G21: 20 | H21: Vietnam | I21: 2 | J21: 20 | K21: Polonia Fem | L21: 3 | M21: 20 | N21: Paises Bajos | O21: 2 | P21: 20 | Q21: Georgia | R21: 2 | S21: 20 | T21: Canada | U21: 3 | V21: 20 | W21: Canada | X21: 6 | Y21: 20 | Z21: Inglaterra | AA21: 3 | AB21: 20 | AC21: Polonia | AD21: 4 | AE21: 20 | AF21: Portugal | AG21: 2 | AH21: 20 | AI21: Espania | AJ21: 6 | AK21: 20 | AL21: Canada | AM21: 3 | AN21: 20 | AO21: Belgica | AP21: 3 | AQ21: 20 | AT21: 20 | AU21: Escocia | AV21: 2 | AW21: 20 | AX21: Australia | AY21: 3 | AZ21: 20 | BA21: Taiwan | BB21: 3 | BC21: 20 | BD21: Eslovenia Fem | BE21: 3 | BF21: 20 | BG21: Hungria Fem | BH21: 2 | BI21: 20 | BJ21: Sri Lanka Fem | BK21: 5 | BL21: 20 | BM21: Canada Fem | BN21: 6 | BO21: 20 | BP21: Eslovenia Fem | BQ21: 4 | BR21: 20 | BS21: Alemania Fem | BT21: 4 | BU21: 20 | BV21: Kenia Fem | BW21: 3 | BX21: 20 | CA21: 20 | CB21: Japon Fem | CC21: 4 | CD21: 20 | CE21: Croacia Fem | CF21: 3 | CG21: 20 | CJ21: 20 | CK21: Sudafrica Fem | CL21: 3 | CM21: 20 | CN21: Vietnam Fem | CO21: 3 | CP21: 20 | CQ21: Finlandia Fem | CR21: 3 | CS21: 20
B22: Dinamarca | C22: 2 | D22: 21 | E22: Corea del Sur Fem | F22: 2 | G22: 21 | H22: Eslovenia | I22: 3 | J22: 21 | K22: Paises Bajos Fem | L22: 3 | M22: 21 | N22: Qatar | O22: 3 | P22: 21 | Q22: Republica Dominicana | R22: 3 | S22: 21 | T22: Israel | U22: 3 | V22: 21 | W22: Nueva Zelanda | X22: 6 | Y22: 21 | Z22: Taiwan | AA22: 3 | AB22: 21 | AC22: Bosnia y Herzegovina | AD22: 4 | AE22: 21 | AF22: Belgica | AG22: 3 | AH22: 21 | AI22: Argentina | AJ22: 6 | AK22: 21 | AL22: Inglaterra | AM22: 3 | AN22: 21 | AO22: Rusia | AP22: 3 | AQ22: 21 | AT22: 21 | AU22: Austria | AV22: 3 | AW22: 21 | AX22: Canada | AY22: 3 | AZ22: 21 | BA22: Espania | BB22: 3 | BC22: 21 | BD22: Kenia Fem | BE22: 3 | BF22: 21 | BG22: Nueva Zelanda Fem | BH22: 3 | BI22: 21 | BJ22: Filipinas Fem | BK22: 5 | BL22: 21 | BM22: Nueva Zelanda Fem | BN22: 6 | BO22: 21 | BP22: Austria Fem | BQ22: 4 | BR22: 21 | BS22: Filipinas Fem | BT22: 4 | BU22: 21 | BV22: Suecia Fem | BW22: 3 | BX22: 21 | CA22: 21 | CB22: Estonia Fem | CC22: 4 | CD22: 21 | CE22: Portugal Fem | CF22: 3 | CG22: 21 | CJ22: 21 | CK22: Malasia Fem | CL22: 3 | CM22: 21 | CN22: Ucrania Fem | CO22: 3 | CP22: 21 | CQ22: Espania Fem | CR22: 3 | CS22: 21
B23: Corea del Sur | C23: 2 | D23: 22 | E23: Portugal Fem | F23: 2 | G23: 22 | H23: Uzbekistan | I23: 3 | J23: 22 | K23: Venezuela Fem | L23: 3 | M23: 22 | N23: Puerto Rico | O23: 3 | P23: 22 | Q23: Japon | R23: 3 | S23: 22 | T23: Brasil | U23: 3 | V23: 22 | W23: Vietnam | X23: 6 | Y23: 22 | Z23: Australia | AA23: 3 | AB23: 22 | AC23: Chile | AD23: 4 | AE23: 22 | AF23: Rumania | AG23: 3 | AH23: 22 | AI23: Canada | AJ23: 6 | AK23: 22 | AL23: Israel | AM23: 3 | AN23: 22 | AO23: Canada | AP23: 3 | AQ23: 22 | AT23: 22 | AU23: Chile | AV23: 3 | AW23: 22 | AX23: Inglaterra | AY23: 3 | AZ23: 22 | BA23: Alemania | BB23: 3 | BC23: 22 | BD23: Colombia Fem | BE23: 3 | BF23: 22 | BG23: Inglaterra Fem | BH23: 3 | BI23: 22 | BJ23: Nicaragua Fem | BK23: 5 | BL23: 22 | BM23: Vietnam Fem | BN23: 6 | BO23: 22 | BP23: Inglaterra Fem | BQ23: 4 | BR23: 22 | BS23: Colombia Fem | BT23: 4 | BU23: 22 | BV23: Alemania Fem | BW23: 3 | BX23: 22 | CA23: 22 | CB23: Mexico Fem | CC23: 4 | CD23: 22 | CE23: Ucrania Fem | CF23: 3 | CG23: 22 | CJ23: 22 | CK23: Canada Fem | CL23: 3 | CM23: 22 | CN23: Colombia Fem | CO23: 3 | CP23: 22 | CQ23: Egipto Fem | CR23: 3 | CS23: 22
B24: Ecuador | C24: 2 | D24: 23 | E24: Finlandia Fem | F24: 2 | G24: 23 | H24: Armenia | I24: 3 | J24: 23 | K24: Hungria Fem | L24: 3 | M24: 23 | N24: Portugal | O24: 3 | P24: 23 | Q24: Republica Checa | R24: 3 | S24: 23 | T24: Sudafrica | U24: 3 | V24: 23 | Y24: 23 | Z24: Belgica | AA24: 4 | AB24: 23 | AC24: Peru | AD24: 4 | AE24: 23 | AF24: Hong Kong | AG24: 3 | AH24: 23 | AK24: 23 | AL24: Ucrania | AM24: 4 | AN24: 23 | AO24: Espania | AP24: 3 | AQ24: 23 | AT24: 23 | AU24: China | AV24: 3 | AW24: 23 | AX24: Uzbekistan | AY24: 3 | AZ24: 23 | BA24: Colombia | BB24: 3 | BC24: 23 | BD24: Puerto Rico Fem | BE24: 3 | BF24: 23 | BG24: Eslovenia Fem | BH24: 3 | BI24: 23 | BJ24: Malasia Fem | BK24: 5 | BL24: 23 | BO24: 23 | BP24: Eslovaquia Fem | BQ24: 4 | BR24: 23 | BS24: Grecia Fem | BT24: 4 | BU24: 23 | BV24: Portugal Fem | BW24: 3 | BX24: 23 | CA24: 23 | CB24: Noruega Fem | CC24: 4 | CD24: 23 | CE24: Paises Bajos Fem | CF24: 4 | CG24: 23 | CJ24: 23 | CK24: Bielorrusia Fem | CL24: 3 | CM24: 23 | CN24: Polonia Fem | CO24: 3 | CP24: 23 | CQ24: Singapur Fem | CR24: 4 | CS24: 23
B25: Austria | C25: 2 | D25: 24 | E25: Polonia Fem | F25: 2 | G25: 24 | H25: Indonesia | I25: 3 | J25: 24 | K25: Marruecos Fem | L25: 3 | M25: 24 | N25: Rumania | O25: 3 | P25: 24 | Q25: Sudan del Sur | R25: 3 | S25: 24 | T25: Filipinas | U25: 3 | V25: 24 | Y25: 24 | Z25: Letonia | AA25: 4 | AB25: 24 | AC25: Georgia | AD25: 4 | AE25: 24 | AF25: Zimbaue | AG25: 3 | AH25: 24 | AK25: 24 | AL25: Mexico | AM25: 4 | AN25: 24 | AO25: Argentina | AP25: 3 | AQ25: 24 | AT25: 24 | AU25: Polonia | AV25: 3 | AW25: 24 | AX25: Polonia | AY25: 3 | AZ25: 24 | BA25: Uzbekistan | BB25: 3 | BC25: 24 | BD25: Rumania Fem | BE25: 3 | BF25: 24 | BG25: Montenegro Fem | BH25: 3 | BI25: 24 | BJ25: Camboya Fem | BK25: 5 | BL25: 24 | BO25: 24 | BP25: Australia Fem | BQ25: 4 | BR25: 24 | BS25: Austria Fem | BT25: 4 | BU25: 24 | BV25: Belgica Fem | BW25: 3 | BX25: 24 | CA25: 24 | CB25: Hungria Fem | CC25: 4 | CD25: 24 | CE25: Turquia Fem | CF25: 4 | CG25: 24 | CJ25: 24 | CK25: Rusia Fem | CL25: 3 | CM25: 24 | CN25: Inglaterra Fem | CO25: 3 | CP25: 24 | CQ25: Colombia Fem | CR25: 4 | CS25: 24
B26: Turquia | C26: 2 | D26: 25 | E26: Suiza Fem | F26: 2 | G26: 25 | H26: Bielorrusia | I26: 3 | J26: 25 | K26: Uzbekistan Fem | L26: 3 | M26: 25 | N26: Grecia | O26: 3 | P26: 25 | Q26: Nueva Zelanda | R26: 3 | S26: 25 | T26: Francia | U26: 3 | V26: 25 | Y26: 25 | Z26: Eslovaquia | AA26: 4 | AB26: 25 | AC26: Francia | AD26: 4 | AE26: 25 | AF26: Canada | AG26: 3 | AH26: 25 | AK26: 25 | AL26: Nueva Zelanda | AM26: 4 | AN26: 25 | AO26: Kazajistan | AP26: 3 | AQ26: 25 | AT26: 25 | AU26: Estados Unidos | AV26: 3 | AW26: 25 | AX26: Bangladesh | AY26: 3 | AZ26: 25 | BA26: Estonia | BB26: 3 | BC26: 25 | BD26: Bulgaria Fem | BE26: 3 | BF26: 25 | BG26: Senegal Fem | BH26: 3 | BI26: 25 | BJ26: Sudafrica Fem | BK26: 6 | BL26: 25 | BO26: 25 | BP26: Taiwan Fem | BQ26: 4 | BR26: 25 | BS26: Indonesia Fem | BT26: 4 | BU26: 25 | BV26: Brasil Fem | BW26: 3 | BX26: 25 | CA26: 25 | CB26: Argentina Fem | CC26: 4 | CD26: 25 | CE26: Tailandia Fem | CF26: 4 | CG26: 25 | CJ26: 25 | CK26: Gales Fem | CL26: 3 | CM26: 25 | CN26: Georgia Fem | CO26: 3 | CP26: 25 | CQ26: Uzbekistan Fem | CR26: 4 | CS26: 25
B27: Australia | C27: 2 | D27: 26 | E27: Escocia Fem | F27: 2 | G27: 26 | H27: Serbia | I27: 3 | J27: 26 | K27: Ecuador Fem | L27: 3 | M27: 26 | N27: Corea del Sur | O27: 3 | P27: 26 | Q27: Iran | R27: 3 | S27: 26 | T27: Espania | U27: 3 | V27: 26 | Y27: 26 | Z27: Hungria | AA27: 4 | AB27: 26 | AC27: Japon | AD27: 4 | AE27: 26 | AF27: Paises Bajos | AG27: 3 | AH27: 26 | AK27: 26 | AL27: Belgica | AM27: 4 | AN27: 26 | AO27: Portugal | AP27: 3 | AQ27: 26 | AT27: 26 | AU27: Oman | AV27: 3 | AW27: 26 | AX27: Indonesia | AY27: 3 | AZ27: 26 | BA27: Arabia Saudita | BB27: 3 | BC27: 26 | BD27: Suecia Fem | BE27: 3 | BF27: 26 | BG27: Grecia Fem | BH27: 3 | BI27: 26 | BJ27: Argentina Fem | BK27: 6 | BL27: 26 | BO27: 26 | BP27: Finlandia Fem | BQ27: 4 | BR27: 26 | BS27: Brasil Fem | BT27: 4 | BU27: 26 | BV27: Tonga Fem | BW27: 4 | BX27: 26 | CA27: 26 | CB27: Tailandia Fem | CC27: 4 | CD27: 26 | CE27: Republica Checa Fem | CF27: 4 | CG27: 26 | CJ27: 26 | CK27: Polonia Fem | CL27: 3 | CM27: 26 | CN27: Moldavia Fem | CO27: 3 | CP27: 26 | CQ27: India Fem | CR27: 4 | CS27: 26
B28: Canada | C28: 2 | D28: 27 | E28: Irlanda Fem | F28: 2 | G28: 27 | H28: Colombia | I28: 3 | J28: 27 | K28: Malasia Fem | L28: 3 | M28: 27 | N28: Egipto | O28: 3 | P28: 27 | Q28: China | R28: 3 | S28: 27 | T28: Austria | U28: 3 | V28: 27 | Y28: 27 | Z28: Irlanda | AA28: 4 | AB28: 27 | AC28: China | AD28: 4 | AE28: 27 | AF28: Namibia | AG28: 3 | AH28: 27 | AK28: 27 | AL28: Dinamarca | AM28: 4 | AN28: 27 | AO28: Chile | AP28: 3 | AQ28: 27 | AT28: 27 | AU28: Rusia | AV28: 3 | AW28: 27 | AX28: Malasia | AY28: 3 | AZ28: 27 | BA28: Sudafrica | BB28: 3 | BC28: 27 | BD28: Cuba Fem | BE28: 3 | BF28: 27 | BG28: Argentina Fem | BH28: 3 | BI28: 27 | BJ28: Paises Bajos Fem | BK28: 6 | BL28: 27 | BO28: 27 | BP28: Kazajistan Fem | BQ28: 4 | BR28: 27 | BS28: Argentina Fem | BT28: 4 | BU28: 27 | BV28: China Fem | BW28: 4 | BX28: 27 | CA28: 27 | CB28: Peru Fem | CC28: 4 | CD28: 27 | CE28: Serbia Fem | CF28: 4 | CG28: 27 | CJ28: 27 | CK28: Republica Checa Fem | CL28: 3 | CM28: 27 | CN28: Costa de Marfil Fem | CO28: 3 | CP28: 27 | CQ28: Venezuela Fem | CR28: 4 | CS28: 27
B29: Ucrania | C29: 2 | D29: 28 | E29: Rusia Fem | F29: 2 | G29: 28 | H29: Afganistan | I29: 3 | J29: 28 | K29: Costa Rica Fem | L29: 3 | M29: 28 | N29: China | O29: 3 | P29: 28 | Q29: Libano | R29: 3 | S29: 28 | T29: Hong Kong | U29: 3 | V29: 28 | Y29: 28 | Z29: Rusia | AA29: 4 | AB29: 28 | AC29: Taiwan | AD29: 4 | AE29: 28 | AF29: Suiza | AG29: 3 | AH29: 28 | AK29: 28 | AL29: Uruguay | AM29: 4 | AN29: 28 | AO29: Luxemburgo | AP29: 3 | AQ29: 28 | AT29: 28 | AU29: Italia | AV29: 3 | AW29: 28 | AX29: Suiza | AY29: 3 | AZ29: 28 | BA29: Brasil | BB29: 3 | BC29: 28 | BD29: Vietnam Fem | BE29: 3 | BF29: 28 | BG29: Suecia Fem | BH29: 3 | BI29: 28 | BJ29: Iran Fem | BK29: 6 | BL29: 28 | BO29: 28 | BP29: Mexico Fem | BQ29: 4 | BR29: 28 | BS29: Serbia Fem | BT29: 4 | BU29: 28 | BV29: Colombia Fem | BW29: 4 | BX29: 28 | CA29: 28 | CB29: Eslovenia Fem | CC29: 4 | CD29: 28 | CE29: Italia Fem | CF29: 4 | CG29: 28 | CJ29: 28 | CK29: Tailandia Fem | CL29: 4 | CM29: 28 | CN29: Eslovaquia Fem | CO29: 3 | CP29: 28 | CQ29: Brasil Fem | CR29: 4 | CS29: 28
B30: Noruega | C30: 2 | D30: 29 | E30: Mexico Fem | F30: 2 | G30: 29 | H30: Paises Bajos | I30: 3 | J30: 29 | K30: Armenia Fem | L30: 3 | M30: 29 | N30: Chile | O30: 3 | P30: 29 | Q30: Venezuela | R30: 3 | S30: 29 | T30: Curazao | U30: 4 | V30: 29 | Y30: 29 | Z30: Gales | AA30: 4 | AB30: 29 | AC30: Finlandia | AD30: 5 | AE30: 29 | AF30: Republica Checa | AG30: 3 | AH30: 29 | AK30: 29 | AL30: Eslovaquia | AM30: 4 | AN30: 29 | AO30: Inglaterra | AP30: 3 | AQ30: 29 | AT30: 29 | AU30: Bangladesh | AV30: 3 | AW30: 29 | AX30: Eslovenia | AY30: 3 | AZ30: 29 | BA30: Finlandia | BB30: 3 | BC30: 29 | BD30: Grecia Fem | BE30: 3 | BF30: 29 | BG30: Bosnia y Herzegovina Fem | BH30: 3 | BI30: 29 | BJ30: Republica Dominicana Fem | BK30: 6 | BL30: 29 | BO30: 29 | BP30: Espania Fem | BQ30: 5 | BR30: 29 | BS30: Croacia Fem | BT30: 5 | BU30: 29 | BV30: Uganda Fem | BW30: 4 | BX30: 29 | CA30: 29 | CB30: Venezuela Fem | CC30: 4 | CD30: 29 | CE30: Chile Fem | CF30: 4 | CG30: 29 | CJ30: 29 | CK30: Ucrania Fem | CL30: 4 | CM30: 29 | CN30: Hong Kong Fem | CO30: 3 | CP30: 29 | CQ30: Argelia Fem | CR30: 4 | CS30: 29
B31: Panama | C31: 2 | D31: 30 | E31: Argentina Fem | F31: 2 | G31: 30 | H31: Uruguay | I31: 3 | J31: 30 | K31: Palestina Fem | L31: 3 | M31: 30 | N31: Israel | O31: 3 | P31: 30 | Q31: Mexico | R31: 3 | S31: 30 | T31: Tailandia | U31: 4 | V31: 30 | Y31: 30 | Z31: Estonia | AA31: 4 | AB31: 30 | AC31: Lituania | AD31: 5 | AE31: 30 | AF31: Polonia | AG31: 3 | AH31: 30 | AK31: 30 | AL31: Mozambique | AM31: 4 | AN31: 30 | AO31: Iran | AP31: 3 | AQ31: 30 | AT31: 30 | AU31: Ucrania | AV31: 3 | AW31: 30 | AX31: Hong Kong | AY31: 3 | AZ31: 30 | BA31: Suecia | BB31: 3 | BC31: 30 | BD31: Espania Fem | BE31: 3 | BF31: 30 | BG31: Mexico Fem | BH31: 3 | BI31: 30 | BL31: 30 | BO31: 30 | BP31: Brasil Fem | BQ31: 5 | BR31: 30 | BS31: Hungria Fem | BT31: 5 | BU31: 30 | BV31: Trinidad y Tobago Fem | BW31: 4 | BX31: 30 | CA31: 30 | CB31: Rumania Fem | CC31: 4 | CD31: 30 | CE31: Espania Fem | CF31: 4 | CG31: 30 | CJ31: 30 | CK31: Mexico Fem | CL31: 4 | CM31: 30 | CN31: Argelia Fem | CO31: 3 | CP31: 30 | CQ31: Argentina Fem | CR31: 4 | CS31: 30
B32: Polonia | C32: 3 | D32: 31 | E32: Republica Checa Fem | F32: 3 | G32: 31 | H32: Finlandia | I32: 3 | J32: 31 | K32: Nueva Zelanda Fem | L32: 4 | M32: 31 | N32: Suiza | O32: 3 | P32: 31 | Q32: Israel | R32: 3 | S32: 31 | T32: Peru | U32: 4 | V32: 31 | Y32: 31 | Z32: Francia | AA32: 4 | AB32: 31 | AC32: Austria | AD32: 5 | AE32: 31 | AF32: Paraguay | AG32: 3 | AH32: 31 | AK32: 31 | AL32: Indonesia | AM32: 4 | AN32: 31 | AO32: Camerun | AP32: 4 | AQ32: 31 | AT32: 31 | AU32: Mexico | AV32: 3 | AW32: 31 | AX32: Chile | AY32: 3 | AZ32: 31 | BA32: Inglaterra | BB32: 4 | BC32: 31 | BD32: Hungria Fem | BE32: 3 | BF32: 31 | BG32: Lituania Fem | BH32: 3 | BI32: 31 | BL32: 31 | BO32: 31 | BP32: Belgica Fem | BQ32: 5 | BR32: 31 | BS32: Mexico Fem | BT32: 5 | BU32: 31 | BV32: Madagascar Fem | BW32: 4 | BX32: 31 | CA32: 31 | CB32: Vanuatu Fem | CC32: 5 | CD32: 31 | CE32: Nigeria Fem | CF32: 4 | CG32: 31 | CJ32: 31 | CK32: Kenia Fem | CL32: 4 | CM32: 31 | CN32: Bangladesh Fem | CO32: 3 | CP32: 31 | CQ32: Inglaterra Fem | CR32: 4 | CS32: 31
B33: Gales | C33: 3 | D33: 32 | E33: Gales Fem | F33: 3 | G33: 32 | H33: Hungria | I33: 3 | J33: 32 | K33: Hong Kong Fem | L33: 4 | M33: 32 | N33: Mexico | O33: 3 | P33: 32 | Q33: Angola | R33: 3 | S33: 32 | T33: Croacia | U33: 4 | V33: 32 | Y33: 32 | Z33: Ucrania | AA33: 4 | AB33: 32 | AC33: Hong Kong | AD33: 5 | AE33: 32 | AF33: Rusia | AG33: 3 | AH33: 32 | AK33: 32 | AL33: Venezuela | AM33: 4 | AN33: 32 | AO33: Malta | AP33: 4 | AQ33: 32 | AT33: 32 | AU33: Republica Checa | AV33: 3 | AW33: 32 | AX33: Mongolia | AY33: 3 | AZ33: 32 | BA33: Panama | BB33: 4 | BC33: 32 | BD33: Suiza Fem | BE33: 3 | BF33: 32 | BG33: Mozambique Fem | BH33: 3 | BI33: 32 | BL33: 32 | BO33: 32 | BP33: Polonia Fem | BQ33: 5 | BR33: 32 | BS33: Nueva Zelanda Fem | BT33: 5 | BU33: 32 | BV33: Croacia Fem | BW33: 4 | BX33: 32 | CA33: 32 | CB33: Mozambique Fem | CC33: 5 | CD33: 32 | CE33: Argentina Fem | CF33: 4 | CG33: 32 | CJ33: 32 | CK33: Ghana Fem | CL33: 4 | CM33: 32 | CN33: Puerto Rico Fem | CO33: 3 | CP33: 32 | CQ33: Sudafrica Fem | CR33: 4 | CS33: 32
B34: Rusia | C34: 3 | D34: 33 | E34: Serbia Fem | F34: 3 | G34: 33 | H34: Panama | I34: 3 | J34: 33 | K34: Bolivia Fem | L34: 4 | M34: 33 | N34: Australia | O34: 3 | P34: 33 | Q34: Bosnia y Herzegovina | R34: 3 | S34: 33 | T34: Argentina | U34: 4 | V34: 33 | Y34: 33 | Z34: Polonia | AA34: 4 | AB34: 33 | AC34: Tunez | AD34: 5 | AE34: 33 | AF34: Suecia | AG34: 3 | AH34: 33 | AK34: 33 | AL34: Lituania | AM34: 4 | AN34: 33 | AO34: Benin | AP34: 4 | AQ34: 33 | AT34: 33 | AU34: Brasil | AV34: 3 | AW34: 33 | AX34: Vietnam | AY34: 3 | AZ34: 33 | BA34: Rusia | BB34: 4 | BC34: 33 | BD34: Eslovaquia Fem | BE34: 3 | BF34: 33 | BG34: Republica Dominicana Fem | BH34: 3 | BI34: 33 | BL34: 33 | BO34: 33 | BP34: Ucrania Fem | BQ34: 5 | BR34: 33 | BS34: Uzbekistan Fem | BT34: 5 | BU34: 33 | BV34: Georgia Fem | BW34: 4 | BX34: 33 | CA34: 33 | CB34: Ecuador Fem | CC34: 5 | CD34: 33 | CE34: Tunez Fem | CF34: 4 | CG34: 33 | CJ34: 33 | CK34: Austria Fem | CL34: 4 | CM34: 33 | CN34: Emiratos Arabes Unidos Fem | CO34: 3 | CP34: 33 | CQ34: Paises Bajos Fem | CR34: 4 | CS34: 33
B35: Argelia | C35: 3 | D35: 34 | E35: Ucrania Fem | F35: 3 | G35: 34 | H35: Belgica | I35: 3 | J35: 34 | K35: Guatemala Fem | L35: 4 | M35: 34 | N35: Estonia | O35: 3 | P35: 34 | Q35: Croacia | R35: 3 | S35: 34 | T35: Suiza | U35: 4 | V35: 34 | Y35: 34 | Z35: Kazajistan | AA35: 4 | AB35: 34 | AC35: Noruega | AD35: 5 | AE35: 34 | AF35: Brasil | AG35: 3 | AH35: 34 | AK35: 34 | AL35: Espania | AM35: 4 | AN35: 34 | AO35: Nueva Zelanda | AP35: 4 | AQ35: 34 | AT35: 34 | AU35: Bielorrusia | AV35: 3 | AW35: 34 | AX35: Georgia | AY35: 3 | AZ35: 34 | BA35: Argentina | BB35: 4 | BC35: 34 | BD35: Finlandia Fem | BE35: 3 | BF35: 34 | BG35: Eslovaquia Fem | BH35: 3 | BI35: 34 | BL35: 34 | BO35: 34 | BP35: Hong Kong Fem | BQ35: 5 | BR35: 34 | BS35: Paises Bajos Fem | BT35: 5 | BU35: 34 | BV35: Mexico Fem | BW35: 4 | BX35: 34 | CA35: 34 | CB35: Bolivia Fem | CC35: 5 | CD35: 34 | CE35: Uganda Fem | CF35: 4 | CG35: 34 | CJ35: 34 | CK35: Hong Kong Fem | CL35: 4 | CM35: 34 | CN35: Iran Fem | CO35: 3 | CP35: 34 | CQ35: Republica Checa Fem | CR35: 4 | CS35: 34
B36: Egipto | C36: 3 | D36: 35 | E36: Nueva Zelanda Fem | F36: 3 | G36: 35 | H36: Costa Rica | I36: 3 | J36: 35 | K36: Bahrein Fem | L36: 4 | M36: 35 | N36: Eslovaquia | O36: 3 | P36: 35 | Q36: Belgica | R36: 3 | S36: 35 | T36: Suecia | U36: 4 | V36: 35 | Y36: 35 | Z36: Hong Kong | AA36: 5 | AB36: 35 | AC36: Ghana | AD36: 5 | AE36: 35 | AF36: Alemania | AG36: 3 | AH36: 35 | AK36: 35 | AL36: Paraguay | AM36: 5 | AN36: 35 | AO36: Tunez | AP36: 4 | AQ36: 35 | AT36: 35 | AU36: Ghana | AV36: 3 | AW36: 35 | AX36: Dinamarca | AY36: 4 | AZ36: 35 | BA36: Argelia | BB36: 4 | BC36: 35 | BD36: Kazajistan Fem | BE36: 3 | BF36: 35 | BG36: Camerun Fem | BH36: 3 | BI36: 35 | BL36: 35 | BO36: 35 | BP36: Paises Bajos Fem | BQ36: 5 | BR36: 35 | BS36: Eslovenia Fem | BT36: 5 | BU36: 35 | BV36: Finlandia Fem | BW36: 4 | BX36: 35 | CA36: 35 | CB36: Filipinas Fem | CC36: 5 | CD36: 35 | CE36: Argelia Fem | CF36: 5 | CG36: 35 | CJ36: 35 | CK36: Turquia Fem | CL36: 4 | CM36: 35 | CN36: Grecia Fem | CO36: 4 | CP36: 35 | CQ36: Angola Fem | CR36: 5 | CS36: 35
B37: Escocia | C37: 3 | D37: 36 | E37: Vietnam Fem | F37: 3 | G37: 36 | H37: Rumania | I37: 3 | J37: 36 | K37: Rumania Fem | L37: 4 | M37: 36 | N37: Espania | O37: 3 | P37: 36 | Q37: Filipinas | R37: 3 | S37: 36 | T37: Guam | U37: 4 | V37: 36 | Y37: 36 | Z37: Eslovenia | AA37: 5 | AB37: 36 | AC37: Suiza | AD37: 5 | AE37: 36 | AF37: Kenia | AG37: 3 | AH37: 36 | AK37: 36 | AL37: Hungria | AM37: 5 | AN37: 36 | AO37: Argelia | AP37: 4 | AQ37: 36 | AT37: 36 | AU37: Nigeria | AV37: 3 | AW37: 36 | AX37: Mauricio | AY37: 4 | AZ37: 36 | BA37: Australia | BB37: 4 | BC37: 36 | BD37: Croacia Fem | BE37: 4 | BF37: 36 | BG37: Taiwan Fem | BH37: 3 | BI37: 36 | BL37: 36 | BO37: 36 | BP37: Gales Fem | BQ37: 5 | BR37: 36 | BS37: Tunez Fem | BT37: 5 | BU37: 36 | BV37: Andorra Fem | BW37: 4 | BX37: 36 | CA37: 36 | CB37: Nicaragua Fem | CC37: 5 | CD37: 36 | CE37: Nueva Zelanda Fem | CF37: 5 | CG37: 36 | CJ37: 36 | CK37: Singapur Fem | CL37: 4 | CM37: 36 | CN37: Kenia Fem | CO37: 4 | CP37: 36 | CQ37: Taiwan Fem | CR37: 5 | CS37: 36
B38: Serbia | C38: 3 | D38: 37 | E38: Nigeria Fem | F38: 3 | G38: 37 | H38: Irak | I38: 3 | J38: 37 | K38: Republica Checa Fem | L38: 4 | M38: 37 | N38: Republica Dominicana | O38: 3 | P38: 37 | Q38: Estonia | R38: 3 | S38: 37 | T38: Palestina | U38: 4 | V38: 37 | Y38: 37 | Z38: Brasil | AA38: 5 | AB38: 37 | AC38: Paraguay | AD38: 5 | AE38: 37 | AF38: Corea del Sur | AG38: 3 | AH38: 37 | AK38: 37 | AL38: Turquia | AM38: 5 | AN38: 37 | AO38: Singapur | AP38: 4 | AQ38: 37 | AT38: 37 | AU38: Venezuela | AV38: 3 | AW38: 37 | AX38: Iran | AY38: 4 | AZ38: 37 | BA38: India | BB38: 4 | BC38: 37 | BD38: Taiwan Fem | BE38: 4 | BF38: 37 | BG38: Letonia Fem | BH38: 3 | BI38: 37 | BL38: 37 | BO38: 37 | BP38: Jamaica Fem | BQ38: 5 | BR38: 37 | BS38: Egipto Fem | BT38: 5 | BU38: 37 | BV38: Tunez Fem | BW38: 4 | BX38: 37 | CA38: 37 | CB38: China Fem | CC38: 5 | CD38: 37 | CE38: Sudafrica Fem | CF38: 5 | CG38: 37 | CJ38: 37 | CK38: Cuba Fem | CL38: 4 | CM38: 37 | CN38: Mongolia Fem | CO38: 4 | CP38: 37 | CQ38: Nigeria Fem | CR38: 5 | CS38: 37
B39: Nigeria | C39: 3 | D39: 38 | E39: Eslovenia Fem | F39: 3 | G39: 38 | H39: Eslovaquia | I39: 3 | J39: 38 | K39: Birmania Fem | L39: 4 | M39: 38 | N39: Tunez | O39: 3 | P39: 38 | Q39: Jordania | R39: 3 | S39: 38 | T39: Belgica | U39: 4 | V39: 38 | Y39: 38 | Z39: Filipinas | AA39: 5 | AB39: 38 | AC39: Estonia | AD39: 5 | AE39: 38 | AF39: Mexico | AG39: 3 | AH39: 38 | AK39: 38 | AL39: Cuba | AM39: 5 | AN39: 38 | AO39: Puerto Rico | AP39: 4 | AQ39: 38 | AT39: 38 | AU39: Suiza | AV39: 3 | AW39: 38 | AX39: Butan | AY39: 4 | AZ39: 38 | BA39: Angola | BB39: 4 | BC39: 38 | BD39: Peru Fem | BE39: 4 | BF39: 38 | BG39: Portugal Fem | BH39: 3 | BI39: 38 | BL39: 38 | BO39: 38 | BP39: Rusia Fem | BQ39: 5 | BR39: 38 | BS39: Andorra Fem | BT39: 5 | BU39: 38 | BV39: Camerun Fem | BW39: 4 | BX39: 38 | CA39: 38 | CB39: Eslovaquia Fem | CC39: 5 | CD39: 38 | CE39: Rusia Fem | CF39: 5 | CG39: 38 | CJ39: 38 | CK39: Kazajistan Fem | CL39: 4 | CM39: 38 | CN39: Guatemala Fem | CO39: 4 | CP39: 38 | CQ39: Austria Fem | CR39: 5 | CS39: 38
B40: Paraguay | C40: 3 | D40: 39 | E40: Jamaica Fem | F40: 3 | G40: 39 | H40: Egipto | I40: 3 | J40: 39 | K40: Croacia Fem | L40: 4 | M40: 39 | N40: Croacia | O40: 3 | P40: 39 | Q40: Costa de Marfil | R40: 3 | S40: 39 | T40: Costa Rica | U40: 4 | V40: 39 | Y40: 39 | Z40: Guyana | AA40: 5 | AB40: 39 | AC40: Colombia | AD40: 6 | AE40: 39 | AF40: Marruecos | AG40: 3 | AH40: 39 | AK40: 39 | AL40: Estonia | AM40: 5 | AN40: 39 | AO40: Eslovaquia | AP40: 4 | AQ40: 39 | AT40: 39 | AU40: Sri Lanka | AV40: 3 | AW40: 39 | AX40: Costa de Marfil | AY40: 4 | AZ40: 39 | BA40: Singapur | BB40: 4 | BC40: 39 | BD40: Austria Fem | BE40: 4 | BF40: 39 | BG40: Filipinas Fem | BH40: 3 | BI40: 39 | BL40: 39 | BO40: 39 | BP40: Francia Fem | BQ40: 6 | BR40: 39 | BS40: Taiwan Fem | BT40: 6 | BU40: 39 | BV40: Austria Fem | BW40: 4 | BX40: 39 | CA40: 39 | CB40: Grecia Fem | CC40: 5 | CD40: 39 | CE40: Filipinas Fem | CF40: 5 | CG40: 39 | CJ40: 39 | CK40: Barbados Fem | CL40: 4 | CM40: 39 | CN40: Panama Fem | CO40: 4 | CP40: 39 | CQ40: Benin Fem | CR40: 5 | CS40: 39
B41: Hungria | C41: 3 | D41: 40 | E41: Taiwan Fem | F41: 3 | G41: 40 | H41: Kuwait | I41: 3 | J41: 40 | K41: Libano Fem | L41: 4 | M41: 40 | N41: Bahrein | O41: 3 | P41: 40 | Q41: Ucrania | R41: 3 | S41: 40 | T41: Bahamas | U41: 4 | V41: 40 | Y41: 40 | Z41: India | AA41: 5 | AB41: 40 | AC41: Ucrania | AD41: 6 | AE41: 40 | AF41: Emiratos Arabes Unidos | AG41: 3 | AH41: 40 | AK41: 40 | AL41: Nicaragua | AM41: 5 | AN41: 40 | AO41: Noruega | AP41: 4 | AQ41: 40 | AT41: 40 | AU41: Cuba | AV41: 3 | AW41: 40 | AX41: Cuba | AY41: 4 | AZ41: 40 | BA41: Eslovaquia | BB41: 4 | BC41: 40 | BD41: Corea del Sur Fem | BE41: 4 | BF41: 40 | BG41: Croacia Fem | BH41: 3 | BI41: 40 | BL41: 40 | BO41: 40 | BP41: Portugal Fem | BQ41: 6 | BR41: 40 | BS41: Bulgaria Fem | BT41: 6 | BU41: 40 | BV41: Jamaica Fem | BW41: 4 | BX41: 40 | CA41: 40 | CB41: Marruecos Fem | CC41: 5 | CD41: 40 | CE41: Ghana Fem | CF41: 5 | CG41: 40 | CJ41: 40 | CK41: Suiza Fem | CL41: 4 | CM41: 40 | CN41: Singapur Fem | CO41: 4 | CP41: 40 | CQ41: Mexico Fem | CR41: 5 | CS41: 40
B42: Tunez | C42: 3 | D42: 41 | E42: Filipinas Fem | F42: 3 | G42: 41 | H42: Nueva Zelanda | I42: 4 | J42: 41 | K42: Belgica Fem | L42: 4 | M42: 41 | N42: Dinamarca | O42: 4 | P42: 41 | Q42: Suecia | R42: 3 | S42: 41 | T42: Islas Virgenes Estadounidenses | U42: 4 | V42: 41 | Y42: 41 | Z42: Rumania | AA42: 5 | AB42: 41 | AC42: Ecuador | AD42: 6 | AE42: 41 | AF42: Colombia | AG42: 3 | AH42: 41 | AK42: 41 | AL42: El Salvador | AM42: 5 | AN42: 41 | AO42: Ecuador | AP42: 4 | AQ42: 41 | AT42: 41 | AU42: Gibraltar | AV42: 4 | AW42: 41 | AX42: Puerto Rico | AY42: 4 | AZ42: 41 | BA42: Libano | BB42: 4 | BC42: 41 | BD42: Portugal Fem | BE42: 4 | BF42: 41 | BG42: Libano Fem | BH42: 3 | BI42: 41 | BL42: 41 | BO42: 41 | BP42: Irlanda Fem | BQ42: 6 | BR42: 41 | BS42: Tailandia Fem | BT42: 6 | BU42: 41 | BV42: Letonia Fem | BW42: 5 | BX42: 41 | CA42: 41 | CB42: Kazajistan Fem | CC42: 5 | CD42: 41 | CE42: Malasia Fem | CF42: 5 | CG42: 41 | CJ42: 41 | CK42: Fiji Fem | CL42: 4 | CM42: 41 | CN42: Cuba Fem | CO42: 4 | CP42: 41 | CQ42: Australia Fem | CR42: 5 | CS42: 41
... B48: Rumania | C48: 3 | D48: 47 | E48: Chile Fem | F48: 3 | G48: 47 | H48: Tayikistan | I48: 4 | J48: 47 | K48: Afganistan Fem | L48: 5 | M48: 47 | N48: Macedonia del Norte | O48: 4 | P48: 47 | Q48: Hungria | R48: 3 | S48: 47 | T48: Laos | U48: 5 | V48: 47 | Y48: 47 | Z48: Liechtenstein | AA48: 5 | AB48: 47 | AC48: Grecia | AD48: 6 | AE48: 47 | AF48: Islas Caiman | AG48: 4 | AH48: 47 | AK48: 47 | AL48: Togo | AM48: 6 | AN48: 47 | AO48: Madagascar | AP48: 5 | AQ48: 47 | AT48: 47 | AU48: Guatemala | AV48: 4 | AW48: 47 | AX48: Uruguay | AY48: 4 | AZ48: 47 | BA48: Cuba | BB48: 5 | BC48: 47 | BD48: Iran Fem | BE48: 4 | BF48: 47 | BG48: Cuba Fem | BH48: 4 | BI48: 47 | BL48: 47 | BO48: 47 | BP48: Serbia Fem | BQ48: 6 | BR48: 47 | BS48: Liechtenstein Fem | BT48: 6 | BU48: 47 | BV48: Noruega Fem | BW48: 5 | BX48: 47 | CA48: 47 | CB48: Nigeria Fem | CC48: 6 | CD48: 47 | CE48: Kazajistan Fem | CF48: 6 | CG48: 47 | CJ48: 47 | CK48: Namibia Fem | CL48: 5 | CM48: 47 | CN48: Tailandia Fem | CO48: 4 | CP48: 47 | CQ48: Turkmenistan Fem | CR48: 6 | CS48: 47
B49: Venezuela | C49: 3 | D49: 48 | E49: Bielorrusia Fem | F49: 3 | G49: 48 | H49: Alemania | I49: 4 | J49: 48 | K49: Francia Fem | L49: 5 | M49: 48 | N49: Hungria | O49: 4 | P49: 48 | Q49: Cabo Verde | R49: 3 | S49: 48 | T49: Hungria | U49: 5 | V49: 48 | Y49: 48 | Z49: Qatar | AA49: 6 | AB49: 48 | AC49: Jordania | AD49: 6 | AE49: 48 | AF49: Croacia | AG49: 4 | AH49: 48 | AK49: 48 | AL49: Costa Rica | AM49: 6 | AN49: 48 | AO49: Grecia | AP49: 5 | AQ49: 48 | AT49: 48 | AU49: Hong Kong | AV49: 4 | AW49: 48 | AX49: Ecuador | AY49: 4 | AZ49: 48 | BA49: Emiratos Arabes Unidos | BB49: 5 | BC49: 48 | BD49: Azerbaijan Fem | BE49: 4 | BF49: 48 | BG49: El Salvador Fem | BH49: 4 | BI49: 48 | BL49: 48 | BO49: 48 | BR49: 48 | BU49: 48 | BV49: Singapur Fem | BW49: 5 | BX49: 48 | CA49: 48 | CB49: Panama Fem | CC49: 6 | CD49: 48 | CE49: Venezuela Fem | CF49: 6 | CG49: 48 | CJ49: 48 | CK49: Tonga Fem | CL49: 5 | CM49: 48 | CN49: Arabia Saudita Fem | CO49: 4 | CP49: 48 | CQ49: El Salvador Fem | CR49: 6 | CS49: 48
B50: Costa Rica | C50: 3 | D50: 49 | E50: Uzbekistan Fem | F50: 3 | G50: 49 | H50: Peru | I50: 4 | J50: 49 | K50: Irak Fem | L50: 5 | M50: 49 | N50: Curazao | O50: 4 | P50: 49 | Q50: Tunez | R50: 3 | S50: 49 | T50: Uganda | U50: 5 | V50: 49 | Y50: 49 | Z50: Jamaica | AA50: 6 | AB50: 49 | AE50: 49 | AF50: Trinidad y Tobago | AG50: 4 | AH50: 49 | AK50: 49 | AL50: Libano | AM50: 6 | AN50: 49 | AO50: Mexico | AP50: 5 | AQ50: 49 | AT50: 49 | AU50: Chipre | AV50: 4 | AW50: 49 | AX50: Armenia | AY50: 4 | AZ50: 49 | BA50: Nueva Zelanda | BB50: 5 | BC50: 49 | BD50: Santa Lucia Fem | BE50: 4 | BF50: 49 | BG50: Suiza Fem | BH50: 4 | BI50: 49 | BL50: 49 | BO50: 49 | BR50: 49 | BU50: 49 | BV50: Zambia Fem | BW50: 5 | BX50: 49 | CA50: 49 | CB50: Cuba Fem | CC50: 6 | CD50: 49 | CE50: Eslovenia Fem | CF50: 6 | CG50: 49 | CJ50: 49 | CK50: Pakistan Fem | CL50: 5 | CM50: 49 | CN50: Islandia Fem | CO50: 4 | CP50: 49 | CQ50: Indonesia Fem | CR50: 6 | CS50: 49
B51: Uzbekistan | C51: 3 | D51: 50 | E51: Haiti Fem | F51: 3 | G51: 50 | H51: Libia | I51: 4 | J51: 50 | K51: Noruega Fem | L51: 5 | M51: 50 | N51: Camerun | O51: 4 | P51: 50 | Q51: Nigeria | R51: 3 | S51: 50 | T51: Grecia | U51: 5 | V51: 50 | Y51: 50 | Z51: Nigeria | AA51: 6 | AB51: 50 | AE51: 50 | AF51: Uganda | AG51: 4 | AH51: 50 | AK51: 50 | AL51: Republica Dominicana | AM51: 6 | AN51: 50 | AO51: Tahiti | AP51: 5 | AQ51: 50 | AT51: 50 | AU51: Puerto Rico | AV51: 4 | AW51: 50 | AX51: Guinea | AY51: 4 | AZ51: 50 | BA51: Marruecos | BB51: 5 | BC51: 50 | BD51: Bermudas Fem | BE51: 4 | BF51: 50 | BG51: Costa de Marfil Fem | BH51: 4 | BI51: 50 | BL51: 50 | BO51: 50 | BR51: 50 | BU51: 50 | BV51: Guyana Fem | BW51: 5 | BX51: 50 | CA51: 50 | CB51: Burundi Fem | CC51: 6 | CD51: 50 | CE51: Islas Cook Fem | CF51: 6 | CG51: 50 | CJ51: 50 | CK51: Guatemala Fem | CL51: 5 | CM51: 50 | CN51: Venezuela Fem | CO51: 4 | CP51: 50 | CQ51: Filipinas Fem | CR51: 6 | CS51: 50
B52: Peru | C52: 3 | D52: 51 | E52: Eslovaquia Fem | F52: 3 | G52: 51 | H52: Australia | I52: 4 | J52: 51 | K52: Turkmenistan Fem | L52: 5 | M52: 51 | N52: Indonesia | O52: 4 | P52: 51 | Q52: Senegal | R52: 4 | S52: 51 | T52: Chile | U52: 5 | V52: 51 | Y52: 51 | Z52: Georgia | AA52: 6 | AB52: 51 | AE52: 51 | AF52: Malta | AG52: 4 | AH52: 51 | AK52: 51 | AL52: Benin | AM52: 6 | AN52: 51 | AO52: Costa de Marfil | AP52: 5 | AQ52: 51 | AT52: 51 | AU52: Uruguay | AV52: 4 | AW52: 51 | AX52: Republica Checa | AY52: 4 | AZ52: 51 | BA52: Austria | BB52: 5 | BC52: 51 | BD52: Barbados Fem | BE52: 4 | BF52: 51 | BG52: Angola Fem | BH52: 4 | BI52: 51 | BL52: 51 | BO52: 51 | BR52: 51 | BU52: 51 | BV52: Senegal Fem | BW52: 5 | BX52: 51 | CA52: 51 | CB52: San Cristobal y Nieves Fem | CC52: 6 | CD52: 51 | CE52: Tahiti Fem | CF52: 6 | CG52: 51 | CJ52: 51 | CK52: Eslovenia Fem | CL52: 5 | CM52: 51 | CN52: Suiza Fem | CO52: 4 | CP52: 51 | CQ52: Kuwait Fem | CR52: 6 | CS52: 51
B53: Chile | C53: 3 | D53: 52 | E53: Rumania Fem | F53: 3 | G53: 52 | H53: Letonia | I53: 4 | J53: 52 | K53: Eslovenia Fem | L53: 5 | M53: 52 | N53: Austria | O53: 4 | P53: 52 | Q53: Bahamas | R53: 4 | S53: 52 | T53: Ecuador | U53: 5 | V53: 52 | Y53: 52 | Z53: Israel | AA53: 6 | AB53: 52 | AE53: 52 | AF53: Ucrania | AG53: 4 | AH53: 52 | AK53: 52 | AL53: Namibia | AM53: 6 | AN53: 52 | AO53: Nueva Caledonia | AP53: 5 | AQ53: 52 | AT53: 52 | AU53: Islas Salomon | AV53: 4 | AW53: 52 | AX53: Kenia | AY53: 4 | AZ53: 52 | BA53: El Salvador | BB53: 5 | BC53: 52 | BD53: Nicaragua Fem | BE53: 4 | BF53: 52 | BG53: Israel Fem | BH53: 4 | BI53: 52 | BL53: 52 | BO53: 52 | BR53: 52 | BU53: 52 | BV53: Zimbaue Fem | BW53: 5 | BX53: 52 | CA53: 52 | CB53: Libano Fem | CC53: 6 | CD53: 52 | CE53: Mexico Fem | CF53: 6 | CG53: 52 | CJ53: 52 | CK53: Peru Fem | CL53: 5 | CM53: 52 | CN53: Serbia Fem | CO53: 4 | CP53: 52 | CQ53: Marruecos Fem | CR53: 6 | CS53: 52
B54: Mali | C54: 3 | D54: 53 | E54: Tailandia Fem | F54: 3 | G54: 53 | H54: Azerbaijan | I54: 4 | J54: 53 | K54: Serbia Fem | L54: 5 | M54: 53 | N54: Taiwan | O54: 4 | P54: 53 | Q54: Paises Bajos | R54: 4 | S54: 53 | T54: Sri Lanka | U54: 5 | V54: 53 | Y54: 53 | Z54: Lituania | AA54: 6 | AB54: 53 | AE54: 53 | AF54: Filipinas | AG54: 4 | AH54: 53 | AK54: 53 | AL54: Belice | AM54: 6 | AN54: 53 | AO54: Colombia | AP54: 5 | AQ54: 53 | AT54: 53 | AU54: Tailandia | AV54: 4 | AW54: 53 | AX54: Filipinas | AY54: 5 | AZ54: 53 | BA54: Peru | BB54: 5 | BC54: 53 | BD54: San Marino Fem | BE54: 4 | BF54: 53 | BG54: Uganda Fem | BH54: 4 | BI54: 53 | BL54: 53 | BO54: 53 | BR54: 53 | BU54: 53 | BV54: Bosnia y Herzegovina Fem | BW54: 5 | BX54: 53 | CA54: 53 | CD54: 53 | CE54: Camerun Fem | CF54: 6 | CG54: 53 | CJ54: 53 | CK54: Bolivia Fem | CL54: 5 | CM54: 53 | CN54: Uruguay Fem | CO54: 5 | CP54: 53 | CQ54: Grecia Fem | CR54: 6 | CS54: 53
